Workbook

Sheet Cover
B2: ISO37101 assessment
B4: If needed, see the "HowTo" tab for next actions
B6: Content | C6: Review of Aarhus Activities | F6: Summary table: | G6: The following table summarizes the finding of this assessment.
B8: WP | C8: Aarhus | F8: Average Score | G8: Attractiveness | I8: Environment | K8: Resilience | M8: Resources | O8: Cohesion | Q8: Well Being | U8: Review | V8: Content
B9: LL | C9: Content from Activities elements. | G9: Bld. | H9: Neig. | I9: Bld. | J9: Neig. | K9: Bld. | L9: Neig. | M9: Bld. | N9: Neig. | O9: Bld. | P9: Neig. | Q9: Bld. | R9: Neig. | U9: 1ae03038ed69 | V9: VisBlue flow batteries
B10: Date | C10: July 02, 2024 - 09:47PM | F10: =LEFT(Definitions!B12,25)&"…" -> Governance, empowerment a… | G10: =IFERROR(AVERAGE('1ae03038ed69'!C39,'1572eb063e5c'!C39,b6ea66d78823!C39,'6d8dcb722ca4'!C39,'9306b30af184'!C39,'3b760aaeab13'!C39,b2f4402deaee!C39,'1c4d314e87cd'!C39,acd4708edfe6!C39,'9a32b1f50fb5'!C39,'2df562aa32e7'!C39,'3a5a3c04bd9d'!C39,'192241189337'!C39,'23a0423d7f40'!C39,'096252bb3796'!C39,a53d1c7f9645!C39,'283d32631463'!C39,'1a542cfbf2c5'!C39,cf262786a0e1!C39,'4b9efdeaeb40'!C39,'66fab14edc4c'!C39,d9a84a7879b5!C39,caf2b28627a3!C39,'602e9d1875d1'!C39,f168037f7f37!C39,eb071de1ab08!C39,'7b3bd85715a4'!C39,e2a9b537c609!C39,f97457958ce9!C39,'281fcc7d7eae'!C39,'01454b1cfeba'!C39,'79287892b1d7'!C39,'1b3f96535b56'!C39),"") -> 4 | H10: =IFERROR(AVERAGE('1ae03038ed69'!D39,'1572eb063e5c'!D39,b6ea66d78823!D39,'6d8dcb722ca4'!D39,'9306b30af184'!D39,'3b760aaeab13'!D39,b2f4402deaee!D39,'1c4d314e87cd'!D39,acd4708edfe6!D39,'9a32b1f50fb5'!D39,'2df562aa32e7'!D39,'3a5a3c04bd9d'!D39,'192241189337'!D39,'23a0423d7f40'!D39,'096252bb3796'!D39,a53d1c7f9645!D39,'283d32631463'!D39,'1a542cfbf2c5'!D39,cf262786a0e1!D39,'4b9efdeaeb40'!D39,'66fab14edc4c'!D39,d9a84a7879b5!D39,caf2b28627a3!D39,'602e9d1875d1'!D39,f168037f7f37!D39,eb071de1ab08!D39,'7b3bd85715a4'!D39,e2a9b537c609!D39,f97457958ce9!D39,'281fcc7d7eae'!D39,'01454b1cfeba'!D39,'79287892b1d7'!D39,'1b3f96535b56'!D39),"") -> 4.5 | I10: =IFERROR(AVERAGE('1ae03038ed69'!E39,'1572eb063e5c'!E39,b6ea66d78823!E39,'6d8dcb722ca4'!E39,'9306b30af184'!E39,'3b760aaeab13'!E39,b2f4402deaee!E39,'1c4d314e87cd'!E39,acd4708edfe6!E39,'9a32b1f50fb5'!E39,'2df562aa32e7'!E39,'3a5a3c04bd9d'!E39,'192241189337'!E39,'23a0423d7f40'!E39,'096252bb3796'!E39,a53d1c7f9645!E39,'283d32631463'!E39,'1a542cfbf2c5'!E39,cf262786a0e1!E39,'4b9efdeaeb40'!E39,'66fab14edc4c'!E39,d9a84a7879b5!E39,caf2b28627a3!E39,'602e9d1875d1'!E39,f168037f7f37!E39,eb071de1ab08!E39,'7b3bd85715a4'!E39,e2a9b537c609!E39,f97457958ce9!E39,'281fcc7d7eae'!E39,'01454b1cfeba'!E39,'79287892b1d7'!E39,'1b3f96535b56'!E39),"") -> 4 | J10: =IFERROR(AVERAGE('1ae03038ed69'!F39,'1572eb063e5c'!F39,b6ea66d78823!F39,'6d8dcb722ca4'!F39,'9306b30af184'!F39,'3b760aaeab13'!F39,b2f4402deaee!F39,'1c4d314e87cd'!F39,acd4708edfe6!F39,'9a32b1f50fb5'!F39,'2df562aa32e7'!F39,'3a5a3c04bd9d'!F39,'192241189337'!F39,'23a0423d7f40'!F39,'096252bb3796'!F39,a53d1c7f9645!F39,'283d32631463'!F39,'1a542cfbf2c5'!F39,cf262786a0e1!F39,'4b9efdeaeb40'!F39,'66fab14edc4c'!F39,d9a84a7879b5!F39,caf2b28627a3!F39,'602e9d1875d1'!F39,f168037f7f37!F39,eb071de1ab08!F39,'7b3bd85715a4'!F39,e2a9b537c609!F39,f97457958ce9!F39,'281fcc7d7eae'!F39,'01454b1cfeba'!F39,'79287892b1d7'!F39,'1b3f96535b56'!F39),"") -> 4 | K10: =IFERROR(AVERAGE('1ae03038ed69'!G39,'1572eb063e5c'!G39,b6ea66d78823!G39,'6d8dcb722ca4'!G39,'9306b30af184'!G39,'3b760aaeab13'!G39,b2f4402deaee!G39,'1c4d314e87cd'!G39,acd4708edfe6!G39,'9a32b1f50fb5'!G39,'2df562aa32e7'!G39,'3a5a3c04bd9d'!G39,'192241189337'!G39,'23a0423d7f40'!G39,'096252bb3796'!G39,a53d1c7f9645!G39,'283d32631463'!G39,'1a542cfbf2c5'!G39,cf262786a0e1!G39,'4b9efdeaeb40'!G39,'66fab14edc4c'!G39,d9a84a7879b5!G39,caf2b28627a3!G39,'602e9d1875d1'!G39,f168037f7f37!G39,eb071de1ab08!G39,'7b3bd85715a4'!G39,e2a9b537c609!G39,f97457958ce9!G39,'281fcc7d7eae'!G39,'01454b1cfeba'!G39,'79287892b1d7'!G39,'1b3f96535b56'!G39),"") | L10: =IFERROR(AVERAGE('1ae03038ed69'!H39,'1572eb063e5c'!H39,b6ea66d78823!H39,'6d8dcb722ca4'!H39,'9306b30af184'!H39,'3b760aaeab13'!H39,b2f4402deaee!H39,'1c4d314e87cd'!H39,acd4708edfe6!H39,'9a32b1f50fb5'!H39,'2df562aa32e7'!H39,'3a5a3c04bd9d'!H39,'192241189337'!H39,'23a0423d7f40'!H39,'096252bb3796'!H39,a53d1c7f9645!H39,'283d32631463'!H39,'1a542cfbf2c5'!H39,cf262786a0e1!H39,'4b9efdeaeb40'!H39,'66fab14edc4c'!H39,d9a84a7879b5!H39,caf2b28627a3!H39,'602e9d1875d1'!H39,f168037f7f37!H39,eb071de1ab08!H39,'7b3bd85715a4'!H39,e2a9b537c609!H39,f97457958ce9!H39,'281fcc7d7eae'!H39,'01454b1cfeba'!H39,'79287892b1d7'!H39,'1b3f96535b56'!H39),"") -> 4 | M10: =IFERROR(AVERAGE('1ae03038ed69'!I39,'1572eb063e5c'!I39,b6ea66d78823!I39,'6d8dcb722ca4'!I39,'9306b30af184'!I39,'3b760aaeab13'!I39,b2f4402deaee!I39,'1c4d314e87cd'!I39,acd4708edfe6!I39,'9a32b1f50fb5'!I39,'2df562aa32e7'!I39,'3a5a3c04bd9d'!I39,'192241189337'!I39,'23a0423d7f40'!I39,'096252bb3796'!I39,a53d1c7f9645!I39,'283d32631463'!I39,'1a542cfbf2c5'!I39,cf262786a0e1!I39,'4b9efdeaeb40'!I39,'66fab14edc4c'!I39,d9a84a7879b5!I39,caf2b28627a3!I39,'602e9d1875d1'!I39,f168037f7f37!I39,eb071de1ab08!I39,'7b3bd85715a4'!I39,e2a9b537c609!I39,f97457958ce9!I39,'281fcc7d7eae'!I39,'01454b1cfeba'!I39,'79287892b1d7'!I39,'1b3f96535b56'!I39),"") -> 5 | N10: =IFERROR(AVERAGE('1ae03038ed69'!J39,'1572eb063e5c'!J39,b6ea66d78823!J39,'6d8dcb722ca4'!J39,'9306b30af184'!J39,'3b760aaeab13'!J39,b2f4402deaee!J39,'1c4d314e87cd'!J39,acd4708edfe6!J39,'9a32b1f50fb5'!J39,'2df562aa32e7'!J39,'3a5a3c04bd9d'!J39,'192241189337'!J39,'23a0423d7f40'!J39,'096252bb3796'!J39,a53d1c7f9645!J39,'283d32631463'!J39,'1a542cfbf2c5'!J39,cf262786a0e1!J39,'4b9efdeaeb40'!J39,'66fab14edc4c'!J39,d9a84a7879b5!J39,caf2b28627a3!J39,'602e9d1875d1'!J39,f168037f7f37!J39,eb071de1ab08!J39,'7b3bd85715a4'!J39,e2a9b537c609!J39,f97457958ce9!J39,'281fcc7d7eae'!J39,'01454b1cfeba'!J39,'79287892b1d7'!J39,'1b3f96535b56'!J39),"") -> 5 | ... R10: =IFERROR(AVERAGE('1ae03038ed69'!N39,'1572eb063e5c'!N39,b6ea66d78823!N39,'6d8dcb722ca4'!N39,'9306b30af184'!N39,'3b760aaeab13'!N39,b2f4402deaee!N39,'1c4d314e87cd'!N39,acd4708edfe6!N39,'9a32b1f50fb5'!N39,'2df562aa32e7'!N39,'3a5a3c04bd9d'!N39,'192241189337'!N39,'23a0423d7f40'!N39,'096252bb3796'!N39,a53d1c7f9645!N39,'283d32631463'!N39,'1a542cfbf2c5'!N39,cf262786a0e1!N39,'4b9efdeaeb40'!N39,'66fab14edc4c'!N39,d9a84a7879b5!N39,caf2b28627a3!N39,'602e9d1875d1'!N39,f168037f7f37!N39,eb071de1ab08!N39,'7b3bd85715a4'!N39,e2a9b537c609!N39,f97457958ce9!N39,'281fcc7d7eae'!N39,'01454b1cfeba'!N39,'79287892b1d7'!N39,'1b3f96535b56'!N39),"") | U10: 1572eb063e5c | V10: COWI upcycling
F11: =LEFT(Definitions!B13,25)&"…" -> Education and capacity bu… | G11: =IFERROR(AVERAGE('1ae03038ed69'!C40,'1572eb063e5c'!C40,b6ea66d78823!C40,'6d8dcb722ca4'!C40,'9306b30af184'!C40,'3b760aaeab13'!C40,b2f4402deaee!C40,'1c4d314e87cd'!C40,acd4708edfe6!C40,'9a32b1f50fb5'!C40,'2df562aa32e7'!C40,'3a5a3c04bd9d'!C40,'192241189337'!C40,'23a0423d7f40'!C40,'096252bb3796'!C40,a53d1c7f9645!C40,'283d32631463'!C40,'1a542cfbf2c5'!C40,cf262786a0e1!C40,'4b9efdeaeb40'!C40,'66fab14edc4c'!C40,d9a84a7879b5!C40,caf2b28627a3!C40,'602e9d1875d1'!C40,f168037f7f37!C40,eb071de1ab08!C40,'7b3bd85715a4'!C40,e2a9b537c609!C40,f97457958ce9!C40,'281fcc7d7eae'!C40,'01454b1cfeba'!C40,'79287892b1d7'!C40,'1b3f96535b56'!C40),"") | H11: =IFERROR(AVERAGE('1ae03038ed69'!D40,'1572eb063e5c'!D40,b6ea66d78823!D40,'6d8dcb722ca4'!D40,'9306b30af184'!D40,'3b760aaeab13'!D40,b2f4402deaee!D40,'1c4d314e87cd'!D40,acd4708edfe6!D40,'9a32b1f50fb5'!D40,'2df562aa32e7'!D40,'3a5a3c04bd9d'!D40,'192241189337'!D40,'23a0423d7f40'!D40,'096252bb3796'!D40,a53d1c7f9645!D40,'283d32631463'!D40,'1a542cfbf2c5'!D40,cf262786a0e1!D40,'4b9efdeaeb40'!D40,'66fab14edc4c'!D40,d9a84a7879b5!D40,caf2b28627a3!D40,'602e9d1875d1'!D40,f168037f7f37!D40,eb071de1ab08!D40,'7b3bd85715a4'!D40,e2a9b537c609!D40,f97457958ce9!D40,'281fcc7d7eae'!D40,'01454b1cfeba'!D40,'79287892b1d7'!D40,'1b3f96535b56'!D40),"") | I11: =IFERROR(AVERAGE('1ae03038ed69'!E40,'1572eb063e5c'!E40,b6ea66d78823!E40,'6d8dcb722ca4'!E40,'9306b30af184'!E40,'3b760aaeab13'!E40,b2f4402deaee!E40,'1c4d314e87cd'!E40,acd4708edfe6!E40,'9a32b1f50fb5'!E40,'2df562aa32e7'!E40,'3a5a3c04bd9d'!E40,'192241189337'!E40,'23a0423d7f40'!E40,'096252bb3796'!E40,a53d1c7f9645!E40,'283d32631463'!E40,'1a542cfbf2c5'!E40,cf262786a0e1!E40,'4b9efdeaeb40'!E40,'66fab14edc4c'!E40,d9a84a7879b5!E40,caf2b28627a3!E40,'602e9d1875d1'!E40,f168037f7f37!E40,eb071de1ab08!E40,'7b3bd85715a4'!E40,e2a9b537c609!E40,f97457958ce9!E40,'281fcc7d7eae'!E40,'01454b1cfeba'!E40,'79287892b1d7'!E40,'1b3f96535b56'!E40),"") -> 4 | J11: =IFERROR(AVERAGE('1ae03038ed69'!F40,'1572eb063e5c'!F40,b6ea66d78823!F40,'6d8dcb722ca4'!F40,'9306b30af184'!F40,'3b760aaeab13'!F40,b2f4402deaee!F40,'1c4d314e87cd'!F40,acd4708edfe6!F40,'9a32b1f50fb5'!F40,'2df562aa32e7'!F40,'3a5a3c04bd9d'!F40,'192241189337'!F40,'23a0423d7f40'!F40,'096252bb3796'!F40,a53d1c7f9645!F40,'283d32631463'!F40,'1a542cfbf2c5'!F40,cf262786a0e1!F40,'4b9efdeaeb40'!F40,'66fab14edc4c'!F40,d9a84a7879b5!F40,caf2b28627a3!F40,'602e9d1875d1'!F40,f168037f7f37!F40,eb071de1ab08!F40,'7b3bd85715a4'!F40,e2a9b537c609!F40,f97457958ce9!F40,'281fcc7d7eae'!F40,'01454b1cfeba'!F40,'79287892b1d7'!F40,'1b3f96535b56'!F40),"") -> 4.3333333 | K11: =IFERROR(AVERAGE('1ae03038ed69'!G40,'1572eb063e5c'!G40,b6ea66d78823!G40,'6d8dcb722ca4'!G40,'9306b30af184'!G40,'3b760aaeab13'!G40,b2f4402deaee!G40,'1c4d314e87cd'!G40,acd4708edfe6!G40,'9a32b1f50fb5'!G40,'2df562aa32e7'!G40,'3a5a3c04bd9d'!G40,'192241189337'!G40,'23a0423d7f40'!G40,'096252bb3796'!G40,a53d1c7f9645!G40,'283d32631463'!G40,'1a542cfbf2c5'!G40,cf262786a0e1!G40,'4b9efdeaeb40'!G40,'66fab14edc4c'!G40,d9a84a7879b5!G40,caf2b28627a3!G40,'602e9d1875d1'!G40,f168037f7f37!G40,eb071de1ab08!G40,'7b3bd85715a4'!G40,e2a9b537c609!G40,f97457958ce9!G40,'281fcc7d7eae'!G40,'01454b1cfeba'!G40,'79287892b1d7'!G40,'1b3f96535b56'!G40),"") | L11: =IFERROR(AVERAGE('1ae03038ed69'!H40,'1572eb063e5c'!H40,b6ea66d78823!H40,'6d8dcb722ca4'!H40,'9306b30af184'!H40,'3b760aaeab13'!H40,b2f4402deaee!H40,'1c4d314e87cd'!H40,acd4708edfe6!H40,'9a32b1f50fb5'!H40,'2df562aa32e7'!H40,'3a5a3c04bd9d'!H40,'192241189337'!H40,'23a0423d7f40'!H40,'096252bb3796'!H40,a53d1c7f9645!H40,'283d32631463'!H40,'1a542cfbf2c5'!H40,cf262786a0e1!H40,'4b9efdeaeb40'!H40,'66fab14edc4c'!H40,d9a84a7879b5!H40,caf2b28627a3!H40,'602e9d1875d1'!H40,f168037f7f37!H40,eb071de1ab08!H40,'7b3bd85715a4'!H40,e2a9b537c609!H40,f97457958ce9!H40,'281fcc7d7eae'!H40,'01454b1cfeba'!H40,'79287892b1d7'!H40,'1b3f96535b56'!H40),"") | M11: =IFERROR(AVERAGE('1ae03038ed69'!I40,'1572eb063e5c'!I40,b6ea66d78823!I40,'6d8dcb722ca4'!I40,'9306b30af184'!I40,'3b760aaeab13'!I40,b2f4402deaee!I40,'1c4d314e87cd'!I40,acd4708edfe6!I40,'9a32b1f50fb5'!I40,'2df562aa32e7'!I40,'3a5a3c04bd9d'!I40,'192241189337'!I40,'23a0423d7f40'!I40,'096252bb3796'!I40,a53d1c7f9645!I40,'283d32631463'!I40,'1a542cfbf2c5'!I40,cf262786a0e1!I40,'4b9efdeaeb40'!I40,'66fab14edc4c'!I40,d9a84a7879b5!I40,caf2b28627a3!I40,'602e9d1875d1'!I40,f168037f7f37!I40,eb071de1ab08!I40,'7b3bd85715a4'!I40,e2a9b537c609!I40,f97457958ce9!I40,'281fcc7d7eae'!I40,'01454b1cfeba'!I40,'79287892b1d7'!I40,'1b3f96535b56'!I40),"") | N11: =IFERROR(AVERAGE('1ae03038ed69'!J40,'1572eb063e5c'!J40,b6ea66d78823!J40,'6d8dcb722ca4'!J40,'9306b30af184'!J40,'3b760aaeab13'!J40,b2f4402deaee!J40,'1c4d314e87cd'!J40,acd4708edfe6!J40,'9a32b1f50fb5'!J40,'2df562aa32e7'!J40,'3a5a3c04bd9d'!J40,'192241189337'!J40,'23a0423d7f40'!J40,'096252bb3796'!J40,a53d1c7f9645!J40,'283d32631463'!J40,'1a542cfbf2c5'!J40,cf262786a0e1!J40,'4b9efdeaeb40'!J40,'66fab14edc4c'!J40,d9a84a7879b5!J40,caf2b28627a3!J40,'602e9d1875d1'!J40,f168037f7f37!J40,eb071de1ab08!J40,'7b3bd85715a4'!J40,e2a9b537c609!J40,f97457958ce9!J40,'281fcc7d7eae'!J40,'01454b1cfeba'!J40,'79287892b1d7'!J40,'1b3f96535b56'!J40),"") | ... R11: =IFERROR(AVERAGE('1ae03038ed69'!N40,'1572eb063e5c'!N40,b6ea66d78823!N40,'6d8dcb722ca4'!N40,'9306b30af184'!N40,'3b760aaeab13'!N40,b2f4402deaee!N40,'1c4d314e87cd'!N40,acd4708edfe6!N40,'9a32b1f50fb5'!N40,'2df562aa32e7'!N40,'3a5a3c04bd9d'!N40,'192241189337'!N40,'23a0423d7f40'!N40,'096252bb3796'!N40,a53d1c7f9645!N40,'283d32631463'!N40,'1a542cfbf2c5'!N40,cf262786a0e1!N40,'4b9efdeaeb40'!N40,'66fab14edc4c'!N40,d9a84a7879b5!N40,caf2b28627a3!N40,'602e9d1875d1'!N40,f168037f7f37!N40,eb071de1ab08!N40,'7b3bd85715a4'!N40,e2a9b537c609!N40,f97457958ce9!N40,'281fcc7d7eae'!N40,'01454b1cfeba'!N40,'79287892b1d7'!N40,'1b3f96535b56'!N40),"") | U11: b6ea66d78823 | V11: Geodesign workshop for AU Viborg.
B12: Author(s) | C12: Automated | F12: =LEFT(Definitions!B14,25)&"…" -> Innovation, creativity an… | G12: =IFERROR(AVERAGE('1ae03038ed69'!C41,'1572eb063e5c'!C41,b6ea66d78823!C41,'6d8dcb722ca4'!C41,'9306b30af184'!C41,'3b760aaeab13'!C41,b2f4402deaee!C41,'1c4d314e87cd'!C41,acd4708edfe6!C41,'9a32b1f50fb5'!C41,'2df562aa32e7'!C41,'3a5a3c04bd9d'!C41,'192241189337'!C41,'23a0423d7f40'!C41,'096252bb3796'!C41,a53d1c7f9645!C41,'283d32631463'!C41,'1a542cfbf2c5'!C41,cf262786a0e1!C41,'4b9efdeaeb40'!C41,'66fab14edc4c'!C41,d9a84a7879b5!C41,caf2b28627a3!C41,'602e9d1875d1'!C41,f168037f7f37!C41,eb071de1ab08!C41,'7b3bd85715a4'!C41,e2a9b537c609!C41,f97457958ce9!C41,'281fcc7d7eae'!C41,'01454b1cfeba'!C41,'79287892b1d7'!C41,'1b3f96535b56'!C41),"") -> 5 | H12: =IFERROR(AVERAGE('1ae03038ed69'!D41,'1572eb063e5c'!D41,b6ea66d78823!D41,'6d8dcb722ca4'!D41,'9306b30af184'!D41,'3b760aaeab13'!D41,b2f4402deaee!D41,'1c4d314e87cd'!D41,acd4708edfe6!D41,'9a32b1f50fb5'!D41,'2df562aa32e7'!D41,'3a5a3c04bd9d'!D41,'192241189337'!D41,'23a0423d7f40'!D41,'096252bb3796'!D41,a53d1c7f9645!D41,'283d32631463'!D41,'1a542cfbf2c5'!D41,cf262786a0e1!D41,'4b9efdeaeb40'!D41,'66fab14edc4c'!D41,d9a84a7879b5!D41,caf2b28627a3!D41,'602e9d1875d1'!D41,f168037f7f37!D41,eb071de1ab08!D41,'7b3bd85715a4'!D41,e2a9b537c609!D41,f97457958ce9!D41,'281fcc7d7eae'!D41,'01454b1cfeba'!D41,'79287892b1d7'!D41,'1b3f96535b56'!D41),"") -> 3 | I12: =IFERROR(AVERAGE('1ae03038ed69'!E41,'1572eb063e5c'!E41,b6ea66d78823!E41,'6d8dcb722ca4'!E41,'9306b30af184'!E41,'3b760aaeab13'!E41,b2f4402deaee!E41,'1c4d314e87cd'!E41,acd4708edfe6!E41,'9a32b1f50fb5'!E41,'2df562aa32e7'!E41,'3a5a3c04bd9d'!E41,'192241189337'!E41,'23a0423d7f40'!E41,'096252bb3796'!E41,a53d1c7f9645!E41,'283d32631463'!E41,'1a542cfbf2c5'!E41,cf262786a0e1!E41,'4b9efdeaeb40'!E41,'66fab14edc4c'!E41,d9a84a7879b5!E41,caf2b28627a3!E41,'602e9d1875d1'!E41,f168037f7f37!E41,eb071de1ab08!E41,'7b3bd85715a4'!E41,e2a9b537c609!E41,f97457958ce9!E41,'281fcc7d7eae'!E41,'01454b1cfeba'!E41,'79287892b1d7'!E41,'1b3f96535b56'!E41),"") -> 4.5 | J12: =IFERROR(AVERAGE('1ae03038ed69'!F41,'1572eb063e5c'!F41,b6ea66d78823!F41,'6d8dcb722ca4'!F41,'9306b30af184'!F41,'3b760aaeab13'!F41,b2f4402deaee!F41,'1c4d314e87cd'!F41,acd4708edfe6!F41,'9a32b1f50fb5'!F41,'2df562aa32e7'!F41,'3a5a3c04bd9d'!F41,'192241189337'!F41,'23a0423d7f40'!F41,'096252bb3796'!F41,a53d1c7f9645!F41,'283d32631463'!F41,'1a542cfbf2c5'!F41,cf262786a0e1!F41,'4b9efdeaeb40'!F41,'66fab14edc4c'!F41,d9a84a7879b5!F41,caf2b28627a3!F41,'602e9d1875d1'!F41,f168037f7f37!F41,eb071de1ab08!F41,'7b3bd85715a4'!F41,e2a9b537c609!F41,f97457958ce9!F41,'281fcc7d7eae'!F41,'01454b1cfeba'!F41,'79287892b1d7'!F41,'1b3f96535b56'!F41),"") -> 3.8333333 | K12: =IFERROR(AVERAGE('1ae03038ed69'!G41,'1572eb063e5c'!G41,b6ea66d78823!G41,'6d8dcb722ca4'!G41,'9306b30af184'!G41,'3b760aaeab13'!G41,b2f4402deaee!G41,'1c4d314e87cd'!G41,acd4708edfe6!G41,'9a32b1f50fb5'!G41,'2df562aa32e7'!G41,'3a5a3c04bd9d'!G41,'192241189337'!G41,'23a0423d7f40'!G41,'096252bb3796'!G41,a53d1c7f9645!G41,'283d32631463'!G41,'1a542cfbf2c5'!G41,cf262786a0e1!G41,'4b9efdeaeb40'!G41,'66fab14edc4c'!G41,d9a84a7879b5!G41,caf2b28627a3!G41,'602e9d1875d1'!G41,f168037f7f37!G41,eb071de1ab08!G41,'7b3bd85715a4'!G41,e2a9b537c609!G41,f97457958ce9!G41,'281fcc7d7eae'!G41,'01454b1cfeba'!G41,'79287892b1d7'!G41,'1b3f96535b56'!G41),"") -> 3.875 | L12: =IFERROR(AVERAGE('1ae03038ed69'!H41,'1572eb063e5c'!H41,b6ea66d78823!H41,'6d8dcb722ca4'!H41,'9306b30af184'!H41,'3b760aaeab13'!H41,b2f4402deaee!H41,'1c4d314e87cd'!H41,acd4708edfe6!H41,'9a32b1f50fb5'!H41,'2df562aa32e7'!H41,'3a5a3c04bd9d'!H41,'192241189337'!H41,'23a0423d7f40'!H41,'096252bb3796'!H41,a53d1c7f9645!H41,'283d32631463'!H41,'1a542cfbf2c5'!H41,cf262786a0e1!H41,'4b9efdeaeb40'!H41,'66fab14edc4c'!H41,d9a84a7879b5!H41,caf2b28627a3!H41,'602e9d1875d1'!H41,f168037f7f37!H41,eb071de1ab08!H41,'7b3bd85715a4'!H41,e2a9b537c609!H41,f97457958ce9!H41,'281fcc7d7eae'!H41,'01454b1cfeba'!H41,'79287892b1d7'!H41,'1b3f96535b56'!H41),"") -> 3.25 | M12: =IFERROR(AVERAGE('1ae03038ed69'!I41,'1572eb063e5c'!I41,b6ea66d78823!I41,'6d8dcb722ca4'!I41,'9306b30af184'!I41,'3b760aaeab13'!I41,b2f4402deaee!I41,'1c4d314e87cd'!I41,acd4708edfe6!I41,'9a32b1f50fb5'!I41,'2df562aa32e7'!I41,'3a5a3c04bd9d'!I41,'192241189337'!I41,'23a0423d7f40'!I41,'096252bb3796'!I41,a53d1c7f9645!I41,'283d32631463'!I41,'1a542cfbf2c5'!I41,cf262786a0e1!I41,'4b9efdeaeb40'!I41,'66fab14edc4c'!I41,d9a84a7879b5!I41,caf2b28627a3!I41,'602e9d1875d1'!I41,f168037f7f37!I41,eb071de1ab08!I41,'7b3bd85715a4'!I41,e2a9b537c609!I41,f97457958ce9!I41,'281fcc7d7eae'!I41,'01454b1cfeba'!I41,'79287892b1d7'!I41,'1b3f96535b56'!I41),"") -> 4 | N12: =IFERROR(AVERAGE('1ae03038ed69'!J41,'1572eb063e5c'!J41,b6ea66d78823!J41,'6d8dcb722ca4'!J41,'9306b30af184'!J41,'3b760aaeab13'!J41,b2f4402deaee!J41,'1c4d314e87cd'!J41,acd4708edfe6!J41,'9a32b1f50fb5'!J41,'2df562aa32e7'!J41,'3a5a3c04bd9d'!J41,'192241189337'!J41,'23a0423d7f40'!J41,'096252bb3796'!J41,a53d1c7f9645!J41,'283d32631463'!J41,'1a542cfbf2c5'!J41,cf262786a0e1!J41,'4b9efdeaeb40'!J41,'66fab14edc4c'!J41,d9a84a7879b5!J41,caf2b28627a3!J41,'602e9d1875d1'!J41,f168037f7f37!J41,eb071de1ab08!J41,'7b3bd85715a4'!J41,e2a9b537c609!J41,f97457958ce9!J41,'281fcc7d7eae'!J41,'01454b1cfeba'!J41,'79287892b1d7'!J41,'1b3f96535b56'!J41),"") -> 4 | ... R12: =IFERROR(AVERAGE('1ae03038ed69'!N41,'1572eb063e5c'!N41,b6ea66d78823!N41,'6d8dcb722ca4'!N41,'9306b30af184'!N41,'3b760aaeab13'!N41,b2f4402deaee!N41,'1c4d314e87cd'!N41,acd4708edfe6!N41,'9a32b1f50fb5'!N41,'2df562aa32e7'!N41,'3a5a3c04bd9d'!N41,'192241189337'!N41,'23a0423d7f40'!N41,'096252bb3796'!N41,a53d1c7f9645!N41,'283d32631463'!N41,'1a542cfbf2c5'!N41,cf262786a0e1!N41,'4b9efdeaeb40'!N41,'66fab14edc4c'!N41,d9a84a7879b5!N41,caf2b28627a3!N41,'602e9d1875d1'!N41,f168037f7f37!N41,eb071de1ab08!N41,'7b3bd85715a4'!N41,e2a9b537c609!N41,f97457958ce9!N41,'281fcc7d7eae'!N41,'01454b1cfeba'!N41,'79287892b1d7'!N41,'1b3f96535b56'!N41),"") | U12: 6d8dcb722ca4 | V12: Automated DGNB assessment tool for architects.
F13: =LEFT(Definitions!B15,25)&"…" -> Health and care in the co… | G13: =IFERROR(AVERAGE('1ae03038ed69'!C42,'1572eb063e5c'!C42,b6ea66d78823!C42,'6d8dcb722ca4'!C42,'9306b30af184'!C42,'3b760aaeab13'!C42,b2f4402deaee!C42,'1c4d314e87cd'!C42,acd4708edfe6!C42,'9a32b1f50fb5'!C42,'2df562aa32e7'!C42,'3a5a3c04bd9d'!C42,'192241189337'!C42,'23a0423d7f40'!C42,'096252bb3796'!C42,a53d1c7f9645!C42,'283d32631463'!C42,'1a542cfbf2c5'!C42,cf262786a0e1!C42,'4b9efdeaeb40'!C42,'66fab14edc4c'!C42,d9a84a7879b5!C42,caf2b28627a3!C42,'602e9d1875d1'!C42,f168037f7f37!C42,eb071de1ab08!C42,'7b3bd85715a4'!C42,e2a9b537c609!C42,f97457958ce9!C42,'281fcc7d7eae'!C42,'01454b1cfeba'!C42,'79287892b1d7'!C42,'1b3f96535b56'!C42),"") -> 3 | H13: =IFERROR(AVERAGE('1ae03038ed69'!D42,'1572eb063e5c'!D42,b6ea66d78823!D42,'6d8dcb722ca4'!D42,'9306b30af184'!D42,'3b760aaeab13'!D42,b2f4402deaee!D42,'1c4d314e87cd'!D42,acd4708edfe6!D42,'9a32b1f50fb5'!D42,'2df562aa32e7'!D42,'3a5a3c04bd9d'!D42,'192241189337'!D42,'23a0423d7f40'!D42,'096252bb3796'!D42,a53d1c7f9645!D42,'283d32631463'!D42,'1a542cfbf2c5'!D42,cf262786a0e1!D42,'4b9efdeaeb40'!D42,'66fab14edc4c'!D42,d9a84a7879b5!D42,caf2b28627a3!D42,'602e9d1875d1'!D42,f168037f7f37!D42,eb071de1ab08!D42,'7b3bd85715a4'!D42,e2a9b537c609!D42,f97457958ce9!D42,'281fcc7d7eae'!D42,'01454b1cfeba'!D42,'79287892b1d7'!D42,'1b3f96535b56'!D42),"") -> 2.5 | I13: =IFERROR(AVERAGE('1ae03038ed69'!E42,'1572eb063e5c'!E42,b6ea66d78823!E42,'6d8dcb722ca4'!E42,'9306b30af184'!E42,'3b760aaeab13'!E42,b2f4402deaee!E42,'1c4d314e87cd'!E42,acd4708edfe6!E42,'9a32b1f50fb5'!E42,'2df562aa32e7'!E42,'3a5a3c04bd9d'!E42,'192241189337'!E42,'23a0423d7f40'!E42,'096252bb3796'!E42,a53d1c7f9645!E42,'283d32631463'!E42,'1a542cfbf2c5'!E42,cf262786a0e1!E42,'4b9efdeaeb40'!E42,'66fab14edc4c'!E42,d9a84a7879b5!E42,caf2b28627a3!E42,'602e9d1875d1'!E42,f168037f7f37!E42,eb071de1ab08!E42,'7b3bd85715a4'!E42,e2a9b537c609!E42,f97457958ce9!E42,'281fcc7d7eae'!E42,'01454b1cfeba'!E42,'79287892b1d7'!E42,'1b3f96535b56'!E42),"") | J13: =IFERROR(AVERAGE('1ae03038ed69'!F42,'1572eb063e5c'!F42,b6ea66d78823!F42,'6d8dcb722ca4'!F42,'9306b30af184'!F42,'3b760aaeab13'!F42,b2f4402deaee!F42,'1c4d314e87cd'!F42,acd4708edfe6!F42,'9a32b1f50fb5'!F42,'2df562aa32e7'!F42,'3a5a3c04bd9d'!F42,'192241189337'!F42,'23a0423d7f40'!F42,'096252bb3796'!F42,a53d1c7f9645!F42,'283d32631463'!F42,'1a542cfbf2c5'!F42,cf262786a0e1!F42,'4b9efdeaeb40'!F42,'66fab14edc4c'!F42,d9a84a7879b5!F42,caf2b28627a3!F42,'602e9d1875d1'!F42,f168037f7f37!F42,eb071de1ab08!F42,'7b3bd85715a4'!F42,e2a9b537c609!F42,f97457958ce9!F42,'281fcc7d7eae'!F42,'01454b1cfeba'!F42,'79287892b1d7'!F42,'1b3f96535b56'!F42),"") | K13: =IFERROR(AVERAGE('1ae03038ed69'!G42,'1572eb063e5c'!G42,b6ea66d78823!G42,'6d8dcb722ca4'!G42,'9306b30af184'!G42,'3b760aaeab13'!G42,b2f4402deaee!G42,'1c4d314e87cd'!G42,acd4708edfe6!G42,'9a32b1f50fb5'!G42,'2df562aa32e7'!G42,'3a5a3c04bd9d'!G42,'192241189337'!G42,'23a0423d7f40'!G42,'096252bb3796'!G42,a53d1c7f9645!G42,'283d32631463'!G42,'1a542cfbf2c5'!G42,cf262786a0e1!G42,'4b9efdeaeb40'!G42,'66fab14edc4c'!G42,d9a84a7879b5!G42,caf2b28627a3!G42,'602e9d1875d1'!G42,f168037f7f37!G42,eb071de1ab08!G42,'7b3bd85715a4'!G42,e2a9b537c609!G42,f97457958ce9!G42,'281fcc7d7eae'!G42,'01454b1cfeba'!G42,'79287892b1d7'!G42,'1b3f96535b56'!G42),"") | L13: =IFERROR(AVERAGE('1ae03038ed69'!H42,'1572eb063e5c'!H42,b6ea66d78823!H42,'6d8dcb722ca4'!H42,'9306b30af184'!H42,'3b760aaeab13'!H42,b2f4402deaee!H42,'1c4d314e87cd'!H42,acd4708edfe6!H42,'9a32b1f50fb5'!H42,'2df562aa32e7'!H42,'3a5a3c04bd9d'!H42,'192241189337'!H42,'23a0423d7f40'!H42,'096252bb3796'!H42,a53d1c7f9645!H42,'283d32631463'!H42,'1a542cfbf2c5'!H42,cf262786a0e1!H42,'4b9efdeaeb40'!H42,'66fab14edc4c'!H42,d9a84a7879b5!H42,caf2b28627a3!H42,'602e9d1875d1'!H42,f168037f7f37!H42,eb071de1ab08!H42,'7b3bd85715a4'!H42,e2a9b537c609!H42,f97457958ce9!H42,'281fcc7d7eae'!H42,'01454b1cfeba'!H42,'79287892b1d7'!H42,'1b3f96535b56'!H42),"") | M13: =IFERROR(AVERAGE('1ae03038ed69'!I42,'1572eb063e5c'!I42,b6ea66d78823!I42,'6d8dcb722ca4'!I42,'9306b30af184'!I42,'3b760aaeab13'!I42,b2f4402deaee!I42,'1c4d314e87cd'!I42,acd4708edfe6!I42,'9a32b1f50fb5'!I42,'2df562aa32e7'!I42,'3a5a3c04bd9d'!I42,'192241189337'!I42,'23a0423d7f40'!I42,'096252bb3796'!I42,a53d1c7f9645!I42,'283d32631463'!I42,'1a542cfbf2c5'!I42,cf262786a0e1!I42,'4b9efdeaeb40'!I42,'66fab14edc4c'!I42,d9a84a7879b5!I42,caf2b28627a3!I42,'602e9d1875d1'!I42,f168037f7f37!I42,eb071de1ab08!I42,'7b3bd85715a4'!I42,e2a9b537c609!I42,f97457958ce9!I42,'281fcc7d7eae'!I42,'01454b1cfeba'!I42,'79287892b1d7'!I42,'1b3f96535b56'!I42),"") | N13: =IFERROR(AVERAGE('1ae03038ed69'!J42,'1572eb063e5c'!J42,b6ea66d78823!J42,'6d8dcb722ca4'!J42,'9306b30af184'!J42,'3b760aaeab13'!J42,b2f4402deaee!J42,'1c4d314e87cd'!J42,acd4708edfe6!J42,'9a32b1f50fb5'!J42,'2df562aa32e7'!J42,'3a5a3c04bd9d'!J42,'192241189337'!J42,'23a0423d7f40'!J42,'096252bb3796'!J42,a53d1c7f9645!J42,'283d32631463'!J42,'1a542cfbf2c5'!J42,cf262786a0e1!J42,'4b9efdeaeb40'!J42,'66fab14edc4c'!J42,d9a84a7879b5!J42,caf2b28627a3!J42,'602e9d1875d1'!J42,f168037f7f37!J42,eb071de1ab08!J42,'7b3bd85715a4'!J42,e2a9b537c609!J42,f97457958ce9!J42,'281fcc7d7eae'!J42,'01454b1cfeba'!J42,'79287892b1d7'!J42,'1b3f96535b56'!J42),"") | ... R13: =IFERROR(AVERAGE('1ae03038ed69'!N42,'1572eb063e5c'!N42,b6ea66d78823!N42,'6d8dcb722ca4'!N42,'9306b30af184'!N42,'3b760aaeab13'!N42,b2f4402deaee!N42,'1c4d314e87cd'!N42,acd4708edfe6!N42,'9a32b1f50fb5'!N42,'2df562aa32e7'!N42,'3a5a3c04bd9d'!N42,'192241189337'!N42,'23a0423d7f40'!N42,'096252bb3796'!N42,a53d1c7f9645!N42,'283d32631463'!N42,'1a542cfbf2c5'!N42,cf262786a0e1!N42,'4b9efdeaeb40'!N42,'66fab14edc4c'!N42,d9a84a7879b5!N42,caf2b28627a3!N42,'602e9d1875d1'!N42,f168037f7f37!N42,eb071de1ab08!N42,'7b3bd85715a4'!N42,e2a9b537c609!N42,f97457958ce9!N42,'281fcc7d7eae'!N42,'01454b1cfeba'!N42,'79287892b1d7'!N42,'1b3f96535b56'!N42),"") -> 3.5 | U13: 9306b30af184 | V13: Check building design predictions in operation
F14: =LEFT(Definitions!B16,25)&"…" -> Culture and community ide… | G14: =IFERROR(AVERAGE('1ae03038ed69'!C43,'1572eb063e5c'!C43,b6ea66d78823!C43,'6d8dcb722ca4'!C43,'9306b30af184'!C43,'3b760aaeab13'!C43,b2f4402deaee!C43,'1c4d314e87cd'!C43,acd4708edfe6!C43,'9a32b1f50fb5'!C43,'2df562aa32e7'!C43,'3a5a3c04bd9d'!C43,'192241189337'!C43,'23a0423d7f40'!C43,'096252bb3796'!C43,a53d1c7f9645!C43,'283d32631463'!C43,'1a542cfbf2c5'!C43,cf262786a0e1!C43,'4b9efdeaeb40'!C43,'66fab14edc4c'!C43,d9a84a7879b5!C43,caf2b28627a3!C43,'602e9d1875d1'!C43,f168037f7f37!C43,eb071de1ab08!C43,'7b3bd85715a4'!C43,e2a9b537c609!C43,f97457958ce9!C43,'281fcc7d7eae'!C43,'01454b1cfeba'!C43,'79287892b1d7'!C43,'1b3f96535b56'!C43),"") -> 2 | H14: =IFERROR(AVERAGE('1ae03038ed69'!D43,'1572eb063e5c'!D43,b6ea66d78823!D43,'6d8dcb722ca4'!D43,'9306b30af184'!D43,'3b760aaeab13'!D43,b2f4402deaee!D43,'1c4d314e87cd'!D43,acd4708edfe6!D43,'9a32b1f50fb5'!D43,'2df562aa32e7'!D43,'3a5a3c04bd9d'!D43,'192241189337'!D43,'23a0423d7f40'!D43,'096252bb3796'!D43,a53d1c7f9645!D43,'283d32631463'!D43,'1a542cfbf2c5'!D43,cf262786a0e1!D43,'4b9efdeaeb40'!D43,'66fab14edc4c'!D43,d9a84a7879b5!D43,caf2b28627a3!D43,'602e9d1875d1'!D43,f168037f7f37!D43,eb071de1ab08!D43,'7b3bd85715a4'!D43,e2a9b537c609!D43,f97457958ce9!D43,'281fcc7d7eae'!D43,'01454b1cfeba'!D43,'79287892b1d7'!D43,'1b3f96535b56'!D43),"") -> 2 | I14: =IFERROR(AVERAGE('1ae03038ed69'!E43,'1572eb063e5c'!E43,b6ea66d78823!E43,'6d8dcb722ca4'!E43,'9306b30af184'!E43,'3b760aaeab13'!E43,b2f4402deaee!E43,'1c4d314e87cd'!E43,acd4708edfe6!E43,'9a32b1f50fb5'!E43,'2df562aa32e7'!E43,'3a5a3c04bd9d'!E43,'192241189337'!E43,'23a0423d7f40'!E43,'096252bb3796'!E43,a53d1c7f9645!E43,'283d32631463'!E43,'1a542cfbf2c5'!E43,cf262786a0e1!E43,'4b9efdeaeb40'!E43,'66fab14edc4c'!E43,d9a84a7879b5!E43,caf2b28627a3!E43,'602e9d1875d1'!E43,f168037f7f37!E43,eb071de1ab08!E43,'7b3bd85715a4'!E43,e2a9b537c609!E43,f97457958ce9!E43,'281fcc7d7eae'!E43,'01454b1cfeba'!E43,'79287892b1d7'!E43,'1b3f96535b56'!E43),"") -> 5 | J14: =IFERROR(AVERAGE('1ae03038ed69'!F43,'1572eb063e5c'!F43,b6ea66d78823!F43,'6d8dcb722ca4'!F43,'9306b30af184'!F43,'3b760aaeab13'!F43,b2f4402deaee!F43,'1c4d314e87cd'!F43,acd4708edfe6!F43,'9a32b1f50fb5'!F43,'2df562aa32e7'!F43,'3a5a3c04bd9d'!F43,'192241189337'!F43,'23a0423d7f40'!F43,'096252bb3796'!F43,a53d1c7f9645!F43,'283d32631463'!F43,'1a542cfbf2c5'!F43,cf262786a0e1!F43,'4b9efdeaeb40'!F43,'66fab14edc4c'!F43,d9a84a7879b5!F43,caf2b28627a3!F43,'602e9d1875d1'!F43,f168037f7f37!F43,eb071de1ab08!F43,'7b3bd85715a4'!F43,e2a9b537c609!F43,f97457958ce9!F43,'281fcc7d7eae'!F43,'01454b1cfeba'!F43,'79287892b1d7'!F43,'1b3f96535b56'!F43),"") -> 5 | K14: =IFERROR(AVERAGE('1ae03038ed69'!G43,'1572eb063e5c'!G43,b6ea66d78823!G43,'6d8dcb722ca4'!G43,'9306b30af184'!G43,'3b760aaeab13'!G43,b2f4402deaee!G43,'1c4d314e87cd'!G43,acd4708edfe6!G43,'9a32b1f50fb5'!G43,'2df562aa32e7'!G43,'3a5a3c04bd9d'!G43,'192241189337'!G43,'23a0423d7f40'!G43,'096252bb3796'!G43,a53d1c7f9645!G43,'283d32631463'!G43,'1a542cfbf2c5'!G43,cf262786a0e1!G43,'4b9efdeaeb40'!G43,'66fab14edc4c'!G43,d9a84a7879b5!G43,caf2b28627a3!G43,'602e9d1875d1'!G43,f168037f7f37!G43,eb071de1ab08!G43,'7b3bd85715a4'!G43,e2a9b537c609!G43,f97457958ce9!G43,'281fcc7d7eae'!G43,'01454b1cfeba'!G43,'79287892b1d7'!G43,'1b3f96535b56'!G43),"") | L14: =IFERROR(AVERAGE('1ae03038ed69'!H43,'1572eb063e5c'!H43,b6ea66d78823!H43,'6d8dcb722ca4'!H43,'9306b30af184'!H43,'3b760aaeab13'!H43,b2f4402deaee!H43,'1c4d314e87cd'!H43,acd4708edfe6!H43,'9a32b1f50fb5'!H43,'2df562aa32e7'!H43,'3a5a3c04bd9d'!H43,'192241189337'!H43,'23a0423d7f40'!H43,'096252bb3796'!H43,a53d1c7f9645!H43,'283d32631463'!H43,'1a542cfbf2c5'!H43,cf262786a0e1!H43,'4b9efdeaeb40'!H43,'66fab14edc4c'!H43,d9a84a7879b5!H43,caf2b28627a3!H43,'602e9d1875d1'!H43,f168037f7f37!H43,eb071de1ab08!H43,'7b3bd85715a4'!H43,e2a9b537c609!H43,f97457958ce9!H43,'281fcc7d7eae'!H43,'01454b1cfeba'!H43,'79287892b1d7'!H43,'1b3f96535b56'!H43),"") | M14: =IFERROR(AVERAGE('1ae03038ed69'!I43,'1572eb063e5c'!I43,b6ea66d78823!I43,'6d8dcb722ca4'!I43,'9306b30af184'!I43,'3b760aaeab13'!I43,b2f4402deaee!I43,'1c4d314e87cd'!I43,acd4708edfe6!I43,'9a32b1f50fb5'!I43,'2df562aa32e7'!I43,'3a5a3c04bd9d'!I43,'192241189337'!I43,'23a0423d7f40'!I43,'096252bb3796'!I43,a53d1c7f9645!I43,'283d32631463'!I43,'1a542cfbf2c5'!I43,cf262786a0e1!I43,'4b9efdeaeb40'!I43,'66fab14edc4c'!I43,d9a84a7879b5!I43,caf2b28627a3!I43,'602e9d1875d1'!I43,f168037f7f37!I43,eb071de1ab08!I43,'7b3bd85715a4'!I43,e2a9b537c609!I43,f97457958ce9!I43,'281fcc7d7eae'!I43,'01454b1cfeba'!I43,'79287892b1d7'!I43,'1b3f96535b56'!I43),"") | N14: =IFERROR(AVERAGE('1ae03038ed69'!J43,'1572eb063e5c'!J43,b6ea66d78823!J43,'6d8dcb722ca4'!J43,'9306b30af184'!J43,'3b760aaeab13'!J43,b2f4402deaee!J43,'1c4d314e87cd'!J43,acd4708edfe6!J43,'9a32b1f50fb5'!J43,'2df562aa32e7'!J43,'3a5a3c04bd9d'!J43,'192241189337'!J43,'23a0423d7f40'!J43,'096252bb3796'!J43,a53d1c7f9645!J43,'283d32631463'!J43,'1a542cfbf2c5'!J43,cf262786a0e1!J43,'4b9efdeaeb40'!J43,'66fab14edc4c'!J43,d9a84a7879b5!J43,caf2b28627a3!J43,'602e9d1875d1'!J43,f168037f7f37!J43,eb071de1ab08!J43,'7b3bd85715a4'!J43,e2a9b537c609!J43,f97457958ce9!J43,'281fcc7d7eae'!J43,'01454b1cfeba'!J43,'79287892b1d7'!J43,'1b3f96535b56'!J43),"") | ... R14: =IFERROR(AVERAGE('1ae03038ed69'!N43,'1572eb063e5c'!N43,b6ea66d78823!N43,'6d8dcb722ca4'!N43,'9306b30af184'!N43,'3b760aaeab13'!N43,b2f4402deaee!N43,'1c4d314e87cd'!N43,acd4708edfe6!N43,'9a32b1f50fb5'!N43,'2df562aa32e7'!N43,'3a5a3c04bd9d'!N43,'192241189337'!N43,'23a0423d7f40'!N43,'096252bb3796'!N43,a53d1c7f9645!N43,'283d32631463'!N43,'1a542cfbf2c5'!N43,cf262786a0e1!N43,'4b9efdeaeb40'!N43,'66fab14edc4c'!N43,d9a84a7879b5!N43,caf2b28627a3!N43,'602e9d1875d1'!N43,f168037f7f37!N43,eb071de1ab08!N43,'7b3bd85715a4'!N43,e2a9b537c609!N43,f97457958ce9!N43,'281fcc7d7eae'!N43,'01454b1cfeba'!N43,'79287892b1d7'!N43,'1b3f96535b56'!N43),"") | U14: 3b760aaeab13 | V14: Instant LCA metrics feedback in early building design stage
F15: =LEFT(Definitions!B17,25)&"…" -> Living together, interdep… | G15: =IFERROR(AVERAGE('1ae03038ed69'!C44,'1572eb063e5c'!C44,b6ea66d78823!C44,'6d8dcb722ca4'!C44,'9306b30af184'!C44,'3b760aaeab13'!C44,b2f4402deaee!C44,'1c4d314e87cd'!C44,acd4708edfe6!C44,'9a32b1f50fb5'!C44,'2df562aa32e7'!C44,'3a5a3c04bd9d'!C44,'192241189337'!C44,'23a0423d7f40'!C44,'096252bb3796'!C44,a53d1c7f9645!C44,'283d32631463'!C44,'1a542cfbf2c5'!C44,cf262786a0e1!C44,'4b9efdeaeb40'!C44,'66fab14edc4c'!C44,d9a84a7879b5!C44,caf2b28627a3!C44,'602e9d1875d1'!C44,f168037f7f37!C44,eb071de1ab08!C44,'7b3bd85715a4'!C44,e2a9b537c609!C44,f97457958ce9!C44,'281fcc7d7eae'!C44,'01454b1cfeba'!C44,'79287892b1d7'!C44,'1b3f96535b56'!C44),"") | H15: =IFERROR(AVERAGE('1ae03038ed69'!D44,'1572eb063e5c'!D44,b6ea66d78823!D44,'6d8dcb722ca4'!D44,'9306b30af184'!D44,'3b760aaeab13'!D44,b2f4402deaee!D44,'1c4d314e87cd'!D44,acd4708edfe6!D44,'9a32b1f50fb5'!D44,'2df562aa32e7'!D44,'3a5a3c04bd9d'!D44,'192241189337'!D44,'23a0423d7f40'!D44,'096252bb3796'!D44,a53d1c7f9645!D44,'283d32631463'!D44,'1a542cfbf2c5'!D44,cf262786a0e1!D44,'4b9efdeaeb40'!D44,'66fab14edc4c'!D44,d9a84a7879b5!D44,caf2b28627a3!D44,'602e9d1875d1'!D44,f168037f7f37!D44,eb071de1ab08!D44,'7b3bd85715a4'!D44,e2a9b537c609!D44,f97457958ce9!D44,'281fcc7d7eae'!D44,'01454b1cfeba'!D44,'79287892b1d7'!D44,'1b3f96535b56'!D44),"") | I15: =IFERROR(AVERAGE('1ae03038ed69'!E44,'1572eb063e5c'!E44,b6ea66d78823!E44,'6d8dcb722ca4'!E44,'9306b30af184'!E44,'3b760aaeab13'!E44,b2f4402deaee!E44,'1c4d314e87cd'!E44,acd4708edfe6!E44,'9a32b1f50fb5'!E44,'2df562aa32e7'!E44,'3a5a3c04bd9d'!E44,'192241189337'!E44,'23a0423d7f40'!E44,'096252bb3796'!E44,a53d1c7f9645!E44,'283d32631463'!E44,'1a542cfbf2c5'!E44,cf262786a0e1!E44,'4b9efdeaeb40'!E44,'66fab14edc4c'!E44,d9a84a7879b5!E44,caf2b28627a3!E44,'602e9d1875d1'!E44,f168037f7f37!E44,eb071de1ab08!E44,'7b3bd85715a4'!E44,e2a9b537c609!E44,f97457958ce9!E44,'281fcc7d7eae'!E44,'01454b1cfeba'!E44,'79287892b1d7'!E44,'1b3f96535b56'!E44),"") | J15: =IFERROR(AVERAGE('1ae03038ed69'!F44,'1572eb063e5c'!F44,b6ea66d78823!F44,'6d8dcb722ca4'!F44,'9306b30af184'!F44,'3b760aaeab13'!F44,b2f4402deaee!F44,'1c4d314e87cd'!F44,acd4708edfe6!F44,'9a32b1f50fb5'!F44,'2df562aa32e7'!F44,'3a5a3c04bd9d'!F44,'192241189337'!F44,'23a0423d7f40'!F44,'096252bb3796'!F44,a53d1c7f9645!F44,'283d32631463'!F44,'1a542cfbf2c5'!F44,cf262786a0e1!F44,'4b9efdeaeb40'!F44,'66fab14edc4c'!F44,d9a84a7879b5!F44,caf2b28627a3!F44,'602e9d1875d1'!F44,f168037f7f37!F44,eb071de1ab08!F44,'7b3bd85715a4'!F44,e2a9b537c609!F44,f97457958ce9!F44,'281fcc7d7eae'!F44,'01454b1cfeba'!F44,'79287892b1d7'!F44,'1b3f96535b56'!F44),"") | K15: =IFERROR(AVERAGE('1ae03038ed69'!G44,'1572eb063e5c'!G44,b6ea66d78823!G44,'6d8dcb722ca4'!G44,'9306b30af184'!G44,'3b760aaeab13'!G44,b2f4402deaee!G44,'1c4d314e87cd'!G44,acd4708edfe6!G44,'9a32b1f50fb5'!G44,'2df562aa32e7'!G44,'3a5a3c04bd9d'!G44,'192241189337'!G44,'23a0423d7f40'!G44,'096252bb3796'!G44,a53d1c7f9645!G44,'283d32631463'!G44,'1a542cfbf2c5'!G44,cf262786a0e1!G44,'4b9efdeaeb40'!G44,'66fab14edc4c'!G44,d9a84a7879b5!G44,caf2b28627a3!G44,'602e9d1875d1'!G44,f168037f7f37!G44,eb071de1ab08!G44,'7b3bd85715a4'!G44,e2a9b537c609!G44,f97457958ce9!G44,'281fcc7d7eae'!G44,'01454b1cfeba'!G44,'79287892b1d7'!G44,'1b3f96535b56'!G44),"") | L15: =IFERROR(AVERAGE('1ae03038ed69'!H44,'1572eb063e5c'!H44,b6ea66d78823!H44,'6d8dcb722ca4'!H44,'9306b30af184'!H44,'3b760aaeab13'!H44,b2f4402deaee!H44,'1c4d314e87cd'!H44,acd4708edfe6!H44,'9a32b1f50fb5'!H44,'2df562aa32e7'!H44,'3a5a3c04bd9d'!H44,'192241189337'!H44,'23a0423d7f40'!H44,'096252bb3796'!H44,a53d1c7f9645!H44,'283d32631463'!H44,'1a542cfbf2c5'!H44,cf262786a0e1!H44,'4b9efdeaeb40'!H44,'66fab14edc4c'!H44,d9a84a7879b5!H44,caf2b28627a3!H44,'602e9d1875d1'!H44,f168037f7f37!H44,eb071de1ab08!H44,'7b3bd85715a4'!H44,e2a9b537c609!H44,f97457958ce9!H44,'281fcc7d7eae'!H44,'01454b1cfeba'!H44,'79287892b1d7'!H44,'1b3f96535b56'!H44),"") | M15: =IFERROR(AVERAGE('1ae03038ed69'!I44,'1572eb063e5c'!I44,b6ea66d78823!I44,'6d8dcb722ca4'!I44,'9306b30af184'!I44,'3b760aaeab13'!I44,b2f4402deaee!I44,'1c4d314e87cd'!I44,acd4708edfe6!I44,'9a32b1f50fb5'!I44,'2df562aa32e7'!I44,'3a5a3c04bd9d'!I44,'192241189337'!I44,'23a0423d7f40'!I44,'096252bb3796'!I44,a53d1c7f9645!I44,'283d32631463'!I44,'1a542cfbf2c5'!I44,cf262786a0e1!I44,'4b9efdeaeb40'!I44,'66fab14edc4c'!I44,d9a84a7879b5!I44,caf2b28627a3!I44,'602e9d1875d1'!I44,f168037f7f37!I44,eb071de1ab08!I44,'7b3bd85715a4'!I44,e2a9b537c609!I44,f97457958ce9!I44,'281fcc7d7eae'!I44,'01454b1cfeba'!I44,'79287892b1d7'!I44,'1b3f96535b56'!I44),"") | N15: =IFERROR(AVERAGE('1ae03038ed69'!J44,'1572eb063e5c'!J44,b6ea66d78823!J44,'6d8dcb722ca4'!J44,'9306b30af184'!J44,'3b760aaeab13'!J44,b2f4402deaee!J44,'1c4d314e87cd'!J44,acd4708edfe6!J44,'9a32b1f50fb5'!J44,'2df562aa32e7'!J44,'3a5a3c04bd9d'!J44,'192241189337'!J44,'23a0423d7f40'!J44,'096252bb3796'!J44,a53d1c7f9645!J44,'283d32631463'!J44,'1a542cfbf2c5'!J44,cf262786a0e1!J44,'4b9efdeaeb40'!J44,'66fab14edc4c'!J44,d9a84a7879b5!J44,caf2b28627a3!J44,'602e9d1875d1'!J44,f168037f7f37!J44,eb071de1ab08!J44,'7b3bd85715a4'!J44,e2a9b537c609!J44,f97457958ce9!J44,'281fcc7d7eae'!J44,'01454b1cfeba'!J44,'79287892b1d7'!J44,'1b3f96535b56'!J44),"") | ... R15: =IFERROR(AVERAGE('1ae03038ed69'!N44,'1572eb063e5c'!N44,b6ea66d78823!N44,'6d8dcb722ca4'!N44,'9306b30af184'!N44,'3b760aaeab13'!N44,b2f4402deaee!N44,'1c4d314e87cd'!N44,acd4708edfe6!N44,'9a32b1f50fb5'!N44,'2df562aa32e7'!N44,'3a5a3c04bd9d'!N44,'192241189337'!N44,'23a0423d7f40'!N44,'096252bb3796'!N44,a53d1c7f9645!N44,'283d32631463'!N44,'1a542cfbf2c5'!N44,cf262786a0e1!N44,'4b9efdeaeb40'!N44,'66fab14edc4c'!N44,d9a84a7879b5!N44,caf2b28627a3!N44,'602e9d1875d1'!N44,f168037f7f37!N44,eb071de1ab08!N44,'7b3bd85715a4'!N44,e2a9b537c609!N44,f97457958ce9!N44,'281fcc7d7eae'!N44,'01454b1cfeba'!N44,'79287892b1d7'!N44,'1b3f96535b56'!N44),"") -> 4 | U15: b2f4402deaee | V15: Get feedback on design impact.
B16: Checked | F16: =LEFT(Definitions!B18,25)&"…" -> Economy and sustainable p… | G16: =IFERROR(AVERAGE('1ae03038ed69'!C45,'1572eb063e5c'!C45,b6ea66d78823!C45,'6d8dcb722ca4'!C45,'9306b30af184'!C45,'3b760aaeab13'!C45,b2f4402deaee!C45,'1c4d314e87cd'!C45,acd4708edfe6!C45,'9a32b1f50fb5'!C45,'2df562aa32e7'!C45,'3a5a3c04bd9d'!C45,'192241189337'!C45,'23a0423d7f40'!C45,'096252bb3796'!C45,a53d1c7f9645!C45,'283d32631463'!C45,'1a542cfbf2c5'!C45,cf262786a0e1!C45,'4b9efdeaeb40'!C45,'66fab14edc4c'!C45,d9a84a7879b5!C45,caf2b28627a3!C45,'602e9d1875d1'!C45,f168037f7f37!C45,eb071de1ab08!C45,'7b3bd85715a4'!C45,e2a9b537c609!C45,f97457958ce9!C45,'281fcc7d7eae'!C45,'01454b1cfeba'!C45,'79287892b1d7'!C45,'1b3f96535b56'!C45),"") -> 2.6666667 | H16: =IFERROR(AVERAGE('1ae03038ed69'!D45,'1572eb063e5c'!D45,b6ea66d78823!D45,'6d8dcb722ca4'!D45,'9306b30af184'!D45,'3b760aaeab13'!D45,b2f4402deaee!D45,'1c4d314e87cd'!D45,acd4708edfe6!D45,'9a32b1f50fb5'!D45,'2df562aa32e7'!D45,'3a5a3c04bd9d'!D45,'192241189337'!D45,'23a0423d7f40'!D45,'096252bb3796'!D45,a53d1c7f9645!D45,'283d32631463'!D45,'1a542cfbf2c5'!D45,cf262786a0e1!D45,'4b9efdeaeb40'!D45,'66fab14edc4c'!D45,d9a84a7879b5!D45,caf2b28627a3!D45,'602e9d1875d1'!D45,f168037f7f37!D45,eb071de1ab08!D45,'7b3bd85715a4'!D45,e2a9b537c609!D45,f97457958ce9!D45,'281fcc7d7eae'!D45,'01454b1cfeba'!D45,'79287892b1d7'!D45,'1b3f96535b56'!D45),"") | I16: =IFERROR(AVERAGE('1ae03038ed69'!E45,'1572eb063e5c'!E45,b6ea66d78823!E45,'6d8dcb722ca4'!E45,'9306b30af184'!E45,'3b760aaeab13'!E45,b2f4402deaee!E45,'1c4d314e87cd'!E45,acd4708edfe6!E45,'9a32b1f50fb5'!E45,'2df562aa32e7'!E45,'3a5a3c04bd9d'!E45,'192241189337'!E45,'23a0423d7f40'!E45,'096252bb3796'!E45,a53d1c7f9645!E45,'283d32631463'!E45,'1a542cfbf2c5'!E45,cf262786a0e1!E45,'4b9efdeaeb40'!E45,'66fab14edc4c'!E45,d9a84a7879b5!E45,caf2b28627a3!E45,'602e9d1875d1'!E45,f168037f7f37!E45,eb071de1ab08!E45,'7b3bd85715a4'!E45,e2a9b537c609!E45,f97457958ce9!E45,'281fcc7d7eae'!E45,'01454b1cfeba'!E45,'79287892b1d7'!E45,'1b3f96535b56'!E45),"") -> 1 | J16: =IFERROR(AVERAGE('1ae03038ed69'!F45,'1572eb063e5c'!F45,b6ea66d78823!F45,'6d8dcb722ca4'!F45,'9306b30af184'!F45,'3b760aaeab13'!F45,b2f4402deaee!F45,'1c4d314e87cd'!F45,acd4708edfe6!F45,'9a32b1f50fb5'!F45,'2df562aa32e7'!F45,'3a5a3c04bd9d'!F45,'192241189337'!F45,'23a0423d7f40'!F45,'096252bb3796'!F45,a53d1c7f9645!F45,'283d32631463'!F45,'1a542cfbf2c5'!F45,cf262786a0e1!F45,'4b9efdeaeb40'!F45,'66fab14edc4c'!F45,d9a84a7879b5!F45,caf2b28627a3!F45,'602e9d1875d1'!F45,f168037f7f37!F45,eb071de1ab08!F45,'7b3bd85715a4'!F45,e2a9b537c609!F45,f97457958ce9!F45,'281fcc7d7eae'!F45,'01454b1cfeba'!F45,'79287892b1d7'!F45,'1b3f96535b56'!F45),"") -> 1 | K16: =IFERROR(AVERAGE('1ae03038ed69'!G45,'1572eb063e5c'!G45,b6ea66d78823!G45,'6d8dcb722ca4'!G45,'9306b30af184'!G45,'3b760aaeab13'!G45,b2f4402deaee!G45,'1c4d314e87cd'!G45,acd4708edfe6!G45,'9a32b1f50fb5'!G45,'2df562aa32e7'!G45,'3a5a3c04bd9d'!G45,'192241189337'!G45,'23a0423d7f40'!G45,'096252bb3796'!G45,a53d1c7f9645!G45,'283d32631463'!G45,'1a542cfbf2c5'!G45,cf262786a0e1!G45,'4b9efdeaeb40'!G45,'66fab14edc4c'!G45,d9a84a7879b5!G45,caf2b28627a3!G45,'602e9d1875d1'!G45,f168037f7f37!G45,eb071de1ab08!G45,'7b3bd85715a4'!G45,e2a9b537c609!G45,f97457958ce9!G45,'281fcc7d7eae'!G45,'01454b1cfeba'!G45,'79287892b1d7'!G45,'1b3f96535b56'!G45),"") -> 3.3333333 | L16: =IFERROR(AVERAGE('1ae03038ed69'!H45,'1572eb063e5c'!H45,b6ea66d78823!H45,'6d8dcb722ca4'!H45,'9306b30af184'!H45,'3b760aaeab13'!H45,b2f4402deaee!H45,'1c4d314e87cd'!H45,acd4708edfe6!H45,'9a32b1f50fb5'!H45,'2df562aa32e7'!H45,'3a5a3c04bd9d'!H45,'192241189337'!H45,'23a0423d7f40'!H45,'096252bb3796'!H45,a53d1c7f9645!H45,'283d32631463'!H45,'1a542cfbf2c5'!H45,cf262786a0e1!H45,'4b9efdeaeb40'!H45,'66fab14edc4c'!H45,d9a84a7879b5!H45,caf2b28627a3!H45,'602e9d1875d1'!H45,f168037f7f37!H45,eb071de1ab08!H45,'7b3bd85715a4'!H45,e2a9b537c609!H45,f97457958ce9!H45,'281fcc7d7eae'!H45,'01454b1cfeba'!H45,'79287892b1d7'!H45,'1b3f96535b56'!H45),"") -> 3 | M16: =IFERROR(AVERAGE('1ae03038ed69'!I45,'1572eb063e5c'!I45,b6ea66d78823!I45,'6d8dcb722ca4'!I45,'9306b30af184'!I45,'3b760aaeab13'!I45,b2f4402deaee!I45,'1c4d314e87cd'!I45,acd4708edfe6!I45,'9a32b1f50fb5'!I45,'2df562aa32e7'!I45,'3a5a3c04bd9d'!I45,'192241189337'!I45,'23a0423d7f40'!I45,'096252bb3796'!I45,a53d1c7f9645!I45,'283d32631463'!I45,'1a542cfbf2c5'!I45,cf262786a0e1!I45,'4b9efdeaeb40'!I45,'66fab14edc4c'!I45,d9a84a7879b5!I45,caf2b28627a3!I45,'602e9d1875d1'!I45,f168037f7f37!I45,eb071de1ab08!I45,'7b3bd85715a4'!I45,e2a9b537c609!I45,f97457958ce9!I45,'281fcc7d7eae'!I45,'01454b1cfeba'!I45,'79287892b1d7'!I45,'1b3f96535b56'!I45),"") -> 4 | N16: =IFERROR(AVERAGE('1ae03038ed69'!J45,'1572eb063e5c'!J45,b6ea66d78823!J45,'6d8dcb722ca4'!J45,'9306b30af184'!J45,'3b760aaeab13'!J45,b2f4402deaee!J45,'1c4d314e87cd'!J45,acd4708edfe6!J45,'9a32b1f50fb5'!J45,'2df562aa32e7'!J45,'3a5a3c04bd9d'!J45,'192241189337'!J45,'23a0423d7f40'!J45,'096252bb3796'!J45,a53d1c7f9645!J45,'283d32631463'!J45,'1a542cfbf2c5'!J45,cf262786a0e1!J45,'4b9efdeaeb40'!J45,'66fab14edc4c'!J45,d9a84a7879b5!J45,caf2b28627a3!J45,'602e9d1875d1'!J45,f168037f7f37!J45,eb071de1ab08!J45,'7b3bd85715a4'!J45,e2a9b537c609!J45,f97457958ce9!J45,'281fcc7d7eae'!J45,'01454b1cfeba'!J45,'79287892b1d7'!J45,'1b3f96535b56'!J45),"") -> 4 | ... R16: =IFERROR(AVERAGE('1ae03038ed69'!N45,'1572eb063e5c'!N45,b6ea66d78823!N45,'6d8dcb722ca4'!N45,'9306b30af184'!N45,'3b760aaeab13'!N45,b2f4402deaee!N45,'1c4d314e87cd'!N45,acd4708edfe6!N45,'9a32b1f50fb5'!N45,'2df562aa32e7'!N45,'3a5a3c04bd9d'!N45,'192241189337'!N45,'23a0423d7f40'!N45,'096252bb3796'!N45,a53d1c7f9645!N45,'283d32631463'!N45,'1a542cfbf2c5'!N45,cf262786a0e1!N45,'4b9efdeaeb40'!N45,'66fab14edc4c'!N45,d9a84a7879b5!N45,caf2b28627a3!N45,'602e9d1875d1'!N45,f168037f7f37!N45,eb071de1ab08!N45,'7b3bd85715a4'!N45,e2a9b537c609!N45,f97457958ce9!N45,'281fcc7d7eae'!N45,'01454b1cfeba'!N45,'79287892b1d7'!N45,'1b3f96535b56'!N45),"") -> 1 | U16: 1c4d314e87cd | V16: Automated analysis for "soft" human-centered criteria.
F17: =LEFT(Definitions!B19,25)&"…" -> Living and working enviro… | G17: =IFERROR(AVERAGE('1ae03038ed69'!C46,'1572eb063e5c'!C46,b6ea66d78823!C46,'6d8dcb722ca4'!C46,'9306b30af184'!C46,'3b760aaeab13'!C46,b2f4402deaee!C46,'1c4d314e87cd'!C46,acd4708edfe6!C46,'9a32b1f50fb5'!C46,'2df562aa32e7'!C46,'3a5a3c04bd9d'!C46,'192241189337'!C46,'23a0423d7f40'!C46,'096252bb3796'!C46,a53d1c7f9645!C46,'283d32631463'!C46,'1a542cfbf2c5'!C46,cf262786a0e1!C46,'4b9efdeaeb40'!C46,'66fab14edc4c'!C46,d9a84a7879b5!C46,caf2b28627a3!C46,'602e9d1875d1'!C46,f168037f7f37!C46,eb071de1ab08!C46,'7b3bd85715a4'!C46,e2a9b537c609!C46,f97457958ce9!C46,'281fcc7d7eae'!C46,'01454b1cfeba'!C46,'79287892b1d7'!C46,'1b3f96535b56'!C46),"") -> 3.5 | H17: =IFERROR(AVERAGE('1ae03038ed69'!D46,'1572eb063e5c'!D46,b6ea66d78823!D46,'6d8dcb722ca4'!D46,'9306b30af184'!D46,'3b760aaeab13'!D46,b2f4402deaee!D46,'1c4d314e87cd'!D46,acd4708edfe6!D46,'9a32b1f50fb5'!D46,'2df562aa32e7'!D46,'3a5a3c04bd9d'!D46,'192241189337'!D46,'23a0423d7f40'!D46,'096252bb3796'!D46,a53d1c7f9645!D46,'283d32631463'!D46,'1a542cfbf2c5'!D46,cf262786a0e1!D46,'4b9efdeaeb40'!D46,'66fab14edc4c'!D46,d9a84a7879b5!D46,caf2b28627a3!D46,'602e9d1875d1'!D46,f168037f7f37!D46,eb071de1ab08!D46,'7b3bd85715a4'!D46,e2a9b537c609!D46,f97457958ce9!D46,'281fcc7d7eae'!D46,'01454b1cfeba'!D46,'79287892b1d7'!D46,'1b3f96535b56'!D46),"") -> 4 | I17: =IFERROR(AVERAGE('1ae03038ed69'!E46,'1572eb063e5c'!E46,b6ea66d78823!E46,'6d8dcb722ca4'!E46,'9306b30af184'!E46,'3b760aaeab13'!E46,b2f4402deaee!E46,'1c4d314e87cd'!E46,acd4708edfe6!E46,'9a32b1f50fb5'!E46,'2df562aa32e7'!E46,'3a5a3c04bd9d'!E46,'192241189337'!E46,'23a0423d7f40'!E46,'096252bb3796'!E46,a53d1c7f9645!E46,'283d32631463'!E46,'1a542cfbf2c5'!E46,cf262786a0e1!E46,'4b9efdeaeb40'!E46,'66fab14edc4c'!E46,d9a84a7879b5!E46,caf2b28627a3!E46,'602e9d1875d1'!E46,f168037f7f37!E46,eb071de1ab08!E46,'7b3bd85715a4'!E46,e2a9b537c609!E46,f97457958ce9!E46,'281fcc7d7eae'!E46,'01454b1cfeba'!E46,'79287892b1d7'!E46,'1b3f96535b56'!E46),"") | J17: =IFERROR(AVERAGE('1ae03038ed69'!F46,'1572eb063e5c'!F46,b6ea66d78823!F46,'6d8dcb722ca4'!F46,'9306b30af184'!F46,'3b760aaeab13'!F46,b2f4402deaee!F46,'1c4d314e87cd'!F46,acd4708edfe6!F46,'9a32b1f50fb5'!F46,'2df562aa32e7'!F46,'3a5a3c04bd9d'!F46,'192241189337'!F46,'23a0423d7f40'!F46,'096252bb3796'!F46,a53d1c7f9645!F46,'283d32631463'!F46,'1a542cfbf2c5'!F46,cf262786a0e1!F46,'4b9efdeaeb40'!F46,'66fab14edc4c'!F46,d9a84a7879b5!F46,caf2b28627a3!F46,'602e9d1875d1'!F46,f168037f7f37!F46,eb071de1ab08!F46,'7b3bd85715a4'!F46,e2a9b537c609!F46,f97457958ce9!F46,'281fcc7d7eae'!F46,'01454b1cfeba'!F46,'79287892b1d7'!F46,'1b3f96535b56'!F46),"") | K17: =IFERROR(AVERAGE('1ae03038ed69'!G46,'1572eb063e5c'!G46,b6ea66d78823!G46,'6d8dcb722ca4'!G46,'9306b30af184'!G46,'3b760aaeab13'!G46,b2f4402deaee!G46,'1c4d314e87cd'!G46,acd4708edfe6!G46,'9a32b1f50fb5'!G46,'2df562aa32e7'!G46,'3a5a3c04bd9d'!G46,'192241189337'!G46,'23a0423d7f40'!G46,'096252bb3796'!G46,a53d1c7f9645!G46,'283d32631463'!G46,'1a542cfbf2c5'!G46,cf262786a0e1!G46,'4b9efdeaeb40'!G46,'66fab14edc4c'!G46,d9a84a7879b5!G46,caf2b28627a3!G46,'602e9d1875d1'!G46,f168037f7f37!G46,eb071de1ab08!G46,'7b3bd85715a4'!G46,e2a9b537c609!G46,f97457958ce9!G46,'281fcc7d7eae'!G46,'01454b1cfeba'!G46,'79287892b1d7'!G46,'1b3f96535b56'!G46),"") | L17: =IFERROR(AVERAGE('1ae03038ed69'!H46,'1572eb063e5c'!H46,b6ea66d78823!H46,'6d8dcb722ca4'!H46,'9306b30af184'!H46,'3b760aaeab13'!H46,b2f4402deaee!H46,'1c4d314e87cd'!H46,acd4708edfe6!H46,'9a32b1f50fb5'!H46,'2df562aa32e7'!H46,'3a5a3c04bd9d'!H46,'192241189337'!H46,'23a0423d7f40'!H46,'096252bb3796'!H46,a53d1c7f9645!H46,'283d32631463'!H46,'1a542cfbf2c5'!H46,cf262786a0e1!H46,'4b9efdeaeb40'!H46,'66fab14edc4c'!H46,d9a84a7879b5!H46,caf2b28627a3!H46,'602e9d1875d1'!H46,f168037f7f37!H46,eb071de1ab08!H46,'7b3bd85715a4'!H46,e2a9b537c609!H46,f97457958ce9!H46,'281fcc7d7eae'!H46,'01454b1cfeba'!H46,'79287892b1d7'!H46,'1b3f96535b56'!H46),"") | M17: =IFERROR(AVERAGE('1ae03038ed69'!I46,'1572eb063e5c'!I46,b6ea66d78823!I46,'6d8dcb722ca4'!I46,'9306b30af184'!I46,'3b760aaeab13'!I46,b2f4402deaee!I46,'1c4d314e87cd'!I46,acd4708edfe6!I46,'9a32b1f50fb5'!I46,'2df562aa32e7'!I46,'3a5a3c04bd9d'!I46,'192241189337'!I46,'23a0423d7f40'!I46,'096252bb3796'!I46,a53d1c7f9645!I46,'283d32631463'!I46,'1a542cfbf2c5'!I46,cf262786a0e1!I46,'4b9efdeaeb40'!I46,'66fab14edc4c'!I46,d9a84a7879b5!I46,caf2b28627a3!I46,'602e9d1875d1'!I46,f168037f7f37!I46,eb071de1ab08!I46,'7b3bd85715a4'!I46,e2a9b537c609!I46,f97457958ce9!I46,'281fcc7d7eae'!I46,'01454b1cfeba'!I46,'79287892b1d7'!I46,'1b3f96535b56'!I46),"") -> 3.7916667 | N17: =IFERROR(AVERAGE('1ae03038ed69'!J46,'1572eb063e5c'!J46,b6ea66d78823!J46,'6d8dcb722ca4'!J46,'9306b30af184'!J46,'3b760aaeab13'!J46,b2f4402deaee!J46,'1c4d314e87cd'!J46,acd4708edfe6!J46,'9a32b1f50fb5'!J46,'2df562aa32e7'!J46,'3a5a3c04bd9d'!J46,'192241189337'!J46,'23a0423d7f40'!J46,'096252bb3796'!J46,a53d1c7f9645!J46,'283d32631463'!J46,'1a542cfbf2c5'!J46,cf262786a0e1!J46,'4b9efdeaeb40'!J46,'66fab14edc4c'!J46,d9a84a7879b5!J46,caf2b28627a3!J46,'602e9d1875d1'!J46,f168037f7f37!J46,eb071de1ab08!J46,'7b3bd85715a4'!J46,e2a9b537c609!J46,f97457958ce9!J46,'281fcc7d7eae'!J46,'01454b1cfeba'!J46,'79287892b1d7'!J46,'1b3f96535b56'!J46),"") -> 3 | ... R17: =IFERROR(AVERAGE('1ae03038ed69'!N46,'1572eb063e5c'!N46,b6ea66d78823!N46,'6d8dcb722ca4'!N46,'9306b30af184'!N46,'3b760aaeab13'!N46,b2f4402deaee!N46,'1c4d314e87cd'!N46,acd4708edfe6!N46,'9a32b1f50fb5'!N46,'2df562aa32e7'!N46,'3a5a3c04bd9d'!N46,'192241189337'!N46,'23a0423d7f40'!N46,'096252bb3796'!N46,a53d1c7f9645!N46,'283d32631463'!N46,'1a542cfbf2c5'!N46,cf262786a0e1!N46,'4b9efdeaeb40'!N46,'66fab14edc4c'!N46,d9a84a7879b5!N46,caf2b28627a3!N46,'602e9d1875d1'!N46,f168037f7f37!N46,eb071de1ab08!N46,'7b3bd85715a4'!N46,e2a9b537c609!N46,f97457958ce9!N46,'281fcc7d7eae'!N46,'01454b1cfeba'!N46,'79287892b1d7'!N46,'1b3f96535b56'!N46),"") -> 3 | U17: acd4708edfe6 | V17: AU/SystemX/ITAINNOVA Human-centred analysis
F18: =LEFT(Definitions!B20,25)&"…" -> Safety and security… | G18: =IFERROR(AVERAGE('1ae03038ed69'!C47,'1572eb063e5c'!C47,b6ea66d78823!C47,'6d8dcb722ca4'!C47,'9306b30af184'!C47,'3b760aaeab13'!C47,b2f4402deaee!C47,'1c4d314e87cd'!C47,acd4708edfe6!C47,'9a32b1f50fb5'!C47,'2df562aa32e7'!C47,'3a5a3c04bd9d'!C47,'192241189337'!C47,'23a0423d7f40'!C47,'096252bb3796'!C47,a53d1c7f9645!C47,'283d32631463'!C47,'1a542cfbf2c5'!C47,cf262786a0e1!C47,'4b9efdeaeb40'!C47,'66fab14edc4c'!C47,d9a84a7879b5!C47,caf2b28627a3!C47,'602e9d1875d1'!C47,f168037f7f37!C47,eb071de1ab08!C47,'7b3bd85715a4'!C47,e2a9b537c609!C47,f97457958ce9!C47,'281fcc7d7eae'!C47,'01454b1cfeba'!C47,'79287892b1d7'!C47,'1b3f96535b56'!C47),"") | H18: =IFERROR(AVERAGE('1ae03038ed69'!D47,'1572eb063e5c'!D47,b6ea66d78823!D47,'6d8dcb722ca4'!D47,'9306b30af184'!D47,'3b760aaeab13'!D47,b2f4402deaee!D47,'1c4d314e87cd'!D47,acd4708edfe6!D47,'9a32b1f50fb5'!D47,'2df562aa32e7'!D47,'3a5a3c04bd9d'!D47,'192241189337'!D47,'23a0423d7f40'!D47,'096252bb3796'!D47,a53d1c7f9645!D47,'283d32631463'!D47,'1a542cfbf2c5'!D47,cf262786a0e1!D47,'4b9efdeaeb40'!D47,'66fab14edc4c'!D47,d9a84a7879b5!D47,caf2b28627a3!D47,'602e9d1875d1'!D47,f168037f7f37!D47,eb071de1ab08!D47,'7b3bd85715a4'!D47,e2a9b537c609!D47,f97457958ce9!D47,'281fcc7d7eae'!D47,'01454b1cfeba'!D47,'79287892b1d7'!D47,'1b3f96535b56'!D47),"") | I18: =IFERROR(AVERAGE('1ae03038ed69'!E47,'1572eb063e5c'!E47,b6ea66d78823!E47,'6d8dcb722ca4'!E47,'9306b30af184'!E47,'3b760aaeab13'!E47,b2f4402deaee!E47,'1c4d314e87cd'!E47,acd4708edfe6!E47,'9a32b1f50fb5'!E47,'2df562aa32e7'!E47,'3a5a3c04bd9d'!E47,'192241189337'!E47,'23a0423d7f40'!E47,'096252bb3796'!E47,a53d1c7f9645!E47,'283d32631463'!E47,'1a542cfbf2c5'!E47,cf262786a0e1!E47,'4b9efdeaeb40'!E47,'66fab14edc4c'!E47,d9a84a7879b5!E47,caf2b28627a3!E47,'602e9d1875d1'!E47,f168037f7f37!E47,eb071de1ab08!E47,'7b3bd85715a4'!E47,e2a9b537c609!E47,f97457958ce9!E47,'281fcc7d7eae'!E47,'01454b1cfeba'!E47,'79287892b1d7'!E47,'1b3f96535b56'!E47),"") | J18: =IFERROR(AVERAGE('1ae03038ed69'!F47,'1572eb063e5c'!F47,b6ea66d78823!F47,'6d8dcb722ca4'!F47,'9306b30af184'!F47,'3b760aaeab13'!F47,b2f4402deaee!F47,'1c4d314e87cd'!F47,acd4708edfe6!F47,'9a32b1f50fb5'!F47,'2df562aa32e7'!F47,'3a5a3c04bd9d'!F47,'192241189337'!F47,'23a0423d7f40'!F47,'096252bb3796'!F47,a53d1c7f9645!F47,'283d32631463'!F47,'1a542cfbf2c5'!F47,cf262786a0e1!F47,'4b9efdeaeb40'!F47,'66fab14edc4c'!F47,d9a84a7879b5!F47,caf2b28627a3!F47,'602e9d1875d1'!F47,f168037f7f37!F47,eb071de1ab08!F47,'7b3bd85715a4'!F47,e2a9b537c609!F47,f97457958ce9!F47,'281fcc7d7eae'!F47,'01454b1cfeba'!F47,'79287892b1d7'!F47,'1b3f96535b56'!F47),"") | K18: =IFERROR(AVERAGE('1ae03038ed69'!G47,'1572eb063e5c'!G47,b6ea66d78823!G47,'6d8dcb722ca4'!G47,'9306b30af184'!G47,'3b760aaeab13'!G47,b2f4402deaee!G47,'1c4d314e87cd'!G47,acd4708edfe6!G47,'9a32b1f50fb5'!G47,'2df562aa32e7'!G47,'3a5a3c04bd9d'!G47,'192241189337'!G47,'23a0423d7f40'!G47,'096252bb3796'!G47,a53d1c7f9645!G47,'283d32631463'!G47,'1a542cfbf2c5'!G47,cf262786a0e1!G47,'4b9efdeaeb40'!G47,'66fab14edc4c'!G47,d9a84a7879b5!G47,caf2b28627a3!G47,'602e9d1875d1'!G47,f168037f7f37!G47,eb071de1ab08!G47,'7b3bd85715a4'!G47,e2a9b537c609!G47,f97457958ce9!G47,'281fcc7d7eae'!G47,'01454b1cfeba'!G47,'79287892b1d7'!G47,'1b3f96535b56'!G47),"") -> 3 | L18: =IFERROR(AVERAGE('1ae03038ed69'!H47,'1572eb063e5c'!H47,b6ea66d78823!H47,'6d8dcb722ca4'!H47,'9306b30af184'!H47,'3b760aaeab13'!H47,b2f4402deaee!H47,'1c4d314e87cd'!H47,acd4708edfe6!H47,'9a32b1f50fb5'!H47,'2df562aa32e7'!H47,'3a5a3c04bd9d'!H47,'192241189337'!H47,'23a0423d7f40'!H47,'096252bb3796'!H47,a53d1c7f9645!H47,'283d32631463'!H47,'1a542cfbf2c5'!H47,cf262786a0e1!H47,'4b9efdeaeb40'!H47,'66fab14edc4c'!H47,d9a84a7879b5!H47,caf2b28627a3!H47,'602e9d1875d1'!H47,f168037f7f37!H47,eb071de1ab08!H47,'7b3bd85715a4'!H47,e2a9b537c609!H47,f97457958ce9!H47,'281fcc7d7eae'!H47,'01454b1cfeba'!H47,'79287892b1d7'!H47,'1b3f96535b56'!H47),"") -> 3 | M18: =IFERROR(AVERAGE('1ae03038ed69'!I47,'1572eb063e5c'!I47,b6ea66d78823!I47,'6d8dcb722ca4'!I47,'9306b30af184'!I47,'3b760aaeab13'!I47,b2f4402deaee!I47,'1c4d314e87cd'!I47,acd4708edfe6!I47,'9a32b1f50fb5'!I47,'2df562aa32e7'!I47,'3a5a3c04bd9d'!I47,'192241189337'!I47,'23a0423d7f40'!I47,'096252bb3796'!I47,a53d1c7f9645!I47,'283d32631463'!I47,'1a542cfbf2c5'!I47,cf262786a0e1!I47,'4b9efdeaeb40'!I47,'66fab14edc4c'!I47,d9a84a7879b5!I47,caf2b28627a3!I47,'602e9d1875d1'!I47,f168037f7f37!I47,eb071de1ab08!I47,'7b3bd85715a4'!I47,e2a9b537c609!I47,f97457958ce9!I47,'281fcc7d7eae'!I47,'01454b1cfeba'!I47,'79287892b1d7'!I47,'1b3f96535b56'!I47),"") | N18: =IFERROR(AVERAGE('1ae03038ed69'!J47,'1572eb063e5c'!J47,b6ea66d78823!J47,'6d8dcb722ca4'!J47,'9306b30af184'!J47,'3b760aaeab13'!J47,b2f4402deaee!J47,'1c4d314e87cd'!J47,acd4708edfe6!J47,'9a32b1f50fb5'!J47,'2df562aa32e7'!J47,'3a5a3c04bd9d'!J47,'192241189337'!J47,'23a0423d7f40'!J47,'096252bb3796'!J47,a53d1c7f9645!J47,'283d32631463'!J47,'1a542cfbf2c5'!J47,cf262786a0e1!J47,'4b9efdeaeb40'!J47,'66fab14edc4c'!J47,d9a84a7879b5!J47,caf2b28627a3!J47,'602e9d1875d1'!J47,f168037f7f37!J47,eb071de1ab08!J47,'7b3bd85715a4'!J47,e2a9b537c609!J47,f97457958ce9!J47,'281fcc7d7eae'!J47,'01454b1cfeba'!J47,'79287892b1d7'!J47,'1b3f96535b56'!J47),"") | ... R18: =IFERROR(AVERAGE('1ae03038ed69'!N47,'1572eb063e5c'!N47,b6ea66d78823!N47,'6d8dcb722ca4'!N47,'9306b30af184'!N47,'3b760aaeab13'!N47,b2f4402deaee!N47,'1c4d314e87cd'!N47,acd4708edfe6!N47,'9a32b1f50fb5'!N47,'2df562aa32e7'!N47,'3a5a3c04bd9d'!N47,'192241189337'!N47,'23a0423d7f40'!N47,'096252bb3796'!N47,a53d1c7f9645!N47,'283d32631463'!N47,'1a542cfbf2c5'!N47,cf262786a0e1!N47,'4b9efdeaeb40'!N47,'66fab14edc4c'!N47,d9a84a7879b5!N47,caf2b28627a3!N47,'602e9d1875d1'!N47,f168037f7f37!N47,eb071de1ab08!N47,'7b3bd85715a4'!N47,e2a9b537c609!N47,f97457958ce9!N47,'281fcc7d7eae'!N47,'01454b1cfeba'!N47,'79287892b1d7'!N47,'1b3f96535b56'!N47),"") | U18: 9a32b1f50fb5 | V18: Guidelines optimizing precast concrete buildings.
F19: =LEFT(Definitions!B21,25)&"…" -> Biodiversity and ecosyste… | G19: =IFERROR(AVERAGE('1ae03038ed69'!C48,'1572eb063e5c'!C48,b6ea66d78823!C48,'6d8dcb722ca4'!C48,'9306b30af184'!C48,'3b760aaeab13'!C48,b2f4402deaee!C48,'1c4d314e87cd'!C48,acd4708edfe6!C48,'9a32b1f50fb5'!C48,'2df562aa32e7'!C48,'3a5a3c04bd9d'!C48,'192241189337'!C48,'23a0423d7f40'!C48,'096252bb3796'!C48,a53d1c7f9645!C48,'283d32631463'!C48,'1a542cfbf2c5'!C48,cf262786a0e1!C48,'4b9efdeaeb40'!C48,'66fab14edc4c'!C48,d9a84a7879b5!C48,caf2b28627a3!C48,'602e9d1875d1'!C48,f168037f7f37!C48,eb071de1ab08!C48,'7b3bd85715a4'!C48,e2a9b537c609!C48,f97457958ce9!C48,'281fcc7d7eae'!C48,'01454b1cfeba'!C48,'79287892b1d7'!C48,'1b3f96535b56'!C48),"") | H19: =IFERROR(AVERAGE('1ae03038ed69'!D48,'1572eb063e5c'!D48,b6ea66d78823!D48,'6d8dcb722ca4'!D48,'9306b30af184'!D48,'3b760aaeab13'!D48,b2f4402deaee!D48,'1c4d314e87cd'!D48,acd4708edfe6!D48,'9a32b1f50fb5'!D48,'2df562aa32e7'!D48,'3a5a3c04bd9d'!D48,'192241189337'!D48,'23a0423d7f40'!D48,'096252bb3796'!D48,a53d1c7f9645!D48,'283d32631463'!D48,'1a542cfbf2c5'!D48,cf262786a0e1!D48,'4b9efdeaeb40'!D48,'66fab14edc4c'!D48,d9a84a7879b5!D48,caf2b28627a3!D48,'602e9d1875d1'!D48,f168037f7f37!D48,eb071de1ab08!D48,'7b3bd85715a4'!D48,e2a9b537c609!D48,f97457958ce9!D48,'281fcc7d7eae'!D48,'01454b1cfeba'!D48,'79287892b1d7'!D48,'1b3f96535b56'!D48),"") | I19: =IFERROR(AVERAGE('1ae03038ed69'!E48,'1572eb063e5c'!E48,b6ea66d78823!E48,'6d8dcb722ca4'!E48,'9306b30af184'!E48,'3b760aaeab13'!E48,b2f4402deaee!E48,'1c4d314e87cd'!E48,acd4708edfe6!E48,'9a32b1f50fb5'!E48,'2df562aa32e7'!E48,'3a5a3c04bd9d'!E48,'192241189337'!E48,'23a0423d7f40'!E48,'096252bb3796'!E48,a53d1c7f9645!E48,'283d32631463'!E48,'1a542cfbf2c5'!E48,cf262786a0e1!E48,'4b9efdeaeb40'!E48,'66fab14edc4c'!E48,d9a84a7879b5!E48,caf2b28627a3!E48,'602e9d1875d1'!E48,f168037f7f37!E48,eb071de1ab08!E48,'7b3bd85715a4'!E48,e2a9b537c609!E48,f97457958ce9!E48,'281fcc7d7eae'!E48,'01454b1cfeba'!E48,'79287892b1d7'!E48,'1b3f96535b56'!E48),"") -> 3.4444444 | J19: =IFERROR(AVERAGE('1ae03038ed69'!F48,'1572eb063e5c'!F48,b6ea66d78823!F48,'6d8dcb722ca4'!F48,'9306b30af184'!F48,'3b760aaeab13'!F48,b2f4402deaee!F48,'1c4d314e87cd'!F48,acd4708edfe6!F48,'9a32b1f50fb5'!F48,'2df562aa32e7'!F48,'3a5a3c04bd9d'!F48,'192241189337'!F48,'23a0423d7f40'!F48,'096252bb3796'!F48,a53d1c7f9645!F48,'283d32631463'!F48,'1a542cfbf2c5'!F48,cf262786a0e1!F48,'4b9efdeaeb40'!F48,'66fab14edc4c'!F48,d9a84a7879b5!F48,caf2b28627a3!F48,'602e9d1875d1'!F48,f168037f7f37!F48,eb071de1ab08!F48,'7b3bd85715a4'!F48,e2a9b537c609!F48,f97457958ce9!F48,'281fcc7d7eae'!F48,'01454b1cfeba'!F48,'79287892b1d7'!F48,'1b3f96535b56'!F48),"") | K19: =IFERROR(AVERAGE('1ae03038ed69'!G48,'1572eb063e5c'!G48,b6ea66d78823!G48,'6d8dcb722ca4'!G48,'9306b30af184'!G48,'3b760aaeab13'!G48,b2f4402deaee!G48,'1c4d314e87cd'!G48,acd4708edfe6!G48,'9a32b1f50fb5'!G48,'2df562aa32e7'!G48,'3a5a3c04bd9d'!G48,'192241189337'!G48,'23a0423d7f40'!G48,'096252bb3796'!G48,a53d1c7f9645!G48,'283d32631463'!G48,'1a542cfbf2c5'!G48,cf262786a0e1!G48,'4b9efdeaeb40'!G48,'66fab14edc4c'!G48,d9a84a7879b5!G48,caf2b28627a3!G48,'602e9d1875d1'!G48,f168037f7f37!G48,eb071de1ab08!G48,'7b3bd85715a4'!G48,e2a9b537c609!G48,f97457958ce9!G48,'281fcc7d7eae'!G48,'01454b1cfeba'!G48,'79287892b1d7'!G48,'1b3f96535b56'!G48),"") -> 3 | L19: =IFERROR(AVERAGE('1ae03038ed69'!H48,'1572eb063e5c'!H48,b6ea66d78823!H48,'6d8dcb722ca4'!H48,'9306b30af184'!H48,'3b760aaeab13'!H48,b2f4402deaee!H48,'1c4d314e87cd'!H48,acd4708edfe6!H48,'9a32b1f50fb5'!H48,'2df562aa32e7'!H48,'3a5a3c04bd9d'!H48,'192241189337'!H48,'23a0423d7f40'!H48,'096252bb3796'!H48,a53d1c7f9645!H48,'283d32631463'!H48,'1a542cfbf2c5'!H48,cf262786a0e1!H48,'4b9efdeaeb40'!H48,'66fab14edc4c'!H48,d9a84a7879b5!H48,caf2b28627a3!H48,'602e9d1875d1'!H48,f168037f7f37!H48,eb071de1ab08!H48,'7b3bd85715a4'!H48,e2a9b537c609!H48,f97457958ce9!H48,'281fcc7d7eae'!H48,'01454b1cfeba'!H48,'79287892b1d7'!H48,'1b3f96535b56'!H48),"") -> 3 | M19: =IFERROR(AVERAGE('1ae03038ed69'!I48,'1572eb063e5c'!I48,b6ea66d78823!I48,'6d8dcb722ca4'!I48,'9306b30af184'!I48,'3b760aaeab13'!I48,b2f4402deaee!I48,'1c4d314e87cd'!I48,acd4708edfe6!I48,'9a32b1f50fb5'!I48,'2df562aa32e7'!I48,'3a5a3c04bd9d'!I48,'192241189337'!I48,'23a0423d7f40'!I48,'096252bb3796'!I48,a53d1c7f9645!I48,'283d32631463'!I48,'1a542cfbf2c5'!I48,cf262786a0e1!I48,'4b9efdeaeb40'!I48,'66fab14edc4c'!I48,d9a84a7879b5!I48,caf2b28627a3!I48,'602e9d1875d1'!I48,f168037f7f37!I48,eb071de1ab08!I48,'7b3bd85715a4'!I48,e2a9b537c609!I48,f97457958ce9!I48,'281fcc7d7eae'!I48,'01454b1cfeba'!I48,'79287892b1d7'!I48,'1b3f96535b56'!I48),"") -> 3 | N19: =IFERROR(AVERAGE('1ae03038ed69'!J48,'1572eb063e5c'!J48,b6ea66d78823!J48,'6d8dcb722ca4'!J48,'9306b30af184'!J48,'3b760aaeab13'!J48,b2f4402deaee!J48,'1c4d314e87cd'!J48,acd4708edfe6!J48,'9a32b1f50fb5'!J48,'2df562aa32e7'!J48,'3a5a3c04bd9d'!J48,'192241189337'!J48,'23a0423d7f40'!J48,'096252bb3796'!J48,a53d1c7f9645!J48,'283d32631463'!J48,'1a542cfbf2c5'!J48,cf262786a0e1!J48,'4b9efdeaeb40'!J48,'66fab14edc4c'!J48,d9a84a7879b5!J48,caf2b28627a3!J48,'602e9d1875d1'!J48,f168037f7f37!J48,eb071de1ab08!J48,'7b3bd85715a4'!J48,e2a9b537c609!J48,f97457958ce9!J48,'281fcc7d7eae'!J48,'01454b1cfeba'!J48,'79287892b1d7'!J48,'1b3f96535b56'!J48),"") -> 3 | ... R19: =IFERROR(AVERAGE('1ae03038ed69'!N48,'1572eb063e5c'!N48,b6ea66d78823!N48,'6d8dcb722ca4'!N48,'9306b30af184'!N48,'3b760aaeab13'!N48,b2f4402deaee!N48,'1c4d314e87cd'!N48,acd4708edfe6!N48,'9a32b1f50fb5'!N48,'2df562aa32e7'!N48,'3a5a3c04bd9d'!N48,'192241189337'!N48,'23a0423d7f40'!N48,'096252bb3796'!N48,a53d1c7f9645!N48,'283d32631463'!N48,'1a542cfbf2c5'!N48,cf262786a0e1!N48,'4b9efdeaeb40'!N48,'66fab14edc4c'!N48,d9a84a7879b5!N48,caf2b28627a3!N48,'602e9d1875d1'!N48,f168037f7f37!N48,eb071de1ab08!N48,'7b3bd85715a4'!N48,e2a9b537c609!N48,f97457958ce9!N48,'281fcc7d7eae'!N48,'01454b1cfeba'!N48,'79287892b1d7'!N48,'1b3f96535b56'!N48),"") | U19: 2df562aa32e7 | V19: Assessment of GBN risks.
B20: Validated | F20: =LEFT(Definitions!B22,25)&"…" -> Community smart infrastru… | G20: =IFERROR(AVERAGE('1ae03038ed69'!C49,'1572eb063e5c'!C49,b6ea66d78823!C49,'6d8dcb722ca4'!C49,'9306b30af184'!C49,'3b760aaeab13'!C49,b2f4402deaee!C49,'1c4d314e87cd'!C49,acd4708edfe6!C49,'9a32b1f50fb5'!C49,'2df562aa32e7'!C49,'3a5a3c04bd9d'!C49,'192241189337'!C49,'23a0423d7f40'!C49,'096252bb3796'!C49,a53d1c7f9645!C49,'283d32631463'!C49,'1a542cfbf2c5'!C49,cf262786a0e1!C49,'4b9efdeaeb40'!C49,'66fab14edc4c'!C49,d9a84a7879b5!C49,caf2b28627a3!C49,'602e9d1875d1'!C49,f168037f7f37!C49,eb071de1ab08!C49,'7b3bd85715a4'!C49,e2a9b537c609!C49,f97457958ce9!C49,'281fcc7d7eae'!C49,'01454b1cfeba'!C49,'79287892b1d7'!C49,'1b3f96535b56'!C49),"") -> 2.8 | H20: =IFERROR(AVERAGE('1ae03038ed69'!D49,'1572eb063e5c'!D49,b6ea66d78823!D49,'6d8dcb722ca4'!D49,'9306b30af184'!D49,'3b760aaeab13'!D49,b2f4402deaee!D49,'1c4d314e87cd'!D49,acd4708edfe6!D49,'9a32b1f50fb5'!D49,'2df562aa32e7'!D49,'3a5a3c04bd9d'!D49,'192241189337'!D49,'23a0423d7f40'!D49,'096252bb3796'!D49,a53d1c7f9645!D49,'283d32631463'!D49,'1a542cfbf2c5'!D49,cf262786a0e1!D49,'4b9efdeaeb40'!D49,'66fab14edc4c'!D49,d9a84a7879b5!D49,caf2b28627a3!D49,'602e9d1875d1'!D49,f168037f7f37!D49,eb071de1ab08!D49,'7b3bd85715a4'!D49,e2a9b537c609!D49,f97457958ce9!D49,'281fcc7d7eae'!D49,'01454b1cfeba'!D49,'79287892b1d7'!D49,'1b3f96535b56'!D49),"") -> 3 | I20: =IFERROR(AVERAGE('1ae03038ed69'!E49,'1572eb063e5c'!E49,b6ea66d78823!E49,'6d8dcb722ca4'!E49,'9306b30af184'!E49,'3b760aaeab13'!E49,b2f4402deaee!E49,'1c4d314e87cd'!E49,acd4708edfe6!E49,'9a32b1f50fb5'!E49,'2df562aa32e7'!E49,'3a5a3c04bd9d'!E49,'192241189337'!E49,'23a0423d7f40'!E49,'096252bb3796'!E49,a53d1c7f9645!E49,'283d32631463'!E49,'1a542cfbf2c5'!E49,cf262786a0e1!E49,'4b9efdeaeb40'!E49,'66fab14edc4c'!E49,d9a84a7879b5!E49,caf2b28627a3!E49,'602e9d1875d1'!E49,f168037f7f37!E49,eb071de1ab08!E49,'7b3bd85715a4'!E49,e2a9b537c609!E49,f97457958ce9!E49,'281fcc7d7eae'!E49,'01454b1cfeba'!E49,'79287892b1d7'!E49,'1b3f96535b56'!E49),"") | J20: =IFERROR(AVERAGE('1ae03038ed69'!F49,'1572eb063e5c'!F49,b6ea66d78823!F49,'6d8dcb722ca4'!F49,'9306b30af184'!F49,'3b760aaeab13'!F49,b2f4402deaee!F49,'1c4d314e87cd'!F49,acd4708edfe6!F49,'9a32b1f50fb5'!F49,'2df562aa32e7'!F49,'3a5a3c04bd9d'!F49,'192241189337'!F49,'23a0423d7f40'!F49,'096252bb3796'!F49,a53d1c7f9645!F49,'283d32631463'!F49,'1a542cfbf2c5'!F49,cf262786a0e1!F49,'4b9efdeaeb40'!F49,'66fab14edc4c'!F49,d9a84a7879b5!F49,caf2b28627a3!F49,'602e9d1875d1'!F49,f168037f7f37!F49,eb071de1ab08!F49,'7b3bd85715a4'!F49,e2a9b537c609!F49,f97457958ce9!F49,'281fcc7d7eae'!F49,'01454b1cfeba'!F49,'79287892b1d7'!F49,'1b3f96535b56'!F49),"") | K20: =IFERROR(AVERAGE('1ae03038ed69'!G49,'1572eb063e5c'!G49,b6ea66d78823!G49,'6d8dcb722ca4'!G49,'9306b30af184'!G49,'3b760aaeab13'!G49,b2f4402deaee!G49,'1c4d314e87cd'!G49,acd4708edfe6!G49,'9a32b1f50fb5'!G49,'2df562aa32e7'!G49,'3a5a3c04bd9d'!G49,'192241189337'!G49,'23a0423d7f40'!G49,'096252bb3796'!G49,a53d1c7f9645!G49,'283d32631463'!G49,'1a542cfbf2c5'!G49,cf262786a0e1!G49,'4b9efdeaeb40'!G49,'66fab14edc4c'!G49,d9a84a7879b5!G49,caf2b28627a3!G49,'602e9d1875d1'!G49,f168037f7f37!G49,eb071de1ab08!G49,'7b3bd85715a4'!G49,e2a9b537c609!G49,f97457958ce9!G49,'281fcc7d7eae'!G49,'01454b1cfeba'!G49,'79287892b1d7'!G49,'1b3f96535b56'!G49),"") -> 2.75 | L20: =IFERROR(AVERAGE('1ae03038ed69'!H49,'1572eb063e5c'!H49,b6ea66d78823!H49,'6d8dcb722ca4'!H49,'9306b30af184'!H49,'3b760aaeab13'!H49,b2f4402deaee!H49,'1c4d314e87cd'!H49,acd4708edfe6!H49,'9a32b1f50fb5'!H49,'2df562aa32e7'!H49,'3a5a3c04bd9d'!H49,'192241189337'!H49,'23a0423d7f40'!H49,'096252bb3796'!H49,a53d1c7f9645!H49,'283d32631463'!H49,'1a542cfbf2c5'!H49,cf262786a0e1!H49,'4b9efdeaeb40'!H49,'66fab14edc4c'!H49,d9a84a7879b5!H49,caf2b28627a3!H49,'602e9d1875d1'!H49,f168037f7f37!H49,eb071de1ab08!H49,'7b3bd85715a4'!H49,e2a9b537c609!H49,f97457958ce9!H49,'281fcc7d7eae'!H49,'01454b1cfeba'!H49,'79287892b1d7'!H49,'1b3f96535b56'!H49),"") | M20: =IFERROR(AVERAGE('1ae03038ed69'!I49,'1572eb063e5c'!I49,b6ea66d78823!I49,'6d8dcb722ca4'!I49,'9306b30af184'!I49,'3b760aaeab13'!I49,b2f4402deaee!I49,'1c4d314e87cd'!I49,acd4708edfe6!I49,'9a32b1f50fb5'!I49,'2df562aa32e7'!I49,'3a5a3c04bd9d'!I49,'192241189337'!I49,'23a0423d7f40'!I49,'096252bb3796'!I49,a53d1c7f9645!I49,'283d32631463'!I49,'1a542cfbf2c5'!I49,cf262786a0e1!I49,'4b9efdeaeb40'!I49,'66fab14edc4c'!I49,d9a84a7879b5!I49,caf2b28627a3!I49,'602e9d1875d1'!I49,f168037f7f37!I49,eb071de1ab08!I49,'7b3bd85715a4'!I49,e2a9b537c609!I49,f97457958ce9!I49,'281fcc7d7eae'!I49,'01454b1cfeba'!I49,'79287892b1d7'!I49,'1b3f96535b56'!I49),"") -> 3.4047619 | N20: =IFERROR(AVERAGE('1ae03038ed69'!J49,'1572eb063e5c'!J49,b6ea66d78823!J49,'6d8dcb722ca4'!J49,'9306b30af184'!J49,'3b760aaeab13'!J49,b2f4402deaee!J49,'1c4d314e87cd'!J49,acd4708edfe6!J49,'9a32b1f50fb5'!J49,'2df562aa32e7'!J49,'3a5a3c04bd9d'!J49,'192241189337'!J49,'23a0423d7f40'!J49,'096252bb3796'!J49,a53d1c7f9645!J49,'283d32631463'!J49,'1a542cfbf2c5'!J49,cf262786a0e1!J49,'4b9efdeaeb40'!J49,'66fab14edc4c'!J49,d9a84a7879b5!J49,caf2b28627a3!J49,'602e9d1875d1'!J49,f168037f7f37!J49,eb071de1ab08!J49,'7b3bd85715a4'!J49,e2a9b537c609!J49,f97457958ce9!J49,'281fcc7d7eae'!J49,'01454b1cfeba'!J49,'79287892b1d7'!J49,'1b3f96535b56'!J49),"") | ... R20: =IFERROR(AVERAGE('1ae03038ed69'!N49,'1572eb063e5c'!N49,b6ea66d78823!N49,'6d8dcb722ca4'!N49,'9306b30af184'!N49,'3b760aaeab13'!N49,b2f4402deaee!N49,'1c4d314e87cd'!N49,acd4708edfe6!N49,'9a32b1f50fb5'!N49,'2df562aa32e7'!N49,'3a5a3c04bd9d'!N49,'192241189337'!N49,'23a0423d7f40'!N49,'096252bb3796'!N49,a53d1c7f9645!N49,'283d32631463'!N49,'1a542cfbf2c5'!N49,cf262786a0e1!N49,'4b9efdeaeb40'!N49,'66fab14edc4c'!N49,d9a84a7879b5!N49,caf2b28627a3!N49,'602e9d1875d1'!N49,f168037f7f37!N49,eb071de1ab08!N49,'7b3bd85715a4'!N49,e2a9b537c609!N49,f97457958ce9!N49,'281fcc7d7eae'!N49,'01454b1cfeba'!N49,'79287892b1d7'!N49,'1b3f96535b56'!N49),"") | U20: 3a5a3c04bd9d | V20: Climate change survey in Denmark.
F21: =LEFT(Definitions!B23,25)&"…" -> Mobility… | G21: =IFERROR(AVERAGE('1ae03038ed69'!C50,'1572eb063e5c'!C50,b6ea66d78823!C50,'6d8dcb722ca4'!C50,'9306b30af184'!C50,'3b760aaeab13'!C50,b2f4402deaee!C50,'1c4d314e87cd'!C50,acd4708edfe6!C50,'9a32b1f50fb5'!C50,'2df562aa32e7'!C50,'3a5a3c04bd9d'!C50,'192241189337'!C50,'23a0423d7f40'!C50,'096252bb3796'!C50,a53d1c7f9645!C50,'283d32631463'!C50,'1a542cfbf2c5'!C50,cf262786a0e1!C50,'4b9efdeaeb40'!C50,'66fab14edc4c'!C50,d9a84a7879b5!C50,caf2b28627a3!C50,'602e9d1875d1'!C50,f168037f7f37!C50,eb071de1ab08!C50,'7b3bd85715a4'!C50,e2a9b537c609!C50,f97457958ce9!C50,'281fcc7d7eae'!C50,'01454b1cfeba'!C50,'79287892b1d7'!C50,'1b3f96535b56'!C50),"") | H21: =IFERROR(AVERAGE('1ae03038ed69'!D50,'1572eb063e5c'!D50,b6ea66d78823!D50,'6d8dcb722ca4'!D50,'9306b30af184'!D50,'3b760aaeab13'!D50,b2f4402deaee!D50,'1c4d314e87cd'!D50,acd4708edfe6!D50,'9a32b1f50fb5'!D50,'2df562aa32e7'!D50,'3a5a3c04bd9d'!D50,'192241189337'!D50,'23a0423d7f40'!D50,'096252bb3796'!D50,a53d1c7f9645!D50,'283d32631463'!D50,'1a542cfbf2c5'!D50,cf262786a0e1!D50,'4b9efdeaeb40'!D50,'66fab14edc4c'!D50,d9a84a7879b5!D50,caf2b28627a3!D50,'602e9d1875d1'!D50,f168037f7f37!D50,eb071de1ab08!D50,'7b3bd85715a4'!D50,e2a9b537c609!D50,f97457958ce9!D50,'281fcc7d7eae'!D50,'01454b1cfeba'!D50,'79287892b1d7'!D50,'1b3f96535b56'!D50),"") | I21: =IFERROR(AVERAGE('1ae03038ed69'!E50,'1572eb063e5c'!E50,b6ea66d78823!E50,'6d8dcb722ca4'!E50,'9306b30af184'!E50,'3b760aaeab13'!E50,b2f4402deaee!E50,'1c4d314e87cd'!E50,acd4708edfe6!E50,'9a32b1f50fb5'!E50,'2df562aa32e7'!E50,'3a5a3c04bd9d'!E50,'192241189337'!E50,'23a0423d7f40'!E50,'096252bb3796'!E50,a53d1c7f9645!E50,'283d32631463'!E50,'1a542cfbf2c5'!E50,cf262786a0e1!E50,'4b9efdeaeb40'!E50,'66fab14edc4c'!E50,d9a84a7879b5!E50,caf2b28627a3!E50,'602e9d1875d1'!E50,f168037f7f37!E50,eb071de1ab08!E50,'7b3bd85715a4'!E50,e2a9b537c609!E50,f97457958ce9!E50,'281fcc7d7eae'!E50,'01454b1cfeba'!E50,'79287892b1d7'!E50,'1b3f96535b56'!E50),"") | J21: =IFERROR(AVERAGE('1ae03038ed69'!F50,'1572eb063e5c'!F50,b6ea66d78823!F50,'6d8dcb722ca4'!F50,'9306b30af184'!F50,'3b760aaeab13'!F50,b2f4402deaee!F50,'1c4d314e87cd'!F50,acd4708edfe6!F50,'9a32b1f50fb5'!F50,'2df562aa32e7'!F50,'3a5a3c04bd9d'!F50,'192241189337'!F50,'23a0423d7f40'!F50,'096252bb3796'!F50,a53d1c7f9645!F50,'283d32631463'!F50,'1a542cfbf2c5'!F50,cf262786a0e1!F50,'4b9efdeaeb40'!F50,'66fab14edc4c'!F50,d9a84a7879b5!F50,caf2b28627a3!F50,'602e9d1875d1'!F50,f168037f7f37!F50,eb071de1ab08!F50,'7b3bd85715a4'!F50,e2a9b537c609!F50,f97457958ce9!F50,'281fcc7d7eae'!F50,'01454b1cfeba'!F50,'79287892b1d7'!F50,'1b3f96535b56'!F50),"") | K21: =IFERROR(AVERAGE('1ae03038ed69'!G50,'1572eb063e5c'!G50,b6ea66d78823!G50,'6d8dcb722ca4'!G50,'9306b30af184'!G50,'3b760aaeab13'!G50,b2f4402deaee!G50,'1c4d314e87cd'!G50,acd4708edfe6!G50,'9a32b1f50fb5'!G50,'2df562aa32e7'!G50,'3a5a3c04bd9d'!G50,'192241189337'!G50,'23a0423d7f40'!G50,'096252bb3796'!G50,a53d1c7f9645!G50,'283d32631463'!G50,'1a542cfbf2c5'!G50,cf262786a0e1!G50,'4b9efdeaeb40'!G50,'66fab14edc4c'!G50,d9a84a7879b5!G50,caf2b28627a3!G50,'602e9d1875d1'!G50,f168037f7f37!G50,eb071de1ab08!G50,'7b3bd85715a4'!G50,e2a9b537c609!G50,f97457958ce9!G50,'281fcc7d7eae'!G50,'01454b1cfeba'!G50,'79287892b1d7'!G50,'1b3f96535b56'!G50),"") | L21: =IFERROR(AVERAGE('1ae03038ed69'!H50,'1572eb063e5c'!H50,b6ea66d78823!H50,'6d8dcb722ca4'!H50,'9306b30af184'!H50,'3b760aaeab13'!H50,b2f4402deaee!H50,'1c4d314e87cd'!H50,acd4708edfe6!H50,'9a32b1f50fb5'!H50,'2df562aa32e7'!H50,'3a5a3c04bd9d'!H50,'192241189337'!H50,'23a0423d7f40'!H50,'096252bb3796'!H50,a53d1c7f9645!H50,'283d32631463'!H50,'1a542cfbf2c5'!H50,cf262786a0e1!H50,'4b9efdeaeb40'!H50,'66fab14edc4c'!H50,d9a84a7879b5!H50,caf2b28627a3!H50,'602e9d1875d1'!H50,f168037f7f37!H50,eb071de1ab08!H50,'7b3bd85715a4'!H50,e2a9b537c609!H50,f97457958ce9!H50,'281fcc7d7eae'!H50,'01454b1cfeba'!H50,'79287892b1d7'!H50,'1b3f96535b56'!H50),"") | M21: =IFERROR(AVERAGE('1ae03038ed69'!I50,'1572eb063e5c'!I50,b6ea66d78823!I50,'6d8dcb722ca4'!I50,'9306b30af184'!I50,'3b760aaeab13'!I50,b2f4402deaee!I50,'1c4d314e87cd'!I50,acd4708edfe6!I50,'9a32b1f50fb5'!I50,'2df562aa32e7'!I50,'3a5a3c04bd9d'!I50,'192241189337'!I50,'23a0423d7f40'!I50,'096252bb3796'!I50,a53d1c7f9645!I50,'283d32631463'!I50,'1a542cfbf2c5'!I50,cf262786a0e1!I50,'4b9efdeaeb40'!I50,'66fab14edc4c'!I50,d9a84a7879b5!I50,caf2b28627a3!I50,'602e9d1875d1'!I50,f168037f7f37!I50,eb071de1ab08!I50,'7b3bd85715a4'!I50,e2a9b537c609!I50,f97457958ce9!I50,'281fcc7d7eae'!I50,'01454b1cfeba'!I50,'79287892b1d7'!I50,'1b3f96535b56'!I50),"") | N21: =IFERROR(AVERAGE('1ae03038ed69'!J50,'1572eb063e5c'!J50,b6ea66d78823!J50,'6d8dcb722ca4'!J50,'9306b30af184'!J50,'3b760aaeab13'!J50,b2f4402deaee!J50,'1c4d314e87cd'!J50,acd4708edfe6!J50,'9a32b1f50fb5'!J50,'2df562aa32e7'!J50,'3a5a3c04bd9d'!J50,'192241189337'!J50,'23a0423d7f40'!J50,'096252bb3796'!J50,a53d1c7f9645!J50,'283d32631463'!J50,'1a542cfbf2c5'!J50,cf262786a0e1!J50,'4b9efdeaeb40'!J50,'66fab14edc4c'!J50,d9a84a7879b5!J50,caf2b28627a3!J50,'602e9d1875d1'!J50,f168037f7f37!J50,eb071de1ab08!J50,'7b3bd85715a4'!J50,e2a9b537c609!J50,f97457958ce9!J50,'281fcc7d7eae'!J50,'01454b1cfeba'!J50,'79287892b1d7'!J50,'1b3f96535b56'!J50),"") | ... R21: =IFERROR(AVERAGE('1ae03038ed69'!N50,'1572eb063e5c'!N50,b6ea66d78823!N50,'6d8dcb722ca4'!N50,'9306b30af184'!N50,'3b760aaeab13'!N50,b2f4402deaee!N50,'1c4d314e87cd'!N50,acd4708edfe6!N50,'9a32b1f50fb5'!N50,'2df562aa32e7'!N50,'3a5a3c04bd9d'!N50,'192241189337'!N50,'23a0423d7f40'!N50,'096252bb3796'!N50,a53d1c7f9645!N50,'283d32631463'!N50,'1a542cfbf2c5'!N50,cf262786a0e1!N50,'4b9efdeaeb40'!N50,'66fab14edc4c'!N50,d9a84a7879b5!N50,caf2b28627a3!N50,'602e9d1875d1'!N50,f168037f7f37!N50,eb071de1ab08!N50,'7b3bd85715a4'!N50,e2a9b537c609!N50,f97457958ce9!N50,'281fcc7d7eae'!N50,'01454b1cfeba'!N50,'79287892b1d7'!N50,'1b3f96535b56'!N50),"") | U21: 192241189337 | V21: Reduce embodied energy in buildings.
U22: 23a0423d7f40 | V22: Flagship building exceeds NZEB performance.
U23: 096252bb3796 | V23: Automated DGNB assessment tool for architects.
B24: Version of tool | C24: (10/04/2024) | F24: Number of count | G24: Attractiveness | I24: Environment | K24: Resilience | M24: Resources | O24: Cohesion | Q24: Well Being | U24: a53d1c7f9645 | V24: Get feedback on design impact.
G25: Bld. | H25: Neig. | I25: Bld. | J25: Neig. | K25: Bld. | L25: Neig. | M25: Bld. | N25: Neig. | O25: Bld. | P25: Neig. | Q25: Bld. | R25: Neig. | U25: 283d32631463 | V25: Check building design predictions in operation
F26: =F10 -> Governance, empowerment a… | G26: =IF(ISNUMBER('1ae03038ed69'!C39)+ISNUMBER('1572eb063e5c'!C39)+ISNUMBER(b6ea66d78823!C39)+ISNUMBER('6d8dcb722ca4'!C39)+ISNUMBER('9306b30af184'!C39)+ISNUMBER('3b760aaeab13'!C39)+ISNUMBER(b2f4402deaee!C39)+ISNUMBER('1c4d314e87cd'!C39)+ISNUMBER(acd4708edfe6!C39)+ISNUMBER('9a32b1f50fb5'!C39)+ISNUMBER('2df562aa32e7'!C39)+ISNUMBER('3a5a3c04bd9d'!C39)+ISNUMBER('192241189337'!C39)+ISNUMBER('23a0423d7f40'!C39)+ISNUMBER('096252bb3796'!C39)+ISNUMBER(a53d1c7f9645!C39)+ISNUMBER('283d32631463'!C39)+ISNUMBER('1a542cfbf2c5'!C39)+ISNUMBER(cf262786a0e1!C39)+ISNUMBER('4b9efdeaeb40'!C39)+ISNUMBER('66fab14edc4c'!C39)+ISNUMBER(d9a84a7879b5!C39)+ISNUMBER(caf2b28627a3!C39)+ISNUMBER('602e9d1875d1'!C39)+ISNUMBER(f168037f7f37!C39)+ISNUMBER(eb071de1ab08!C39)+ISNUMBER('7b3bd85715a4'!C39)+ISNUMBER(e2a9b537c609!C39)+ISNUMBER(f97457958ce9!C39)+ISNUMBER('281fcc7d7eae'!C39)+ISNUMBER('01454b1cfeba'!C39)+ISNUMBER('79287892b1d7'!C39)+ISNUMBER('1b3f96535b56'!C39),ISNUMBER('1ae03038ed69'!C39)+ISNUMBER('1572eb063e5c'!C39)+ISNUMBER(b6ea66d78823!C39)+ISNUMBER('6d8dcb722ca4'!C39)+ISNUMBER('9306b30af184'!C39)+ISNUMBER('3b760aaeab13'!C39)+ISNUMBER(b2f4402deaee!C39)+ISNUMBER('1c4d314e87cd'!C39)+ISNUMBER(acd4708edfe6!C39)+ISNUMBER('9a32b1f50fb5'!C39)+ISNUMBER('2df562aa32e7'!C39)+ISNUMBER('3a5a3c04bd9d'!C39)+ISNUMBER('192241189337'!C39)+ISNUMBER('23a0423d7f40'!C39)+ISNUMBER('096252bb3796'!C39)+ISNUMBER(a53d1c7f9645!C39)+ISNUMBER('283d32631463'!C39)+ISNUMBER('1a542cfbf2c5'!C39)+ISNUMBER(cf262786a0e1!C39)+ISNUMBER('4b9efdeaeb40'!C39)+ISNUMBER('66fab14edc4c'!C39)+ISNUMBER(d9a84a7879b5!C39)+ISNUMBER(caf2b28627a3!C39)+ISNUMBER('602e9d1875d1'!C39)+ISNUMBER(f168037f7f37!C39)+ISNUMBER(eb071de1ab08!C39)+ISNUMBER('7b3bd85715a4'!C39)+ISNUMBER(e2a9b537c609!C39)+ISNUMBER(f97457958ce9!C39)+ISNUMBER('281fcc7d7eae'!C39)+ISNUMBER('01454b1cfeba'!C39)+ISNUMBER('79287892b1d7'!C39)+ISNUMBER('1b3f96535b56'!C39),"") -> 2 | H26: =IF(ISNUMBER('1ae03038ed69'!D39)+ISNUMBER('1572eb063e5c'!D39)+ISNUMBER(b6ea66d78823!D39)+ISNUMBER('6d8dcb722ca4'!D39)+ISNUMBER('9306b30af184'!D39)+ISNUMBER('3b760aaeab13'!D39)+ISNUMBER(b2f4402deaee!D39)+ISNUMBER('1c4d314e87cd'!D39)+ISNUMBER(acd4708edfe6!D39)+ISNUMBER('9a32b1f50fb5'!D39)+ISNUMBER('2df562aa32e7'!D39)+ISNUMBER('3a5a3c04bd9d'!D39)+ISNUMBER('192241189337'!D39)+ISNUMBER('23a0423d7f40'!D39)+ISNUMBER('096252bb3796'!D39)+ISNUMBER(a53d1c7f9645!D39)+ISNUMBER('283d32631463'!D39)+ISNUMBER('1a542cfbf2c5'!D39)+ISNUMBER(cf262786a0e1!D39)+ISNUMBER('4b9efdeaeb40'!D39)+ISNUMBER('66fab14edc4c'!D39)+ISNUMBER(d9a84a7879b5!D39)+ISNUMBER(caf2b28627a3!D39)+ISNUMBER('602e9d1875d1'!D39)+ISNUMBER(f168037f7f37!D39)+ISNUMBER(eb071de1ab08!D39)+ISNUMBER('7b3bd85715a4'!D39)+ISNUMBER(e2a9b537c609!D39)+ISNUMBER(f97457958ce9!D39)+ISNUMBER('281fcc7d7eae'!D39)+ISNUMBER('01454b1cfeba'!D39)+ISNUMBER('79287892b1d7'!D39)+ISNUMBER('1b3f96535b56'!D39),ISNUMBER('1ae03038ed69'!D39)+ISNUMBER('1572eb063e5c'!D39)+ISNUMBER(b6ea66d78823!D39)+ISNUMBER('6d8dcb722ca4'!D39)+ISNUMBER('9306b30af184'!D39)+ISNUMBER('3b760aaeab13'!D39)+ISNUMBER(b2f4402deaee!D39)+ISNUMBER('1c4d314e87cd'!D39)+ISNUMBER(acd4708edfe6!D39)+ISNUMBER('9a32b1f50fb5'!D39)+ISNUMBER('2df562aa32e7'!D39)+ISNUMBER('3a5a3c04bd9d'!D39)+ISNUMBER('192241189337'!D39)+ISNUMBER('23a0423d7f40'!D39)+ISNUMBER('096252bb3796'!D39)+ISNUMBER(a53d1c7f9645!D39)+ISNUMBER('283d32631463'!D39)+ISNUMBER('1a542cfbf2c5'!D39)+ISNUMBER(cf262786a0e1!D39)+ISNUMBER('4b9efdeaeb40'!D39)+ISNUMBER('66fab14edc4c'!D39)+ISNUMBER(d9a84a7879b5!D39)+ISNUMBER(caf2b28627a3!D39)+ISNUMBER('602e9d1875d1'!D39)+ISNUMBER(f168037f7f37!D39)+ISNUMBER(eb071de1ab08!D39)+ISNUMBER('7b3bd85715a4'!D39)+ISNUMBER(e2a9b537c609!D39)+ISNUMBER(f97457958ce9!D39)+ISNUMBER('281fcc7d7eae'!D39)+ISNUMBER('01454b1cfeba'!D39)+ISNUMBER('79287892b1d7'!D39)+ISNUMBER('1b3f96535b56'!D39),"") -> 1 | I26: =IF(ISNUMBER('1ae03038ed69'!E39)+ISNUMBER('1572eb063e5c'!E39)+ISNUMBER(b6ea66d78823!E39)+ISNUMBER('6d8dcb722ca4'!E39)+ISNUMBER('9306b30af184'!E39)+ISNUMBER('3b760aaeab13'!E39)+ISNUMBER(b2f4402deaee!E39)+ISNUMBER('1c4d314e87cd'!E39)+ISNUMBER(acd4708edfe6!E39)+ISNUMBER('9a32b1f50fb5'!E39)+ISNUMBER('2df562aa32e7'!E39)+ISNUMBER('3a5a3c04bd9d'!E39)+ISNUMBER('192241189337'!E39)+ISNUMBER('23a0423d7f40'!E39)+ISNUMBER('096252bb3796'!E39)+ISNUMBER(a53d1c7f9645!E39)+ISNUMBER('283d32631463'!E39)+ISNUMBER('1a542cfbf2c5'!E39)+ISNUMBER(cf262786a0e1!E39)+ISNUMBER('4b9efdeaeb40'!E39)+ISNUMBER('66fab14edc4c'!E39)+ISNUMBER(d9a84a7879b5!E39)+ISNUMBER(caf2b28627a3!E39)+ISNUMBER('602e9d1875d1'!E39)+ISNUMBER(f168037f7f37!E39)+ISNUMBER(eb071de1ab08!E39)+ISNUMBER('7b3bd85715a4'!E39)+ISNUMBER(e2a9b537c609!E39)+ISNUMBER(f97457958ce9!E39)+ISNUMBER('281fcc7d7eae'!E39)+ISNUMBER('01454b1cfeba'!E39)+ISNUMBER('79287892b1d7'!E39)+ISNUMBER('1b3f96535b56'!E39),ISNUMBER('1ae03038ed69'!E39)+ISNUMBER('1572eb063e5c'!E39)+ISNUMBER(b6ea66d78823!E39)+ISNUMBER('6d8dcb722ca4'!E39)+ISNUMBER('9306b30af184'!E39)+ISNUMBER('3b760aaeab13'!E39)+ISNUMBER(b2f4402deaee!E39)+ISNUMBER('1c4d314e87cd'!E39)+ISNUMBER(acd4708edfe6!E39)+ISNUMBER('9a32b1f50fb5'!E39)+ISNUMBER('2df562aa32e7'!E39)+ISNUMBER('3a5a3c04bd9d'!E39)+ISNUMBER('192241189337'!E39)+ISNUMBER('23a0423d7f40'!E39)+ISNUMBER('096252bb3796'!E39)+ISNUMBER(a53d1c7f9645!E39)+ISNUMBER('283d32631463'!E39)+ISNUMBER('1a542cfbf2c5'!E39)+ISNUMBER(cf262786a0e1!E39)+ISNUMBER('4b9efdeaeb40'!E39)+ISNUMBER('66fab14edc4c'!E39)+ISNUMBER(d9a84a7879b5!E39)+ISNUMBER(caf2b28627a3!E39)+ISNUMBER('602e9d1875d1'!E39)+ISNUMBER(f168037f7f37!E39)+ISNUMBER(eb071de1ab08!E39)+ISNUMBER('7b3bd85715a4'!E39)+ISNUMBER(e2a9b537c609!E39)+ISNUMBER(f97457958ce9!E39)+ISNUMBER('281fcc7d7eae'!E39)+ISNUMBER('01454b1cfeba'!E39)+ISNUMBER('79287892b1d7'!E39)+ISNUMBER('1b3f96535b56'!E39),"") -> 1 | J26: =IF(ISNUMBER('1ae03038ed69'!F39)+ISNUMBER('1572eb063e5c'!F39)+ISNUMBER(b6ea66d78823!F39)+ISNUMBER('6d8dcb722ca4'!F39)+ISNUMBER('9306b30af184'!F39)+ISNUMBER('3b760aaeab13'!F39)+ISNUMBER(b2f4402deaee!F39)+ISNUMBER('1c4d314e87cd'!F39)+ISNUMBER(acd4708edfe6!F39)+ISNUMBER('9a32b1f50fb5'!F39)+ISNUMBER('2df562aa32e7'!F39)+ISNUMBER('3a5a3c04bd9d'!F39)+ISNUMBER('192241189337'!F39)+ISNUMBER('23a0423d7f40'!F39)+ISNUMBER('096252bb3796'!F39)+ISNUMBER(a53d1c7f9645!F39)+ISNUMBER('283d32631463'!F39)+ISNUMBER('1a542cfbf2c5'!F39)+ISNUMBER(cf262786a0e1!F39)+ISNUMBER('4b9efdeaeb40'!F39)+ISNUMBER('66fab14edc4c'!F39)+ISNUMBER(d9a84a7879b5!F39)+ISNUMBER(caf2b28627a3!F39)+ISNUMBER('602e9d1875d1'!F39)+ISNUMBER(f168037f7f37!F39)+ISNUMBER(eb071de1ab08!F39)+ISNUMBER('7b3bd85715a4'!F39)+ISNUMBER(e2a9b537c609!F39)+ISNUMBER(f97457958ce9!F39)+ISNUMBER('281fcc7d7eae'!F39)+ISNUMBER('01454b1cfeba'!F39)+ISNUMBER('79287892b1d7'!F39)+ISNUMBER('1b3f96535b56'!F39),ISNUMBER('1ae03038ed69'!F39)+ISNUMBER('1572eb063e5c'!F39)+ISNUMBER(b6ea66d78823!F39)+ISNUMBER('6d8dcb722ca4'!F39)+ISNUMBER('9306b30af184'!F39)+ISNUMBER('3b760aaeab13'!F39)+ISNUMBER(b2f4402deaee!F39)+ISNUMBER('1c4d314e87cd'!F39)+ISNUMBER(acd4708edfe6!F39)+ISNUMBER('9a32b1f50fb5'!F39)+ISNUMBER('2df562aa32e7'!F39)+ISNUMBER('3a5a3c04bd9d'!F39)+ISNUMBER('192241189337'!F39)+ISNUMBER('23a0423d7f40'!F39)+ISNUMBER('096252bb3796'!F39)+ISNUMBER(a53d1c7f9645!F39)+ISNUMBER('283d32631463'!F39)+ISNUMBER('1a542cfbf2c5'!F39)+ISNUMBER(cf262786a0e1!F39)+ISNUMBER('4b9efdeaeb40'!F39)+ISNUMBER('66fab14edc4c'!F39)+ISNUMBER(d9a84a7879b5!F39)+ISNUMBER(caf2b28627a3!F39)+ISNUMBER('602e9d1875d1'!F39)+ISNUMBER(f168037f7f37!F39)+ISNUMBER(eb071de1ab08!F39)+ISNUMBER('7b3bd85715a4'!F39)+ISNUMBER(e2a9b537c609!F39)+ISNUMBER(f97457958ce9!F39)+ISNUMBER('281fcc7d7eae'!F39)+ISNUMBER('01454b1cfeba'!F39)+ISNUMBER('79287892b1d7'!F39)+ISNUMBER('1b3f96535b56'!F39),"") -> 1 | K26: =IF(ISNUMBER('1ae03038ed69'!G39)+ISNUMBER('1572eb063e5c'!G39)+ISNUMBER(b6ea66d78823!G39)+ISNUMBER('6d8dcb722ca4'!G39)+ISNUMBER('9306b30af184'!G39)+ISNUMBER('3b760aaeab13'!G39)+ISNUMBER(b2f4402deaee!G39)+ISNUMBER('1c4d314e87cd'!G39)+ISNUMBER(acd4708edfe6!G39)+ISNUMBER('9a32b1f50fb5'!G39)+ISNUMBER('2df562aa32e7'!G39)+ISNUMBER('3a5a3c04bd9d'!G39)+ISNUMBER('192241189337'!G39)+ISNUMBER('23a0423d7f40'!G39)+ISNUMBER('096252bb3796'!G39)+ISNUMBER(a53d1c7f9645!G39)+ISNUMBER('283d32631463'!G39)+ISNUMBER('1a542cfbf2c5'!G39)+ISNUMBER(cf262786a0e1!G39)+ISNUMBER('4b9efdeaeb40'!G39)+ISNUMBER('66fab14edc4c'!G39)+ISNUMBER(d9a84a7879b5!G39)+ISNUMBER(caf2b28627a3!G39)+ISNUMBER('602e9d1875d1'!G39)+ISNUMBER(f168037f7f37!G39)+ISNUMBER(eb071de1ab08!G39)+ISNUMBER('7b3bd85715a4'!G39)+ISNUMBER(e2a9b537c609!G39)+ISNUMBER(f97457958ce9!G39)+ISNUMBER('281fcc7d7eae'!G39)+ISNUMBER('01454b1cfeba'!G39)+ISNUMBER('79287892b1d7'!G39)+ISNUMBER('1b3f96535b56'!G39),ISNUMBER('1ae03038ed69'!G39)+ISNUMBER('1572eb063e5c'!G39)+ISNUMBER(b6ea66d78823!G39)+ISNUMBER('6d8dcb722ca4'!G39)+ISNUMBER('9306b30af184'!G39)+ISNUMBER('3b760aaeab13'!G39)+ISNUMBER(b2f4402deaee!G39)+ISNUMBER('1c4d314e87cd'!G39)+ISNUMBER(acd4708edfe6!G39)+ISNUMBER('9a32b1f50fb5'!G39)+ISNUMBER('2df562aa32e7'!G39)+ISNUMBER('3a5a3c04bd9d'!G39)+ISNUMBER('192241189337'!G39)+ISNUMBER('23a0423d7f40'!G39)+ISNUMBER('096252bb3796'!G39)+ISNUMBER(a53d1c7f9645!G39)+ISNUMBER('283d32631463'!G39)+ISNUMBER('1a542cfbf2c5'!G39)+ISNUMBER(cf262786a0e1!G39)+ISNUMBER('4b9efdeaeb40'!G39)+ISNUMBER('66fab14edc4c'!G39)+ISNUMBER(d9a84a7879b5!G39)+ISNUMBER(caf2b28627a3!G39)+ISNUMBER('602e9d1875d1'!G39)+ISNUMBER(f168037f7f37!G39)+ISNUMBER(eb071de1ab08!G39)+ISNUMBER('7b3bd85715a4'!G39)+ISNUMBER(e2a9b537c609!G39)+ISNUMBER(f97457958ce9!G39)+ISNUMBER('281fcc7d7eae'!G39)+ISNUMBER('01454b1cfeba'!G39)+ISNUMBER('79287892b1d7'!G39)+ISNUMBER('1b3f96535b56'!G39),"") | L26: =IF(ISNUMBER('1ae03038ed69'!H39)+ISNUMBER('1572eb063e5c'!H39)+ISNUMBER(b6ea66d78823!H39)+ISNUMBER('6d8dcb722ca4'!H39)+ISNUMBER('9306b30af184'!H39)+ISNUMBER('3b760aaeab13'!H39)+ISNUMBER(b2f4402deaee!H39)+ISNUMBER('1c4d314e87cd'!H39)+ISNUMBER(acd4708edfe6!H39)+ISNUMBER('9a32b1f50fb5'!H39)+ISNUMBER('2df562aa32e7'!H39)+ISNUMBER('3a5a3c04bd9d'!H39)+ISNUMBER('192241189337'!H39)+ISNUMBER('23a0423d7f40'!H39)+ISNUMBER('096252bb3796'!H39)+ISNUMBER(a53d1c7f9645!H39)+ISNUMBER('283d32631463'!H39)+ISNUMBER('1a542cfbf2c5'!H39)+ISNUMBER(cf262786a0e1!H39)+ISNUMBER('4b9efdeaeb40'!H39)+ISNUMBER('66fab14edc4c'!H39)+ISNUMBER(d9a84a7879b5!H39)+ISNUMBER(caf2b28627a3!H39)+ISNUMBER('602e9d1875d1'!H39)+ISNUMBER(f168037f7f37!H39)+ISNUMBER(eb071de1ab08!H39)+ISNUMBER('7b3bd85715a4'!H39)+ISNUMBER(e2a9b537c609!H39)+ISNUMBER(f97457958ce9!H39)+ISNUMBER('281fcc7d7eae'!H39)+ISNUMBER('01454b1cfeba'!H39)+ISNUMBER('79287892b1d7'!H39)+ISNUMBER('1b3f96535b56'!H39),ISNUMBER('1ae03038ed69'!H39)+ISNUMBER('1572eb063e5c'!H39)+ISNUMBER(b6ea66d78823!H39)+ISNUMBER('6d8dcb722ca4'!H39)+ISNUMBER('9306b30af184'!H39)+ISNUMBER('3b760aaeab13'!H39)+ISNUMBER(b2f4402deaee!H39)+ISNUMBER('1c4d314e87cd'!H39)+ISNUMBER(acd4708edfe6!H39)+ISNUMBER('9a32b1f50fb5'!H39)+ISNUMBER('2df562aa32e7'!H39)+ISNUMBER('3a5a3c04bd9d'!H39)+ISNUMBER('192241189337'!H39)+ISNUMBER('23a0423d7f40'!H39)+ISNUMBER('096252bb3796'!H39)+ISNUMBER(a53d1c7f9645!H39)+ISNUMBER('283d32631463'!H39)+ISNUMBER('1a542cfbf2c5'!H39)+ISNUMBER(cf262786a0e1!H39)+ISNUMBER('4b9efdeaeb40'!H39)+ISNUMBER('66fab14edc4c'!H39)+ISNUMBER(d9a84a7879b5!H39)+ISNUMBER(caf2b28627a3!H39)+ISNUMBER('602e9d1875d1'!H39)+ISNUMBER(f168037f7f37!H39)+ISNUMBER(eb071de1ab08!H39)+ISNUMBER('7b3bd85715a4'!H39)+ISNUMBER(e2a9b537c609!H39)+ISNUMBER(f97457958ce9!H39)+ISNUMBER('281fcc7d7eae'!H39)+ISNUMBER('01454b1cfeba'!H39)+ISNUMBER('79287892b1d7'!H39)+ISNUMBER('1b3f96535b56'!H39),"") -> 1 | M26: =IF(ISNUMBER('1ae03038ed69'!I39)+ISNUMBER('1572eb063e5c'!I39)+ISNUMBER(b6ea66d78823!I39)+ISNUMBER('6d8dcb722ca4'!I39)+ISNUMBER('9306b30af184'!I39)+ISNUMBER('3b760aaeab13'!I39)+ISNUMBER(b2f4402deaee!I39)+ISNUMBER('1c4d314e87cd'!I39)+ISNUMBER(acd4708edfe6!I39)+ISNUMBER('9a32b1f50fb5'!I39)+ISNUMBER('2df562aa32e7'!I39)+ISNUMBER('3a5a3c04bd9d'!I39)+ISNUMBER('192241189337'!I39)+ISNUMBER('23a0423d7f40'!I39)+ISNUMBER('096252bb3796'!I39)+ISNUMBER(a53d1c7f9645!I39)+ISNUMBER('283d32631463'!I39)+ISNUMBER('1a542cfbf2c5'!I39)+ISNUMBER(cf262786a0e1!I39)+ISNUMBER('4b9efdeaeb40'!I39)+ISNUMBER('66fab14edc4c'!I39)+ISNUMBER(d9a84a7879b5!I39)+ISNUMBER(caf2b28627a3!I39)+ISNUMBER('602e9d1875d1'!I39)+ISNUMBER(f168037f7f37!I39)+ISNUMBER(eb071de1ab08!I39)+ISNUMBER('7b3bd85715a4'!I39)+ISNUMBER(e2a9b537c609!I39)+ISNUMBER(f97457958ce9!I39)+ISNUMBER('281fcc7d7eae'!I39)+ISNUMBER('01454b1cfeba'!I39)+ISNUMBER('79287892b1d7'!I39)+ISNUMBER('1b3f96535b56'!I39),ISNUMBER('1ae03038ed69'!I39)+ISNUMBER('1572eb063e5c'!I39)+ISNUMBER(b6ea66d78823!I39)+ISNUMBER('6d8dcb722ca4'!I39)+ISNUMBER('9306b30af184'!I39)+ISNUMBER('3b760aaeab13'!I39)+ISNUMBER(b2f4402deaee!I39)+ISNUMBER('1c4d314e87cd'!I39)+ISNUMBER(acd4708edfe6!I39)+ISNUMBER('9a32b1f50fb5'!I39)+ISNUMBER('2df562aa32e7'!I39)+ISNUMBER('3a5a3c04bd9d'!I39)+ISNUMBER('192241189337'!I39)+ISNUMBER('23a0423d7f40'!I39)+ISNUMBER('096252bb3796'!I39)+ISNUMBER(a53d1c7f9645!I39)+ISNUMBER('283d32631463'!I39)+ISNUMBER('1a542cfbf2c5'!I39)+ISNUMBER(cf262786a0e1!I39)+ISNUMBER('4b9efdeaeb40'!I39)+ISNUMBER('66fab14edc4c'!I39)+ISNUMBER(d9a84a7879b5!I39)+ISNUMBER(caf2b28627a3!I39)+ISNUMBER('602e9d1875d1'!I39)+ISNUMBER(f168037f7f37!I39)+ISNUMBER(eb071de1ab08!I39)+ISNUMBER('7b3bd85715a4'!I39)+ISNUMBER(e2a9b537c609!I39)+ISNUMBER(f97457958ce9!I39)+ISNUMBER('281fcc7d7eae'!I39)+ISNUMBER('01454b1cfeba'!I39)+ISNUMBER('79287892b1d7'!I39)+ISNUMBER('1b3f96535b56'!I39),"") -> 1 | N26: =IF(ISNUMBER('1ae03038ed69'!J39)+ISNUMBER('1572eb063e5c'!J39)+ISNUMBER(b6ea66d78823!J39)+ISNUMBER('6d8dcb722ca4'!J39)+ISNUMBER('9306b30af184'!J39)+ISNUMBER('3b760aaeab13'!J39)+ISNUMBER(b2f4402deaee!J39)+ISNUMBER('1c4d314e87cd'!J39)+ISNUMBER(acd4708edfe6!J39)+ISNUMBER('9a32b1f50fb5'!J39)+ISNUMBER('2df562aa32e7'!J39)+ISNUMBER('3a5a3c04bd9d'!J39)+ISNUMBER('192241189337'!J39)+ISNUMBER('23a0423d7f40'!J39)+ISNUMBER('096252bb3796'!J39)+ISNUMBER(a53d1c7f9645!J39)+ISNUMBER('283d32631463'!J39)+ISNUMBER('1a542cfbf2c5'!J39)+ISNUMBER(cf262786a0e1!J39)+ISNUMBER('4b9efdeaeb40'!J39)+ISNUMBER('66fab14edc4c'!J39)+ISNUMBER(d9a84a7879b5!J39)+ISNUMBER(caf2b28627a3!J39)+ISNUMBER('602e9d1875d1'!J39)+ISNUMBER(f168037f7f37!J39)+ISNUMBER(eb071de1ab08!J39)+ISNUMBER('7b3bd85715a4'!J39)+ISNUMBER(e2a9b537c609!J39)+ISNUMBER(f97457958ce9!J39)+ISNUMBER('281fcc7d7eae'!J39)+ISNUMBER('01454b1cfeba'!J39)+ISNUMBER('79287892b1d7'!J39)+ISNUMBER('1b3f96535b56'!J39),ISNUMBER('1ae03038ed69'!J39)+ISNUMBER('1572eb063e5c'!J39)+ISNUMBER(b6ea66d78823!J39)+ISNUMBER('6d8dcb722ca4'!J39)+ISNUMBER('9306b30af184'!J39)+ISNUMBER('3b760aaeab13'!J39)+ISNUMBER(b2f4402deaee!J39)+ISNUMBER('1c4d314e87cd'!J39)+ISNUMBER(acd4708edfe6!J39)+ISNUMBER('9a32b1f50fb5'!J39)+ISNUMBER('2df562aa32e7'!J39)+ISNUMBER('3a5a3c04bd9d'!J39)+ISNUMBER('192241189337'!J39)+ISNUMBER('23a0423d7f40'!J39)+ISNUMBER('096252bb3796'!J39)+ISNUMBER(a53d1c7f9645!J39)+ISNUMBER('283d32631463'!J39)+ISNUMBER('1a542cfbf2c5'!J39)+ISNUMBER(cf262786a0e1!J39)+ISNUMBER('4b9efdeaeb40'!J39)+ISNUMBER('66fab14edc4c'!J39)+ISNUMBER(d9a84a7879b5!J39)+ISNUMBER(caf2b28627a3!J39)+ISNUMBER('602e9d1875d1'!J39)+ISNUMBER(f168037f7f37!J39)+ISNUMBER(eb071de1ab08!J39)+ISNUMBER('7b3bd85715a4'!J39)+ISNUMBER(e2a9b537c609!J39)+ISNUMBER(f97457958ce9!J39)+ISNUMBER('281fcc7d7eae'!J39)+ISNUMBER('01454b1cfeba'!J39)+ISNUMBER('79287892b1d7'!J39)+ISNUMBER('1b3f96535b56'!J39),"") -> 1 | ... R26: =IF(ISNUMBER('1ae03038ed69'!N39)+ISNUMBER('1572eb063e5c'!N39)+ISNUMBER(b6ea66d78823!N39)+ISNUMBER('6d8dcb722ca4'!N39)+ISNUMBER('9306b30af184'!N39)+ISNUMBER('3b760aaeab13'!N39)+ISNUMBER(b2f4402deaee!N39)+ISNUMBER('1c4d314e87cd'!N39)+ISNUMBER(acd4708edfe6!N39)+ISNUMBER('9a32b1f50fb5'!N39)+ISNUMBER('2df562aa32e7'!N39)+ISNUMBER('3a5a3c04bd9d'!N39)+ISNUMBER('192241189337'!N39)+ISNUMBER('23a0423d7f40'!N39)+ISNUMBER('096252bb3796'!N39)+ISNUMBER(a53d1c7f9645!N39)+ISNUMBER('283d32631463'!N39)+ISNUMBER('1a542cfbf2c5'!N39)+ISNUMBER(cf262786a0e1!N39)+ISNUMBER('4b9efdeaeb40'!N39)+ISNUMBER('66fab14edc4c'!N39)+ISNUMBER(d9a84a7879b5!N39)+ISNUMBER(caf2b28627a3!N39)+ISNUMBER('602e9d1875d1'!N39)+ISNUMBER(f168037f7f37!N39)+ISNUMBER(eb071de1ab08!N39)+ISNUMBER('7b3bd85715a4'!N39)+ISNUMBER(e2a9b537c609!N39)+ISNUMBER(f97457958ce9!N39)+ISNUMBER('281fcc7d7eae'!N39)+ISNUMBER('01454b1cfeba'!N39)+ISNUMBER('79287892b1d7'!N39)+ISNUMBER('1b3f96535b56'!N39),ISNUMBER('1ae03038ed69'!N39)+ISNUMBER('1572eb063e5c'!N39)+ISNUMBER(b6ea66d78823!N39)+ISNUMBER('6d8dcb722ca4'!N39)+ISNUMBER('9306b30af184'!N39)+ISNUMBER('3b760aaeab13'!N39)+ISNUMBER(b2f4402deaee!N39)+ISNUMBER('1c4d314e87cd'!N39)+ISNUMBER(acd4708edfe6!N39)+ISNUMBER('9a32b1f50fb5'!N39)+ISNUMBER('2df562aa32e7'!N39)+ISNUMBER('3a5a3c04bd9d'!N39)+ISNUMBER('192241189337'!N39)+ISNUMBER('23a0423d7f40'!N39)+ISNUMBER('096252bb3796'!N39)+ISNUMBER(a53d1c7f9645!N39)+ISNUMBER('283d32631463'!N39)+ISNUMBER('1a542cfbf2c5'!N39)+ISNUMBER(cf262786a0e1!N39)+ISNUMBER('4b9efdeaeb40'!N39)+ISNUMBER('66fab14edc4c'!N39)+ISNUMBER(d9a84a7879b5!N39)+ISNUMBER(caf2b28627a3!N39)+ISNUMBER('602e9d1875d1'!N39)+ISNUMBER(f168037f7f37!N39)+ISNUMBER(eb071de1ab08!N39)+ISNUMBER('7b3bd85715a4'!N39)+ISNUMBER(e2a9b537c609!N39)+ISNUMBER(f97457958ce9!N39)+ISNUMBER('281fcc7d7eae'!N39)+ISNUMBER('01454b1cfeba'!N39)+ISNUMBER('79287892b1d7'!N39)+ISNUMBER('1b3f96535b56'!N39),"") | U26: 1a542cfbf2c5 | V26: Building energy demand and savings
F27: =F11 -> Education and capacity bu… | G27: =IF(ISNUMBER('1ae03038ed69'!C40)+ISNUMBER('1572eb063e5c'!C40)+ISNUMBER(b6ea66d78823!C40)+ISNUMBER('6d8dcb722ca4'!C40)+ISNUMBER('9306b30af184'!C40)+ISNUMBER('3b760aaeab13'!C40)+ISNUMBER(b2f4402deaee!C40)+ISNUMBER('1c4d314e87cd'!C40)+ISNUMBER(acd4708edfe6!C40)+ISNUMBER('9a32b1f50fb5'!C40)+ISNUMBER('2df562aa32e7'!C40)+ISNUMBER('3a5a3c04bd9d'!C40)+ISNUMBER('192241189337'!C40)+ISNUMBER('23a0423d7f40'!C40)+ISNUMBER('096252bb3796'!C40)+ISNUMBER(a53d1c7f9645!C40)+ISNUMBER('283d32631463'!C40)+ISNUMBER('1a542cfbf2c5'!C40)+ISNUMBER(cf262786a0e1!C40)+ISNUMBER('4b9efdeaeb40'!C40)+ISNUMBER('66fab14edc4c'!C40)+ISNUMBER(d9a84a7879b5!C40)+ISNUMBER(caf2b28627a3!C40)+ISNUMBER('602e9d1875d1'!C40)+ISNUMBER(f168037f7f37!C40)+ISNUMBER(eb071de1ab08!C40)+ISNUMBER('7b3bd85715a4'!C40)+ISNUMBER(e2a9b537c609!C40)+ISNUMBER(f97457958ce9!C40)+ISNUMBER('281fcc7d7eae'!C40)+ISNUMBER('01454b1cfeba'!C40)+ISNUMBER('79287892b1d7'!C40)+ISNUMBER('1b3f96535b56'!C40),ISNUMBER('1ae03038ed69'!C40)+ISNUMBER('1572eb063e5c'!C40)+ISNUMBER(b6ea66d78823!C40)+ISNUMBER('6d8dcb722ca4'!C40)+ISNUMBER('9306b30af184'!C40)+ISNUMBER('3b760aaeab13'!C40)+ISNUMBER(b2f4402deaee!C40)+ISNUMBER('1c4d314e87cd'!C40)+ISNUMBER(acd4708edfe6!C40)+ISNUMBER('9a32b1f50fb5'!C40)+ISNUMBER('2df562aa32e7'!C40)+ISNUMBER('3a5a3c04bd9d'!C40)+ISNUMBER('192241189337'!C40)+ISNUMBER('23a0423d7f40'!C40)+ISNUMBER('096252bb3796'!C40)+ISNUMBER(a53d1c7f9645!C40)+ISNUMBER('283d32631463'!C40)+ISNUMBER('1a542cfbf2c5'!C40)+ISNUMBER(cf262786a0e1!C40)+ISNUMBER('4b9efdeaeb40'!C40)+ISNUMBER('66fab14edc4c'!C40)+ISNUMBER(d9a84a7879b5!C40)+ISNUMBER(caf2b28627a3!C40)+ISNUMBER('602e9d1875d1'!C40)+ISNUMBER(f168037f7f37!C40)+ISNUMBER(eb071de1ab08!C40)+ISNUMBER('7b3bd85715a4'!C40)+ISNUMBER(e2a9b537c609!C40)+ISNUMBER(f97457958ce9!C40)+ISNUMBER('281fcc7d7eae'!C40)+ISNUMBER('01454b1cfeba'!C40)+ISNUMBER('79287892b1d7'!C40)+ISNUMBER('1b3f96535b56'!C40),"") | H27: =IF(ISNUMBER('1ae03038ed69'!D40)+ISNUMBER('1572eb063e5c'!D40)+ISNUMBER(b6ea66d78823!D40)+ISNUMBER('6d8dcb722ca4'!D40)+ISNUMBER('9306b30af184'!D40)+ISNUMBER('3b760aaeab13'!D40)+ISNUMBER(b2f4402deaee!D40)+ISNUMBER('1c4d314e87cd'!D40)+ISNUMBER(acd4708edfe6!D40)+ISNUMBER('9a32b1f50fb5'!D40)+ISNUMBER('2df562aa32e7'!D40)+ISNUMBER('3a5a3c04bd9d'!D40)+ISNUMBER('192241189337'!D40)+ISNUMBER('23a0423d7f40'!D40)+ISNUMBER('096252bb3796'!D40)+ISNUMBER(a53d1c7f9645!D40)+ISNUMBER('283d32631463'!D40)+ISNUMBER('1a542cfbf2c5'!D40)+ISNUMBER(cf262786a0e1!D40)+ISNUMBER('4b9efdeaeb40'!D40)+ISNUMBER('66fab14edc4c'!D40)+ISNUMBER(d9a84a7879b5!D40)+ISNUMBER(caf2b28627a3!D40)+ISNUMBER('602e9d1875d1'!D40)+ISNUMBER(f168037f7f37!D40)+ISNUMBER(eb071de1ab08!D40)+ISNUMBER('7b3bd85715a4'!D40)+ISNUMBER(e2a9b537c609!D40)+ISNUMBER(f97457958ce9!D40)+ISNUMBER('281fcc7d7eae'!D40)+ISNUMBER('01454b1cfeba'!D40)+ISNUMBER('79287892b1d7'!D40)+ISNUMBER('1b3f96535b56'!D40),ISNUMBER('1ae03038ed69'!D40)+ISNUMBER('1572eb063e5c'!D40)+ISNUMBER(b6ea66d78823!D40)+ISNUMBER('6d8dcb722ca4'!D40)+ISNUMBER('9306b30af184'!D40)+ISNUMBER('3b760aaeab13'!D40)+ISNUMBER(b2f4402deaee!D40)+ISNUMBER('1c4d314e87cd'!D40)+ISNUMBER(acd4708edfe6!D40)+ISNUMBER('9a32b1f50fb5'!D40)+ISNUMBER('2df562aa32e7'!D40)+ISNUMBER('3a5a3c04bd9d'!D40)+ISNUMBER('192241189337'!D40)+ISNUMBER('23a0423d7f40'!D40)+ISNUMBER('096252bb3796'!D40)+ISNUMBER(a53d1c7f9645!D40)+ISNUMBER('283d32631463'!D40)+ISNUMBER('1a542cfbf2c5'!D40)+ISNUMBER(cf262786a0e1!D40)+ISNUMBER('4b9efdeaeb40'!D40)+ISNUMBER('66fab14edc4c'!D40)+ISNUMBER(d9a84a7879b5!D40)+ISNUMBER(caf2b28627a3!D40)+ISNUMBER('602e9d1875d1'!D40)+ISNUMBER(f168037f7f37!D40)+ISNUMBER(eb071de1ab08!D40)+ISNUMBER('7b3bd85715a4'!D40)+ISNUMBER(e2a9b537c609!D40)+ISNUMBER(f97457958ce9!D40)+ISNUMBER('281fcc7d7eae'!D40)+ISNUMBER('01454b1cfeba'!D40)+ISNUMBER('79287892b1d7'!D40)+ISNUMBER('1b3f96535b56'!D40),"") | I27: =IF(ISNUMBER('1ae03038ed69'!E40)+ISNUMBER('1572eb063e5c'!E40)+ISNUMBER(b6ea66d78823!E40)+ISNUMBER('6d8dcb722ca4'!E40)+ISNUMBER('9306b30af184'!E40)+ISNUMBER('3b760aaeab13'!E40)+ISNUMBER(b2f4402deaee!E40)+ISNUMBER('1c4d314e87cd'!E40)+ISNUMBER(acd4708edfe6!E40)+ISNUMBER('9a32b1f50fb5'!E40)+ISNUMBER('2df562aa32e7'!E40)+ISNUMBER('3a5a3c04bd9d'!E40)+ISNUMBER('192241189337'!E40)+ISNUMBER('23a0423d7f40'!E40)+ISNUMBER('096252bb3796'!E40)+ISNUMBER(a53d1c7f9645!E40)+ISNUMBER('283d32631463'!E40)+ISNUMBER('1a542cfbf2c5'!E40)+ISNUMBER(cf262786a0e1!E40)+ISNUMBER('4b9efdeaeb40'!E40)+ISNUMBER('66fab14edc4c'!E40)+ISNUMBER(d9a84a7879b5!E40)+ISNUMBER(caf2b28627a3!E40)+ISNUMBER('602e9d1875d1'!E40)+ISNUMBER(f168037f7f37!E40)+ISNUMBER(eb071de1ab08!E40)+ISNUMBER('7b3bd85715a4'!E40)+ISNUMBER(e2a9b537c609!E40)+ISNUMBER(f97457958ce9!E40)+ISNUMBER('281fcc7d7eae'!E40)+ISNUMBER('01454b1cfeba'!E40)+ISNUMBER('79287892b1d7'!E40)+ISNUMBER('1b3f96535b56'!E40),ISNUMBER('1ae03038ed69'!E40)+ISNUMBER('1572eb063e5c'!E40)+ISNUMBER(b6ea66d78823!E40)+ISNUMBER('6d8dcb722ca4'!E40)+ISNUMBER('9306b30af184'!E40)+ISNUMBER('3b760aaeab13'!E40)+ISNUMBER(b2f4402deaee!E40)+ISNUMBER('1c4d314e87cd'!E40)+ISNUMBER(acd4708edfe6!E40)+ISNUMBER('9a32b1f50fb5'!E40)+ISNUMBER('2df562aa32e7'!E40)+ISNUMBER('3a5a3c04bd9d'!E40)+ISNUMBER('192241189337'!E40)+ISNUMBER('23a0423d7f40'!E40)+ISNUMBER('096252bb3796'!E40)+ISNUMBER(a53d1c7f9645!E40)+ISNUMBER('283d32631463'!E40)+ISNUMBER('1a542cfbf2c5'!E40)+ISNUMBER(cf262786a0e1!E40)+ISNUMBER('4b9efdeaeb40'!E40)+ISNUMBER('66fab14edc4c'!E40)+ISNUMBER(d9a84a7879b5!E40)+ISNUMBER(caf2b28627a3!E40)+ISNUMBER('602e9d1875d1'!E40)+ISNUMBER(f168037f7f37!E40)+ISNUMBER(eb071de1ab08!E40)+ISNUMBER('7b3bd85715a4'!E40)+ISNUMBER(e2a9b537c609!E40)+ISNUMBER(f97457958ce9!E40)+ISNUMBER('281fcc7d7eae'!E40)+ISNUMBER('01454b1cfeba'!E40)+ISNUMBER('79287892b1d7'!E40)+ISNUMBER('1b3f96535b56'!E40),"") -> 3 | J27: =IF(ISNUMBER('1ae03038ed69'!F40)+ISNUMBER('1572eb063e5c'!F40)+ISNUMBER(b6ea66d78823!F40)+ISNUMBER('6d8dcb722ca4'!F40)+ISNUMBER('9306b30af184'!F40)+ISNUMBER('3b760aaeab13'!F40)+ISNUMBER(b2f4402deaee!F40)+ISNUMBER('1c4d314e87cd'!F40)+ISNUMBER(acd4708edfe6!F40)+ISNUMBER('9a32b1f50fb5'!F40)+ISNUMBER('2df562aa32e7'!F40)+ISNUMBER('3a5a3c04bd9d'!F40)+ISNUMBER('192241189337'!F40)+ISNUMBER('23a0423d7f40'!F40)+ISNUMBER('096252bb3796'!F40)+ISNUMBER(a53d1c7f9645!F40)+ISNUMBER('283d32631463'!F40)+ISNUMBER('1a542cfbf2c5'!F40)+ISNUMBER(cf262786a0e1!F40)+ISNUMBER('4b9efdeaeb40'!F40)+ISNUMBER('66fab14edc4c'!F40)+ISNUMBER(d9a84a7879b5!F40)+ISNUMBER(caf2b28627a3!F40)+ISNUMBER('602e9d1875d1'!F40)+ISNUMBER(f168037f7f37!F40)+ISNUMBER(eb071de1ab08!F40)+ISNUMBER('7b3bd85715a4'!F40)+ISNUMBER(e2a9b537c609!F40)+ISNUMBER(f97457958ce9!F40)+ISNUMBER('281fcc7d7eae'!F40)+ISNUMBER('01454b1cfeba'!F40)+ISNUMBER('79287892b1d7'!F40)+ISNUMBER('1b3f96535b56'!F40),ISNUMBER('1ae03038ed69'!F40)+ISNUMBER('1572eb063e5c'!F40)+ISNUMBER(b6ea66d78823!F40)+ISNUMBER('6d8dcb722ca4'!F40)+ISNUMBER('9306b30af184'!F40)+ISNUMBER('3b760aaeab13'!F40)+ISNUMBER(b2f4402deaee!F40)+ISNUMBER('1c4d314e87cd'!F40)+ISNUMBER(acd4708edfe6!F40)+ISNUMBER('9a32b1f50fb5'!F40)+ISNUMBER('2df562aa32e7'!F40)+ISNUMBER('3a5a3c04bd9d'!F40)+ISNUMBER('192241189337'!F40)+ISNUMBER('23a0423d7f40'!F40)+ISNUMBER('096252bb3796'!F40)+ISNUMBER(a53d1c7f9645!F40)+ISNUMBER('283d32631463'!F40)+ISNUMBER('1a542cfbf2c5'!F40)+ISNUMBER(cf262786a0e1!F40)+ISNUMBER('4b9efdeaeb40'!F40)+ISNUMBER('66fab14edc4c'!F40)+ISNUMBER(d9a84a7879b5!F40)+ISNUMBER(caf2b28627a3!F40)+ISNUMBER('602e9d1875d1'!F40)+ISNUMBER(f168037f7f37!F40)+ISNUMBER(eb071de1ab08!F40)+ISNUMBER('7b3bd85715a4'!F40)+ISNUMBER(e2a9b537c609!F40)+ISNUMBER(f97457958ce9!F40)+ISNUMBER('281fcc7d7eae'!F40)+ISNUMBER('01454b1cfeba'!F40)+ISNUMBER('79287892b1d7'!F40)+ISNUMBER('1b3f96535b56'!F40),"") -> 1 | K27: =IF(ISNUMBER('1ae03038ed69'!G40)+ISNUMBER('1572eb063e5c'!G40)+ISNUMBER(b6ea66d78823!G40)+ISNUMBER('6d8dcb722ca4'!G40)+ISNUMBER('9306b30af184'!G40)+ISNUMBER('3b760aaeab13'!G40)+ISNUMBER(b2f4402deaee!G40)+ISNUMBER('1c4d314e87cd'!G40)+ISNUMBER(acd4708edfe6!G40)+ISNUMBER('9a32b1f50fb5'!G40)+ISNUMBER('2df562aa32e7'!G40)+ISNUMBER('3a5a3c04bd9d'!G40)+ISNUMBER('192241189337'!G40)+ISNUMBER('23a0423d7f40'!G40)+ISNUMBER('096252bb3796'!G40)+ISNUMBER(a53d1c7f9645!G40)+ISNUMBER('283d32631463'!G40)+ISNUMBER('1a542cfbf2c5'!G40)+ISNUMBER(cf262786a0e1!G40)+ISNUMBER('4b9efdeaeb40'!G40)+ISNUMBER('66fab14edc4c'!G40)+ISNUMBER(d9a84a7879b5!G40)+ISNUMBER(caf2b28627a3!G40)+ISNUMBER('602e9d1875d1'!G40)+ISNUMBER(f168037f7f37!G40)+ISNUMBER(eb071de1ab08!G40)+ISNUMBER('7b3bd85715a4'!G40)+ISNUMBER(e2a9b537c609!G40)+ISNUMBER(f97457958ce9!G40)+ISNUMBER('281fcc7d7eae'!G40)+ISNUMBER('01454b1cfeba'!G40)+ISNUMBER('79287892b1d7'!G40)+ISNUMBER('1b3f96535b56'!G40),ISNUMBER('1ae03038ed69'!G40)+ISNUMBER('1572eb063e5c'!G40)+ISNUMBER(b6ea66d78823!G40)+ISNUMBER('6d8dcb722ca4'!G40)+ISNUMBER('9306b30af184'!G40)+ISNUMBER('3b760aaeab13'!G40)+ISNUMBER(b2f4402deaee!G40)+ISNUMBER('1c4d314e87cd'!G40)+ISNUMBER(acd4708edfe6!G40)+ISNUMBER('9a32b1f50fb5'!G40)+ISNUMBER('2df562aa32e7'!G40)+ISNUMBER('3a5a3c04bd9d'!G40)+ISNUMBER('192241189337'!G40)+ISNUMBER('23a0423d7f40'!G40)+ISNUMBER('096252bb3796'!G40)+ISNUMBER(a53d1c7f9645!G40)+ISNUMBER('283d32631463'!G40)+ISNUMBER('1a542cfbf2c5'!G40)+ISNUMBER(cf262786a0e1!G40)+ISNUMBER('4b9efdeaeb40'!G40)+ISNUMBER('66fab14edc4c'!G40)+ISNUMBER(d9a84a7879b5!G40)+ISNUMBER(caf2b28627a3!G40)+ISNUMBER('602e9d1875d1'!G40)+ISNUMBER(f168037f7f37!G40)+ISNUMBER(eb071de1ab08!G40)+ISNUMBER('7b3bd85715a4'!G40)+ISNUMBER(e2a9b537c609!G40)+ISNUMBER(f97457958ce9!G40)+ISNUMBER('281fcc7d7eae'!G40)+ISNUMBER('01454b1cfeba'!G40)+ISNUMBER('79287892b1d7'!G40)+ISNUMBER('1b3f96535b56'!G40),"") | L27: =IF(ISNUMBER('1ae03038ed69'!H40)+ISNUMBER('1572eb063e5c'!H40)+ISNUMBER(b6ea66d78823!H40)+ISNUMBER('6d8dcb722ca4'!H40)+ISNUMBER('9306b30af184'!H40)+ISNUMBER('3b760aaeab13'!H40)+ISNUMBER(b2f4402deaee!H40)+ISNUMBER('1c4d314e87cd'!H40)+ISNUMBER(acd4708edfe6!H40)+ISNUMBER('9a32b1f50fb5'!H40)+ISNUMBER('2df562aa32e7'!H40)+ISNUMBER('3a5a3c04bd9d'!H40)+ISNUMBER('192241189337'!H40)+ISNUMBER('23a0423d7f40'!H40)+ISNUMBER('096252bb3796'!H40)+ISNUMBER(a53d1c7f9645!H40)+ISNUMBER('283d32631463'!H40)+ISNUMBER('1a542cfbf2c5'!H40)+ISNUMBER(cf262786a0e1!H40)+ISNUMBER('4b9efdeaeb40'!H40)+ISNUMBER('66fab14edc4c'!H40)+ISNUMBER(d9a84a7879b5!H40)+ISNUMBER(caf2b28627a3!H40)+ISNUMBER('602e9d1875d1'!H40)+ISNUMBER(f168037f7f37!H40)+ISNUMBER(eb071de1ab08!H40)+ISNUMBER('7b3bd85715a4'!H40)+ISNUMBER(e2a9b537c609!H40)+ISNUMBER(f97457958ce9!H40)+ISNUMBER('281fcc7d7eae'!H40)+ISNUMBER('01454b1cfeba'!H40)+ISNUMBER('79287892b1d7'!H40)+ISNUMBER('1b3f96535b56'!H40),ISNUMBER('1ae03038ed69'!H40)+ISNUMBER('1572eb063e5c'!H40)+ISNUMBER(b6ea66d78823!H40)+ISNUMBER('6d8dcb722ca4'!H40)+ISNUMBER('9306b30af184'!H40)+ISNUMBER('3b760aaeab13'!H40)+ISNUMBER(b2f4402deaee!H40)+ISNUMBER('1c4d314e87cd'!H40)+ISNUMBER(acd4708edfe6!H40)+ISNUMBER('9a32b1f50fb5'!H40)+ISNUMBER('2df562aa32e7'!H40)+ISNUMBER('3a5a3c04bd9d'!H40)+ISNUMBER('192241189337'!H40)+ISNUMBER('23a0423d7f40'!H40)+ISNUMBER('096252bb3796'!H40)+ISNUMBER(a53d1c7f9645!H40)+ISNUMBER('283d32631463'!H40)+ISNUMBER('1a542cfbf2c5'!H40)+ISNUMBER(cf262786a0e1!H40)+ISNUMBER('4b9efdeaeb40'!H40)+ISNUMBER('66fab14edc4c'!H40)+ISNUMBER(d9a84a7879b5!H40)+ISNUMBER(caf2b28627a3!H40)+ISNUMBER('602e9d1875d1'!H40)+ISNUMBER(f168037f7f37!H40)+ISNUMBER(eb071de1ab08!H40)+ISNUMBER('7b3bd85715a4'!H40)+ISNUMBER(e2a9b537c609!H40)+ISNUMBER(f97457958ce9!H40)+ISNUMBER('281fcc7d7eae'!H40)+ISNUMBER('01454b1cfeba'!H40)+ISNUMBER('79287892b1d7'!H40)+ISNUMBER('1b3f96535b56'!H40),"") | M27: =IF(ISNUMBER('1ae03038ed69'!I40)+ISNUMBER('1572eb063e5c'!I40)+ISNUMBER(b6ea66d78823!I40)+ISNUMBER('6d8dcb722ca4'!I40)+ISNUMBER('9306b30af184'!I40)+ISNUMBER('3b760aaeab13'!I40)+ISNUMBER(b2f4402deaee!I40)+ISNUMBER('1c4d314e87cd'!I40)+ISNUMBER(acd4708edfe6!I40)+ISNUMBER('9a32b1f50fb5'!I40)+ISNUMBER('2df562aa32e7'!I40)+ISNUMBER('3a5a3c04bd9d'!I40)+ISNUMBER('192241189337'!I40)+ISNUMBER('23a0423d7f40'!I40)+ISNUMBER('096252bb3796'!I40)+ISNUMBER(a53d1c7f9645!I40)+ISNUMBER('283d32631463'!I40)+ISNUMBER('1a542cfbf2c5'!I40)+ISNUMBER(cf262786a0e1!I40)+ISNUMBER('4b9efdeaeb40'!I40)+ISNUMBER('66fab14edc4c'!I40)+ISNUMBER(d9a84a7879b5!I40)+ISNUMBER(caf2b28627a3!I40)+ISNUMBER('602e9d1875d1'!I40)+ISNUMBER(f168037f7f37!I40)+ISNUMBER(eb071de1ab08!I40)+ISNUMBER('7b3bd85715a4'!I40)+ISNUMBER(e2a9b537c609!I40)+ISNUMBER(f97457958ce9!I40)+ISNUMBER('281fcc7d7eae'!I40)+ISNUMBER('01454b1cfeba'!I40)+ISNUMBER('79287892b1d7'!I40)+ISNUMBER('1b3f96535b56'!I40),ISNUMBER('1ae03038ed69'!I40)+ISNUMBER('1572eb063e5c'!I40)+ISNUMBER(b6ea66d78823!I40)+ISNUMBER('6d8dcb722ca4'!I40)+ISNUMBER('9306b30af184'!I40)+ISNUMBER('3b760aaeab13'!I40)+ISNUMBER(b2f4402deaee!I40)+ISNUMBER('1c4d314e87cd'!I40)+ISNUMBER(acd4708edfe6!I40)+ISNUMBER('9a32b1f50fb5'!I40)+ISNUMBER('2df562aa32e7'!I40)+ISNUMBER('3a5a3c04bd9d'!I40)+ISNUMBER('192241189337'!I40)+ISNUMBER('23a0423d7f40'!I40)+ISNUMBER('096252bb3796'!I40)+ISNUMBER(a53d1c7f9645!I40)+ISNUMBER('283d32631463'!I40)+ISNUMBER('1a542cfbf2c5'!I40)+ISNUMBER(cf262786a0e1!I40)+ISNUMBER('4b9efdeaeb40'!I40)+ISNUMBER('66fab14edc4c'!I40)+ISNUMBER(d9a84a7879b5!I40)+ISNUMBER(caf2b28627a3!I40)+ISNUMBER('602e9d1875d1'!I40)+ISNUMBER(f168037f7f37!I40)+ISNUMBER(eb071de1ab08!I40)+ISNUMBER('7b3bd85715a4'!I40)+ISNUMBER(e2a9b537c609!I40)+ISNUMBER(f97457958ce9!I40)+ISNUMBER('281fcc7d7eae'!I40)+ISNUMBER('01454b1cfeba'!I40)+ISNUMBER('79287892b1d7'!I40)+ISNUMBER('1b3f96535b56'!I40),"") | N27: =IF(ISNUMBER('1ae03038ed69'!J40)+ISNUMBER('1572eb063e5c'!J40)+ISNUMBER(b6ea66d78823!J40)+ISNUMBER('6d8dcb722ca4'!J40)+ISNUMBER('9306b30af184'!J40)+ISNUMBER('3b760aaeab13'!J40)+ISNUMBER(b2f4402deaee!J40)+ISNUMBER('1c4d314e87cd'!J40)+ISNUMBER(acd4708edfe6!J40)+ISNUMBER('9a32b1f50fb5'!J40)+ISNUMBER('2df562aa32e7'!J40)+ISNUMBER('3a5a3c04bd9d'!J40)+ISNUMBER('192241189337'!J40)+ISNUMBER('23a0423d7f40'!J40)+ISNUMBER('096252bb3796'!J40)+ISNUMBER(a53d1c7f9645!J40)+ISNUMBER('283d32631463'!J40)+ISNUMBER('1a542cfbf2c5'!J40)+ISNUMBER(cf262786a0e1!J40)+ISNUMBER('4b9efdeaeb40'!J40)+ISNUMBER('66fab14edc4c'!J40)+ISNUMBER(d9a84a7879b5!J40)+ISNUMBER(caf2b28627a3!J40)+ISNUMBER('602e9d1875d1'!J40)+ISNUMBER(f168037f7f37!J40)+ISNUMBER(eb071de1ab08!J40)+ISNUMBER('7b3bd85715a4'!J40)+ISNUMBER(e2a9b537c609!J40)+ISNUMBER(f97457958ce9!J40)+ISNUMBER('281fcc7d7eae'!J40)+ISNUMBER('01454b1cfeba'!J40)+ISNUMBER('79287892b1d7'!J40)+ISNUMBER('1b3f96535b56'!J40),ISNUMBER('1ae03038ed69'!J40)+ISNUMBER('1572eb063e5c'!J40)+ISNUMBER(b6ea66d78823!J40)+ISNUMBER('6d8dcb722ca4'!J40)+ISNUMBER('9306b30af184'!J40)+ISNUMBER('3b760aaeab13'!J40)+ISNUMBER(b2f4402deaee!J40)+ISNUMBER('1c4d314e87cd'!J40)+ISNUMBER(acd4708edfe6!J40)+ISNUMBER('9a32b1f50fb5'!J40)+ISNUMBER('2df562aa32e7'!J40)+ISNUMBER('3a5a3c04bd9d'!J40)+ISNUMBER('192241189337'!J40)+ISNUMBER('23a0423d7f40'!J40)+ISNUMBER('096252bb3796'!J40)+ISNUMBER(a53d1c7f9645!J40)+ISNUMBER('283d32631463'!J40)+ISNUMBER('1a542cfbf2c5'!J40)+ISNUMBER(cf262786a0e1!J40)+ISNUMBER('4b9efdeaeb40'!J40)+ISNUMBER('66fab14edc4c'!J40)+ISNUMBER(d9a84a7879b5!J40)+ISNUMBER(caf2b28627a3!J40)+ISNUMBER('602e9d1875d1'!J40)+ISNUMBER(f168037f7f37!J40)+ISNUMBER(eb071de1ab08!J40)+ISNUMBER('7b3bd85715a4'!J40)+ISNUMBER(e2a9b537c609!J40)+ISNUMBER(f97457958ce9!J40)+ISNUMBER('281fcc7d7eae'!J40)+ISNUMBER('01454b1cfeba'!J40)+ISNUMBER('79287892b1d7'!J40)+ISNUMBER('1b3f96535b56'!J40),"") | ... R27: =IF(ISNUMBER('1ae03038ed69'!N40)+ISNUMBER('1572eb063e5c'!N40)+ISNUMBER(b6ea66d78823!N40)+ISNUMBER('6d8dcb722ca4'!N40)+ISNUMBER('9306b30af184'!N40)+ISNUMBER('3b760aaeab13'!N40)+ISNUMBER(b2f4402deaee!N40)+ISNUMBER('1c4d314e87cd'!N40)+ISNUMBER(acd4708edfe6!N40)+ISNUMBER('9a32b1f50fb5'!N40)+ISNUMBER('2df562aa32e7'!N40)+ISNUMBER('3a5a3c04bd9d'!N40)+ISNUMBER('192241189337'!N40)+ISNUMBER('23a0423d7f40'!N40)+ISNUMBER('096252bb3796'!N40)+ISNUMBER(a53d1c7f9645!N40)+ISNUMBER('283d32631463'!N40)+ISNUMBER('1a542cfbf2c5'!N40)+ISNUMBER(cf262786a0e1!N40)+ISNUMBER('4b9efdeaeb40'!N40)+ISNUMBER('66fab14edc4c'!N40)+ISNUMBER(d9a84a7879b5!N40)+ISNUMBER(caf2b28627a3!N40)+ISNUMBER('602e9d1875d1'!N40)+ISNUMBER(f168037f7f37!N40)+ISNUMBER(eb071de1ab08!N40)+ISNUMBER('7b3bd85715a4'!N40)+ISNUMBER(e2a9b537c609!N40)+ISNUMBER(f97457958ce9!N40)+ISNUMBER('281fcc7d7eae'!N40)+ISNUMBER('01454b1cfeba'!N40)+ISNUMBER('79287892b1d7'!N40)+ISNUMBER('1b3f96535b56'!N40),ISNUMBER('1ae03038ed69'!N40)+ISNUMBER('1572eb063e5c'!N40)+ISNUMBER(b6ea66d78823!N40)+ISNUMBER('6d8dcb722ca4'!N40)+ISNUMBER('9306b30af184'!N40)+ISNUMBER('3b760aaeab13'!N40)+ISNUMBER(b2f4402deaee!N40)+ISNUMBER('1c4d314e87cd'!N40)+ISNUMBER(acd4708edfe6!N40)+ISNUMBER('9a32b1f50fb5'!N40)+ISNUMBER('2df562aa32e7'!N40)+ISNUMBER('3a5a3c04bd9d'!N40)+ISNUMBER('192241189337'!N40)+ISNUMBER('23a0423d7f40'!N40)+ISNUMBER('096252bb3796'!N40)+ISNUMBER(a53d1c7f9645!N40)+ISNUMBER('283d32631463'!N40)+ISNUMBER('1a542cfbf2c5'!N40)+ISNUMBER(cf262786a0e1!N40)+ISNUMBER('4b9efdeaeb40'!N40)+ISNUMBER('66fab14edc4c'!N40)+ISNUMBER(d9a84a7879b5!N40)+ISNUMBER(caf2b28627a3!N40)+ISNUMBER('602e9d1875d1'!N40)+ISNUMBER(f168037f7f37!N40)+ISNUMBER(eb071de1ab08!N40)+ISNUMBER('7b3bd85715a4'!N40)+ISNUMBER(e2a9b537c609!N40)+ISNUMBER(f97457958ce9!N40)+ISNUMBER('281fcc7d7eae'!N40)+ISNUMBER('01454b1cfeba'!N40)+ISNUMBER('79287892b1d7'!N40)+ISNUMBER('1b3f96535b56'!N40),"") | U27: cf262786a0e1 | V27: Reduce building energy, meet certifications.
F28: =F12 -> Innovation, creativity an… | G28: =IF(ISNUMBER('1ae03038ed69'!C41)+ISNUMBER('1572eb063e5c'!C41)+ISNUMBER(b6ea66d78823!C41)+ISNUMBER('6d8dcb722ca4'!C41)+ISNUMBER('9306b30af184'!C41)+ISNUMBER('3b760aaeab13'!C41)+ISNUMBER(b2f4402deaee!C41)+ISNUMBER('1c4d314e87cd'!C41)+ISNUMBER(acd4708edfe6!C41)+ISNUMBER('9a32b1f50fb5'!C41)+ISNUMBER('2df562aa32e7'!C41)+ISNUMBER('3a5a3c04bd9d'!C41)+ISNUMBER('192241189337'!C41)+ISNUMBER('23a0423d7f40'!C41)+ISNUMBER('096252bb3796'!C41)+ISNUMBER(a53d1c7f9645!C41)+ISNUMBER('283d32631463'!C41)+ISNUMBER('1a542cfbf2c5'!C41)+ISNUMBER(cf262786a0e1!C41)+ISNUMBER('4b9efdeaeb40'!C41)+ISNUMBER('66fab14edc4c'!C41)+ISNUMBER(d9a84a7879b5!C41)+ISNUMBER(caf2b28627a3!C41)+ISNUMBER('602e9d1875d1'!C41)+ISNUMBER(f168037f7f37!C41)+ISNUMBER(eb071de1ab08!C41)+ISNUMBER('7b3bd85715a4'!C41)+ISNUMBER(e2a9b537c609!C41)+ISNUMBER(f97457958ce9!C41)+ISNUMBER('281fcc7d7eae'!C41)+ISNUMBER('01454b1cfeba'!C41)+ISNUMBER('79287892b1d7'!C41)+ISNUMBER('1b3f96535b56'!C41),ISNUMBER('1ae03038ed69'!C41)+ISNUMBER('1572eb063e5c'!C41)+ISNUMBER(b6ea66d78823!C41)+ISNUMBER('6d8dcb722ca4'!C41)+ISNUMBER('9306b30af184'!C41)+ISNUMBER('3b760aaeab13'!C41)+ISNUMBER(b2f4402deaee!C41)+ISNUMBER('1c4d314e87cd'!C41)+ISNUMBER(acd4708edfe6!C41)+ISNUMBER('9a32b1f50fb5'!C41)+ISNUMBER('2df562aa32e7'!C41)+ISNUMBER('3a5a3c04bd9d'!C41)+ISNUMBER('192241189337'!C41)+ISNUMBER('23a0423d7f40'!C41)+ISNUMBER('096252bb3796'!C41)+ISNUMBER(a53d1c7f9645!C41)+ISNUMBER('283d32631463'!C41)+ISNUMBER('1a542cfbf2c5'!C41)+ISNUMBER(cf262786a0e1!C41)+ISNUMBER('4b9efdeaeb40'!C41)+ISNUMBER('66fab14edc4c'!C41)+ISNUMBER(d9a84a7879b5!C41)+ISNUMBER(caf2b28627a3!C41)+ISNUMBER('602e9d1875d1'!C41)+ISNUMBER(f168037f7f37!C41)+ISNUMBER(eb071de1ab08!C41)+ISNUMBER('7b3bd85715a4'!C41)+ISNUMBER(e2a9b537c609!C41)+ISNUMBER(f97457958ce9!C41)+ISNUMBER('281fcc7d7eae'!C41)+ISNUMBER('01454b1cfeba'!C41)+ISNUMBER('79287892b1d7'!C41)+ISNUMBER('1b3f96535b56'!C41),"") -> 1 | H28: =IF(ISNUMBER('1ae03038ed69'!D41)+ISNUMBER('1572eb063e5c'!D41)+ISNUMBER(b6ea66d78823!D41)+ISNUMBER('6d8dcb722ca4'!D41)+ISNUMBER('9306b30af184'!D41)+ISNUMBER('3b760aaeab13'!D41)+ISNUMBER(b2f4402deaee!D41)+ISNUMBER('1c4d314e87cd'!D41)+ISNUMBER(acd4708edfe6!D41)+ISNUMBER('9a32b1f50fb5'!D41)+ISNUMBER('2df562aa32e7'!D41)+ISNUMBER('3a5a3c04bd9d'!D41)+ISNUMBER('192241189337'!D41)+ISNUMBER('23a0423d7f40'!D41)+ISNUMBER('096252bb3796'!D41)+ISNUMBER(a53d1c7f9645!D41)+ISNUMBER('283d32631463'!D41)+ISNUMBER('1a542cfbf2c5'!D41)+ISNUMBER(cf262786a0e1!D41)+ISNUMBER('4b9efdeaeb40'!D41)+ISNUMBER('66fab14edc4c'!D41)+ISNUMBER(d9a84a7879b5!D41)+ISNUMBER(caf2b28627a3!D41)+ISNUMBER('602e9d1875d1'!D41)+ISNUMBER(f168037f7f37!D41)+ISNUMBER(eb071de1ab08!D41)+ISNUMBER('7b3bd85715a4'!D41)+ISNUMBER(e2a9b537c609!D41)+ISNUMBER(f97457958ce9!D41)+ISNUMBER('281fcc7d7eae'!D41)+ISNUMBER('01454b1cfeba'!D41)+ISNUMBER('79287892b1d7'!D41)+ISNUMBER('1b3f96535b56'!D41),ISNUMBER('1ae03038ed69'!D41)+ISNUMBER('1572eb063e5c'!D41)+ISNUMBER(b6ea66d78823!D41)+ISNUMBER('6d8dcb722ca4'!D41)+ISNUMBER('9306b30af184'!D41)+ISNUMBER('3b760aaeab13'!D41)+ISNUMBER(b2f4402deaee!D41)+ISNUMBER('1c4d314e87cd'!D41)+ISNUMBER(acd4708edfe6!D41)+ISNUMBER('9a32b1f50fb5'!D41)+ISNUMBER('2df562aa32e7'!D41)+ISNUMBER('3a5a3c04bd9d'!D41)+ISNUMBER('192241189337'!D41)+ISNUMBER('23a0423d7f40'!D41)+ISNUMBER('096252bb3796'!D41)+ISNUMBER(a53d1c7f9645!D41)+ISNUMBER('283d32631463'!D41)+ISNUMBER('1a542cfbf2c5'!D41)+ISNUMBER(cf262786a0e1!D41)+ISNUMBER('4b9efdeaeb40'!D41)+ISNUMBER('66fab14edc4c'!D41)+ISNUMBER(d9a84a7879b5!D41)+ISNUMBER(caf2b28627a3!D41)+ISNUMBER('602e9d1875d1'!D41)+ISNUMBER(f168037f7f37!D41)+ISNUMBER(eb071de1ab08!D41)+ISNUMBER('7b3bd85715a4'!D41)+ISNUMBER(e2a9b537c609!D41)+ISNUMBER(f97457958ce9!D41)+ISNUMBER('281fcc7d7eae'!D41)+ISNUMBER('01454b1cfeba'!D41)+ISNUMBER('79287892b1d7'!D41)+ISNUMBER('1b3f96535b56'!D41),"") -> 1 | I28: =IF(ISNUMBER('1ae03038ed69'!E41)+ISNUMBER('1572eb063e5c'!E41)+ISNUMBER(b6ea66d78823!E41)+ISNUMBER('6d8dcb722ca4'!E41)+ISNUMBER('9306b30af184'!E41)+ISNUMBER('3b760aaeab13'!E41)+ISNUMBER(b2f4402deaee!E41)+ISNUMBER('1c4d314e87cd'!E41)+ISNUMBER(acd4708edfe6!E41)+ISNUMBER('9a32b1f50fb5'!E41)+ISNUMBER('2df562aa32e7'!E41)+ISNUMBER('3a5a3c04bd9d'!E41)+ISNUMBER('192241189337'!E41)+ISNUMBER('23a0423d7f40'!E41)+ISNUMBER('096252bb3796'!E41)+ISNUMBER(a53d1c7f9645!E41)+ISNUMBER('283d32631463'!E41)+ISNUMBER('1a542cfbf2c5'!E41)+ISNUMBER(cf262786a0e1!E41)+ISNUMBER('4b9efdeaeb40'!E41)+ISNUMBER('66fab14edc4c'!E41)+ISNUMBER(d9a84a7879b5!E41)+ISNUMBER(caf2b28627a3!E41)+ISNUMBER('602e9d1875d1'!E41)+ISNUMBER(f168037f7f37!E41)+ISNUMBER(eb071de1ab08!E41)+ISNUMBER('7b3bd85715a4'!E41)+ISNUMBER(e2a9b537c609!E41)+ISNUMBER(f97457958ce9!E41)+ISNUMBER('281fcc7d7eae'!E41)+ISNUMBER('01454b1cfeba'!E41)+ISNUMBER('79287892b1d7'!E41)+ISNUMBER('1b3f96535b56'!E41),ISNUMBER('1ae03038ed69'!E41)+ISNUMBER('1572eb063e5c'!E41)+ISNUMBER(b6ea66d78823!E41)+ISNUMBER('6d8dcb722ca4'!E41)+ISNUMBER('9306b30af184'!E41)+ISNUMBER('3b760aaeab13'!E41)+ISNUMBER(b2f4402deaee!E41)+ISNUMBER('1c4d314e87cd'!E41)+ISNUMBER(acd4708edfe6!E41)+ISNUMBER('9a32b1f50fb5'!E41)+ISNUMBER('2df562aa32e7'!E41)+ISNUMBER('3a5a3c04bd9d'!E41)+ISNUMBER('192241189337'!E41)+ISNUMBER('23a0423d7f40'!E41)+ISNUMBER('096252bb3796'!E41)+ISNUMBER(a53d1c7f9645!E41)+ISNUMBER('283d32631463'!E41)+ISNUMBER('1a542cfbf2c5'!E41)+ISNUMBER(cf262786a0e1!E41)+ISNUMBER('4b9efdeaeb40'!E41)+ISNUMBER('66fab14edc4c'!E41)+ISNUMBER(d9a84a7879b5!E41)+ISNUMBER(caf2b28627a3!E41)+ISNUMBER('602e9d1875d1'!E41)+ISNUMBER(f168037f7f37!E41)+ISNUMBER(eb071de1ab08!E41)+ISNUMBER('7b3bd85715a4'!E41)+ISNUMBER(e2a9b537c609!E41)+ISNUMBER(f97457958ce9!E41)+ISNUMBER('281fcc7d7eae'!E41)+ISNUMBER('01454b1cfeba'!E41)+ISNUMBER('79287892b1d7'!E41)+ISNUMBER('1b3f96535b56'!E41),"") -> 5 | J28: =IF(ISNUMBER('1ae03038ed69'!F41)+ISNUMBER('1572eb063e5c'!F41)+ISNUMBER(b6ea66d78823!F41)+ISNUMBER('6d8dcb722ca4'!F41)+ISNUMBER('9306b30af184'!F41)+ISNUMBER('3b760aaeab13'!F41)+ISNUMBER(b2f4402deaee!F41)+ISNUMBER('1c4d314e87cd'!F41)+ISNUMBER(acd4708edfe6!F41)+ISNUMBER('9a32b1f50fb5'!F41)+ISNUMBER('2df562aa32e7'!F41)+ISNUMBER('3a5a3c04bd9d'!F41)+ISNUMBER('192241189337'!F41)+ISNUMBER('23a0423d7f40'!F41)+ISNUMBER('096252bb3796'!F41)+ISNUMBER(a53d1c7f9645!F41)+ISNUMBER('283d32631463'!F41)+ISNUMBER('1a542cfbf2c5'!F41)+ISNUMBER(cf262786a0e1!F41)+ISNUMBER('4b9efdeaeb40'!F41)+ISNUMBER('66fab14edc4c'!F41)+ISNUMBER(d9a84a7879b5!F41)+ISNUMBER(caf2b28627a3!F41)+ISNUMBER('602e9d1875d1'!F41)+ISNUMBER(f168037f7f37!F41)+ISNUMBER(eb071de1ab08!F41)+ISNUMBER('7b3bd85715a4'!F41)+ISNUMBER(e2a9b537c609!F41)+ISNUMBER(f97457958ce9!F41)+ISNUMBER('281fcc7d7eae'!F41)+ISNUMBER('01454b1cfeba'!F41)+ISNUMBER('79287892b1d7'!F41)+ISNUMBER('1b3f96535b56'!F41),ISNUMBER('1ae03038ed69'!F41)+ISNUMBER('1572eb063e5c'!F41)+ISNUMBER(b6ea66d78823!F41)+ISNUMBER('6d8dcb722ca4'!F41)+ISNUMBER('9306b30af184'!F41)+ISNUMBER('3b760aaeab13'!F41)+ISNUMBER(b2f4402deaee!F41)+ISNUMBER('1c4d314e87cd'!F41)+ISNUMBER(acd4708edfe6!F41)+ISNUMBER('9a32b1f50fb5'!F41)+ISNUMBER('2df562aa32e7'!F41)+ISNUMBER('3a5a3c04bd9d'!F41)+ISNUMBER('192241189337'!F41)+ISNUMBER('23a0423d7f40'!F41)+ISNUMBER('096252bb3796'!F41)+ISNUMBER(a53d1c7f9645!F41)+ISNUMBER('283d32631463'!F41)+ISNUMBER('1a542cfbf2c5'!F41)+ISNUMBER(cf262786a0e1!F41)+ISNUMBER('4b9efdeaeb40'!F41)+ISNUMBER('66fab14edc4c'!F41)+ISNUMBER(d9a84a7879b5!F41)+ISNUMBER(caf2b28627a3!F41)+ISNUMBER('602e9d1875d1'!F41)+ISNUMBER(f168037f7f37!F41)+ISNUMBER(eb071de1ab08!F41)+ISNUMBER('7b3bd85715a4'!F41)+ISNUMBER(e2a9b537c609!F41)+ISNUMBER(f97457958ce9!F41)+ISNUMBER('281fcc7d7eae'!F41)+ISNUMBER('01454b1cfeba'!F41)+ISNUMBER('79287892b1d7'!F41)+ISNUMBER('1b3f96535b56'!F41),"") -> 2 | K28: =IF(ISNUMBER('1ae03038ed69'!G41)+ISNUMBER('1572eb063e5c'!G41)+ISNUMBER(b6ea66d78823!G41)+ISNUMBER('6d8dcb722ca4'!G41)+ISNUMBER('9306b30af184'!G41)+ISNUMBER('3b760aaeab13'!G41)+ISNUMBER(b2f4402deaee!G41)+ISNUMBER('1c4d314e87cd'!G41)+ISNUMBER(acd4708edfe6!G41)+ISNUMBER('9a32b1f50fb5'!G41)+ISNUMBER('2df562aa32e7'!G41)+ISNUMBER('3a5a3c04bd9d'!G41)+ISNUMBER('192241189337'!G41)+ISNUMBER('23a0423d7f40'!G41)+ISNUMBER('096252bb3796'!G41)+ISNUMBER(a53d1c7f9645!G41)+ISNUMBER('283d32631463'!G41)+ISNUMBER('1a542cfbf2c5'!G41)+ISNUMBER(cf262786a0e1!G41)+ISNUMBER('4b9efdeaeb40'!G41)+ISNUMBER('66fab14edc4c'!G41)+ISNUMBER(d9a84a7879b5!G41)+ISNUMBER(caf2b28627a3!G41)+ISNUMBER('602e9d1875d1'!G41)+ISNUMBER(f168037f7f37!G41)+ISNUMBER(eb071de1ab08!G41)+ISNUMBER('7b3bd85715a4'!G41)+ISNUMBER(e2a9b537c609!G41)+ISNUMBER(f97457958ce9!G41)+ISNUMBER('281fcc7d7eae'!G41)+ISNUMBER('01454b1cfeba'!G41)+ISNUMBER('79287892b1d7'!G41)+ISNUMBER('1b3f96535b56'!G41),ISNUMBER('1ae03038ed69'!G41)+ISNUMBER('1572eb063e5c'!G41)+ISNUMBER(b6ea66d78823!G41)+ISNUMBER('6d8dcb722ca4'!G41)+ISNUMBER('9306b30af184'!G41)+ISNUMBER('3b760aaeab13'!G41)+ISNUMBER(b2f4402deaee!G41)+ISNUMBER('1c4d314e87cd'!G41)+ISNUMBER(acd4708edfe6!G41)+ISNUMBER('9a32b1f50fb5'!G41)+ISNUMBER('2df562aa32e7'!G41)+ISNUMBER('3a5a3c04bd9d'!G41)+ISNUMBER('192241189337'!G41)+ISNUMBER('23a0423d7f40'!G41)+ISNUMBER('096252bb3796'!G41)+ISNUMBER(a53d1c7f9645!G41)+ISNUMBER('283d32631463'!G41)+ISNUMBER('1a542cfbf2c5'!G41)+ISNUMBER(cf262786a0e1!G41)+ISNUMBER('4b9efdeaeb40'!G41)+ISNUMBER('66fab14edc4c'!G41)+ISNUMBER(d9a84a7879b5!G41)+ISNUMBER(caf2b28627a3!G41)+ISNUMBER('602e9d1875d1'!G41)+ISNUMBER(f168037f7f37!G41)+ISNUMBER(eb071de1ab08!G41)+ISNUMBER('7b3bd85715a4'!G41)+ISNUMBER(e2a9b537c609!G41)+ISNUMBER(f97457958ce9!G41)+ISNUMBER('281fcc7d7eae'!G41)+ISNUMBER('01454b1cfeba'!G41)+ISNUMBER('79287892b1d7'!G41)+ISNUMBER('1b3f96535b56'!G41),"") -> 8 | L28: =IF(ISNUMBER('1ae03038ed69'!H41)+ISNUMBER('1572eb063e5c'!H41)+ISNUMBER(b6ea66d78823!H41)+ISNUMBER('6d8dcb722ca4'!H41)+ISNUMBER('9306b30af184'!H41)+ISNUMBER('3b760aaeab13'!H41)+ISNUMBER(b2f4402deaee!H41)+ISNUMBER('1c4d314e87cd'!H41)+ISNUMBER(acd4708edfe6!H41)+ISNUMBER('9a32b1f50fb5'!H41)+ISNUMBER('2df562aa32e7'!H41)+ISNUMBER('3a5a3c04bd9d'!H41)+ISNUMBER('192241189337'!H41)+ISNUMBER('23a0423d7f40'!H41)+ISNUMBER('096252bb3796'!H41)+ISNUMBER(a53d1c7f9645!H41)+ISNUMBER('283d32631463'!H41)+ISNUMBER('1a542cfbf2c5'!H41)+ISNUMBER(cf262786a0e1!H41)+ISNUMBER('4b9efdeaeb40'!H41)+ISNUMBER('66fab14edc4c'!H41)+ISNUMBER(d9a84a7879b5!H41)+ISNUMBER(caf2b28627a3!H41)+ISNUMBER('602e9d1875d1'!H41)+ISNUMBER(f168037f7f37!H41)+ISNUMBER(eb071de1ab08!H41)+ISNUMBER('7b3bd85715a4'!H41)+ISNUMBER(e2a9b537c609!H41)+ISNUMBER(f97457958ce9!H41)+ISNUMBER('281fcc7d7eae'!H41)+ISNUMBER('01454b1cfeba'!H41)+ISNUMBER('79287892b1d7'!H41)+ISNUMBER('1b3f96535b56'!H41),ISNUMBER('1ae03038ed69'!H41)+ISNUMBER('1572eb063e5c'!H41)+ISNUMBER(b6ea66d78823!H41)+ISNUMBER('6d8dcb722ca4'!H41)+ISNUMBER('9306b30af184'!H41)+ISNUMBER('3b760aaeab13'!H41)+ISNUMBER(b2f4402deaee!H41)+ISNUMBER('1c4d314e87cd'!H41)+ISNUMBER(acd4708edfe6!H41)+ISNUMBER('9a32b1f50fb5'!H41)+ISNUMBER('2df562aa32e7'!H41)+ISNUMBER('3a5a3c04bd9d'!H41)+ISNUMBER('192241189337'!H41)+ISNUMBER('23a0423d7f40'!H41)+ISNUMBER('096252bb3796'!H41)+ISNUMBER(a53d1c7f9645!H41)+ISNUMBER('283d32631463'!H41)+ISNUMBER('1a542cfbf2c5'!H41)+ISNUMBER(cf262786a0e1!H41)+ISNUMBER('4b9efdeaeb40'!H41)+ISNUMBER('66fab14edc4c'!H41)+ISNUMBER(d9a84a7879b5!H41)+ISNUMBER(caf2b28627a3!H41)+ISNUMBER('602e9d1875d1'!H41)+ISNUMBER(f168037f7f37!H41)+ISNUMBER(eb071de1ab08!H41)+ISNUMBER('7b3bd85715a4'!H41)+ISNUMBER(e2a9b537c609!H41)+ISNUMBER(f97457958ce9!H41)+ISNUMBER('281fcc7d7eae'!H41)+ISNUMBER('01454b1cfeba'!H41)+ISNUMBER('79287892b1d7'!H41)+ISNUMBER('1b3f96535b56'!H41),"") -> 4 | M28: =IF(ISNUMBER('1ae03038ed69'!I41)+ISNUMBER('1572eb063e5c'!I41)+ISNUMBER(b6ea66d78823!I41)+ISNUMBER('6d8dcb722ca4'!I41)+ISNUMBER('9306b30af184'!I41)+ISNUMBER('3b760aaeab13'!I41)+ISNUMBER(b2f4402deaee!I41)+ISNUMBER('1c4d314e87cd'!I41)+ISNUMBER(acd4708edfe6!I41)+ISNUMBER('9a32b1f50fb5'!I41)+ISNUMBER('2df562aa32e7'!I41)+ISNUMBER('3a5a3c04bd9d'!I41)+ISNUMBER('192241189337'!I41)+ISNUMBER('23a0423d7f40'!I41)+ISNUMBER('096252bb3796'!I41)+ISNUMBER(a53d1c7f9645!I41)+ISNUMBER('283d32631463'!I41)+ISNUMBER('1a542cfbf2c5'!I41)+ISNUMBER(cf262786a0e1!I41)+ISNUMBER('4b9efdeaeb40'!I41)+ISNUMBER('66fab14edc4c'!I41)+ISNUMBER(d9a84a7879b5!I41)+ISNUMBER(caf2b28627a3!I41)+ISNUMBER('602e9d1875d1'!I41)+ISNUMBER(f168037f7f37!I41)+ISNUMBER(eb071de1ab08!I41)+ISNUMBER('7b3bd85715a4'!I41)+ISNUMBER(e2a9b537c609!I41)+ISNUMBER(f97457958ce9!I41)+ISNUMBER('281fcc7d7eae'!I41)+ISNUMBER('01454b1cfeba'!I41)+ISNUMBER('79287892b1d7'!I41)+ISNUMBER('1b3f96535b56'!I41),ISNUMBER('1ae03038ed69'!I41)+ISNUMBER('1572eb063e5c'!I41)+ISNUMBER(b6ea66d78823!I41)+ISNUMBER('6d8dcb722ca4'!I41)+ISNUMBER('9306b30af184'!I41)+ISNUMBER('3b760aaeab13'!I41)+ISNUMBER(b2f4402deaee!I41)+ISNUMBER('1c4d314e87cd'!I41)+ISNUMBER(acd4708edfe6!I41)+ISNUMBER('9a32b1f50fb5'!I41)+ISNUMBER('2df562aa32e7'!I41)+ISNUMBER('3a5a3c04bd9d'!I41)+ISNUMBER('192241189337'!I41)+ISNUMBER('23a0423d7f40'!I41)+ISNUMBER('096252bb3796'!I41)+ISNUMBER(a53d1c7f9645!I41)+ISNUMBER('283d32631463'!I41)+ISNUMBER('1a542cfbf2c5'!I41)+ISNUMBER(cf262786a0e1!I41)+ISNUMBER('4b9efdeaeb40'!I41)+ISNUMBER('66fab14edc4c'!I41)+ISNUMBER(d9a84a7879b5!I41)+ISNUMBER(caf2b28627a3!I41)+ISNUMBER('602e9d1875d1'!I41)+ISNUMBER(f168037f7f37!I41)+ISNUMBER(eb071de1ab08!I41)+ISNUMBER('7b3bd85715a4'!I41)+ISNUMBER(e2a9b537c609!I41)+ISNUMBER(f97457958ce9!I41)+ISNUMBER('281fcc7d7eae'!I41)+ISNUMBER('01454b1cfeba'!I41)+ISNUMBER('79287892b1d7'!I41)+ISNUMBER('1b3f96535b56'!I41),"") -> 7 | N28: =IF(ISNUMBER('1ae03038ed69'!J41)+ISNUMBER('1572eb063e5c'!J41)+ISNUMBER(b6ea66d78823!J41)+ISNUMBER('6d8dcb722ca4'!J41)+ISNUMBER('9306b30af184'!J41)+ISNUMBER('3b760aaeab13'!J41)+ISNUMBER(b2f4402deaee!J41)+ISNUMBER('1c4d314e87cd'!J41)+ISNUMBER(acd4708edfe6!J41)+ISNUMBER('9a32b1f50fb5'!J41)+ISNUMBER('2df562aa32e7'!J41)+ISNUMBER('3a5a3c04bd9d'!J41)+ISNUMBER('192241189337'!J41)+ISNUMBER('23a0423d7f40'!J41)+ISNUMBER('096252bb3796'!J41)+ISNUMBER(a53d1c7f9645!J41)+ISNUMBER('283d32631463'!J41)+ISNUMBER('1a542cfbf2c5'!J41)+ISNUMBER(cf262786a0e1!J41)+ISNUMBER('4b9efdeaeb40'!J41)+ISNUMBER('66fab14edc4c'!J41)+ISNUMBER(d9a84a7879b5!J41)+ISNUMBER(caf2b28627a3!J41)+ISNUMBER('602e9d1875d1'!J41)+ISNUMBER(f168037f7f37!J41)+ISNUMBER(eb071de1ab08!J41)+ISNUMBER('7b3bd85715a4'!J41)+ISNUMBER(e2a9b537c609!J41)+ISNUMBER(f97457958ce9!J41)+ISNUMBER('281fcc7d7eae'!J41)+ISNUMBER('01454b1cfeba'!J41)+ISNUMBER('79287892b1d7'!J41)+ISNUMBER('1b3f96535b56'!J41),ISNUMBER('1ae03038ed69'!J41)+ISNUMBER('1572eb063e5c'!J41)+ISNUMBER(b6ea66d78823!J41)+ISNUMBER('6d8dcb722ca4'!J41)+ISNUMBER('9306b30af184'!J41)+ISNUMBER('3b760aaeab13'!J41)+ISNUMBER(b2f4402deaee!J41)+ISNUMBER('1c4d314e87cd'!J41)+ISNUMBER(acd4708edfe6!J41)+ISNUMBER('9a32b1f50fb5'!J41)+ISNUMBER('2df562aa32e7'!J41)+ISNUMBER('3a5a3c04bd9d'!J41)+ISNUMBER('192241189337'!J41)+ISNUMBER('23a0423d7f40'!J41)+ISNUMBER('096252bb3796'!J41)+ISNUMBER(a53d1c7f9645!J41)+ISNUMBER('283d32631463'!J41)+ISNUMBER('1a542cfbf2c5'!J41)+ISNUMBER(cf262786a0e1!J41)+ISNUMBER('4b9efdeaeb40'!J41)+ISNUMBER('66fab14edc4c'!J41)+ISNUMBER(d9a84a7879b5!J41)+ISNUMBER(caf2b28627a3!J41)+ISNUMBER('602e9d1875d1'!J41)+ISNUMBER(f168037f7f37!J41)+ISNUMBER(eb071de1ab08!J41)+ISNUMBER('7b3bd85715a4'!J41)+ISNUMBER(e2a9b537c609!J41)+ISNUMBER(f97457958ce9!J41)+ISNUMBER('281fcc7d7eae'!J41)+ISNUMBER('01454b1cfeba'!J41)+ISNUMBER('79287892b1d7'!J41)+ISNUMBER('1b3f96535b56'!J41),"") -> 1 | ... R28: =IF(ISNUMBER('1ae03038ed69'!N41)+ISNUMBER('1572eb063e5c'!N41)+ISNUMBER(b6ea66d78823!N41)+ISNUMBER('6d8dcb722ca4'!N41)+ISNUMBER('9306b30af184'!N41)+ISNUMBER('3b760aaeab13'!N41)+ISNUMBER(b2f4402deaee!N41)+ISNUMBER('1c4d314e87cd'!N41)+ISNUMBER(acd4708edfe6!N41)+ISNUMBER('9a32b1f50fb5'!N41)+ISNUMBER('2df562aa32e7'!N41)+ISNUMBER('3a5a3c04bd9d'!N41)+ISNUMBER('192241189337'!N41)+ISNUMBER('23a0423d7f40'!N41)+ISNUMBER('096252bb3796'!N41)+ISNUMBER(a53d1c7f9645!N41)+ISNUMBER('283d32631463'!N41)+ISNUMBER('1a542cfbf2c5'!N41)+ISNUMBER(cf262786a0e1!N41)+ISNUMBER('4b9efdeaeb40'!N41)+ISNUMBER('66fab14edc4c'!N41)+ISNUMBER(d9a84a7879b5!N41)+ISNUMBER(caf2b28627a3!N41)+ISNUMBER('602e9d1875d1'!N41)+ISNUMBER(f168037f7f37!N41)+ISNUMBER(eb071de1ab08!N41)+ISNUMBER('7b3bd85715a4'!N41)+ISNUMBER(e2a9b537c609!N41)+ISNUMBER(f97457958ce9!N41)+ISNUMBER('281fcc7d7eae'!N41)+ISNUMBER('01454b1cfeba'!N41)+ISNUMBER('79287892b1d7'!N41)+ISNUMBER('1b3f96535b56'!N41),ISNUMBER('1ae03038ed69'!N41)+ISNUMBER('1572eb063e5c'!N41)+ISNUMBER(b6ea66d78823!N41)+ISNUMBER('6d8dcb722ca4'!N41)+ISNUMBER('9306b30af184'!N41)+ISNUMBER('3b760aaeab13'!N41)+ISNUMBER(b2f4402deaee!N41)+ISNUMBER('1c4d314e87cd'!N41)+ISNUMBER(acd4708edfe6!N41)+ISNUMBER('9a32b1f50fb5'!N41)+ISNUMBER('2df562aa32e7'!N41)+ISNUMBER('3a5a3c04bd9d'!N41)+ISNUMBER('192241189337'!N41)+ISNUMBER('23a0423d7f40'!N41)+ISNUMBER('096252bb3796'!N41)+ISNUMBER(a53d1c7f9645!N41)+ISNUMBER('283d32631463'!N41)+ISNUMBER('1a542cfbf2c5'!N41)+ISNUMBER(cf262786a0e1!N41)+ISNUMBER('4b9efdeaeb40'!N41)+ISNUMBER('66fab14edc4c'!N41)+ISNUMBER(d9a84a7879b5!N41)+ISNUMBER(caf2b28627a3!N41)+ISNUMBER('602e9d1875d1'!N41)+ISNUMBER(f168037f7f37!N41)+ISNUMBER(eb071de1ab08!N41)+ISNUMBER('7b3bd85715a4'!N41)+ISNUMBER(e2a9b537c609!N41)+ISNUMBER(f97457958ce9!N41)+ISNUMBER('281fcc7d7eae'!N41)+ISNUMBER('01454b1cfeba'!N41)+ISNUMBER('79287892b1d7'!N41)+ISNUMBER('1b3f96535b56'!N41),"") | U28: 4b9efdeaeb40 | V28: Geodesign workshop for AU Viborg.
F29: =F13 -> Health and care in the co… | G29: =IF(ISNUMBER('1ae03038ed69'!C42)+ISNUMBER('1572eb063e5c'!C42)+ISNUMBER(b6ea66d78823!C42)+ISNUMBER('6d8dcb722ca4'!C42)+ISNUMBER('9306b30af184'!C42)+ISNUMBER('3b760aaeab13'!C42)+ISNUMBER(b2f4402deaee!C42)+ISNUMBER('1c4d314e87cd'!C42)+ISNUMBER(acd4708edfe6!C42)+ISNUMBER('9a32b1f50fb5'!C42)+ISNUMBER('2df562aa32e7'!C42)+ISNUMBER('3a5a3c04bd9d'!C42)+ISNUMBER('192241189337'!C42)+ISNUMBER('23a0423d7f40'!C42)+ISNUMBER('096252bb3796'!C42)+ISNUMBER(a53d1c7f9645!C42)+ISNUMBER('283d32631463'!C42)+ISNUMBER('1a542cfbf2c5'!C42)+ISNUMBER(cf262786a0e1!C42)+ISNUMBER('4b9efdeaeb40'!C42)+ISNUMBER('66fab14edc4c'!C42)+ISNUMBER(d9a84a7879b5!C42)+ISNUMBER(caf2b28627a3!C42)+ISNUMBER('602e9d1875d1'!C42)+ISNUMBER(f168037f7f37!C42)+ISNUMBER(eb071de1ab08!C42)+ISNUMBER('7b3bd85715a4'!C42)+ISNUMBER(e2a9b537c609!C42)+ISNUMBER(f97457958ce9!C42)+ISNUMBER('281fcc7d7eae'!C42)+ISNUMBER('01454b1cfeba'!C42)+ISNUMBER('79287892b1d7'!C42)+ISNUMBER('1b3f96535b56'!C42),ISNUMBER('1ae03038ed69'!C42)+ISNUMBER('1572eb063e5c'!C42)+ISNUMBER(b6ea66d78823!C42)+ISNUMBER('6d8dcb722ca4'!C42)+ISNUMBER('9306b30af184'!C42)+ISNUMBER('3b760aaeab13'!C42)+ISNUMBER(b2f4402deaee!C42)+ISNUMBER('1c4d314e87cd'!C42)+ISNUMBER(acd4708edfe6!C42)+ISNUMBER('9a32b1f50fb5'!C42)+ISNUMBER('2df562aa32e7'!C42)+ISNUMBER('3a5a3c04bd9d'!C42)+ISNUMBER('192241189337'!C42)+ISNUMBER('23a0423d7f40'!C42)+ISNUMBER('096252bb3796'!C42)+ISNUMBER(a53d1c7f9645!C42)+ISNUMBER('283d32631463'!C42)+ISNUMBER('1a542cfbf2c5'!C42)+ISNUMBER(cf262786a0e1!C42)+ISNUMBER('4b9efdeaeb40'!C42)+ISNUMBER('66fab14edc4c'!C42)+ISNUMBER(d9a84a7879b5!C42)+ISNUMBER(caf2b28627a3!C42)+ISNUMBER('602e9d1875d1'!C42)+ISNUMBER(f168037f7f37!C42)+ISNUMBER(eb071de1ab08!C42)+ISNUMBER('7b3bd85715a4'!C42)+ISNUMBER(e2a9b537c609!C42)+ISNUMBER(f97457958ce9!C42)+ISNUMBER('281fcc7d7eae'!C42)+ISNUMBER('01454b1cfeba'!C42)+ISNUMBER('79287892b1d7'!C42)+ISNUMBER('1b3f96535b56'!C42),"") -> 1 | H29: =IF(ISNUMBER('1ae03038ed69'!D42)+ISNUMBER('1572eb063e5c'!D42)+ISNUMBER(b6ea66d78823!D42)+ISNUMBER('6d8dcb722ca4'!D42)+ISNUMBER('9306b30af184'!D42)+ISNUMBER('3b760aaeab13'!D42)+ISNUMBER(b2f4402deaee!D42)+ISNUMBER('1c4d314e87cd'!D42)+ISNUMBER(acd4708edfe6!D42)+ISNUMBER('9a32b1f50fb5'!D42)+ISNUMBER('2df562aa32e7'!D42)+ISNUMBER('3a5a3c04bd9d'!D42)+ISNUMBER('192241189337'!D42)+ISNUMBER('23a0423d7f40'!D42)+ISNUMBER('096252bb3796'!D42)+ISNUMBER(a53d1c7f9645!D42)+ISNUMBER('283d32631463'!D42)+ISNUMBER('1a542cfbf2c5'!D42)+ISNUMBER(cf262786a0e1!D42)+ISNUMBER('4b9efdeaeb40'!D42)+ISNUMBER('66fab14edc4c'!D42)+ISNUMBER(d9a84a7879b5!D42)+ISNUMBER(caf2b28627a3!D42)+ISNUMBER('602e9d1875d1'!D42)+ISNUMBER(f168037f7f37!D42)+ISNUMBER(eb071de1ab08!D42)+ISNUMBER('7b3bd85715a4'!D42)+ISNUMBER(e2a9b537c609!D42)+ISNUMBER(f97457958ce9!D42)+ISNUMBER('281fcc7d7eae'!D42)+ISNUMBER('01454b1cfeba'!D42)+ISNUMBER('79287892b1d7'!D42)+ISNUMBER('1b3f96535b56'!D42),ISNUMBER('1ae03038ed69'!D42)+ISNUMBER('1572eb063e5c'!D42)+ISNUMBER(b6ea66d78823!D42)+ISNUMBER('6d8dcb722ca4'!D42)+ISNUMBER('9306b30af184'!D42)+ISNUMBER('3b760aaeab13'!D42)+ISNUMBER(b2f4402deaee!D42)+ISNUMBER('1c4d314e87cd'!D42)+ISNUMBER(acd4708edfe6!D42)+ISNUMBER('9a32b1f50fb5'!D42)+ISNUMBER('2df562aa32e7'!D42)+ISNUMBER('3a5a3c04bd9d'!D42)+ISNUMBER('192241189337'!D42)+ISNUMBER('23a0423d7f40'!D42)+ISNUMBER('096252bb3796'!D42)+ISNUMBER(a53d1c7f9645!D42)+ISNUMBER('283d32631463'!D42)+ISNUMBER('1a542cfbf2c5'!D42)+ISNUMBER(cf262786a0e1!D42)+ISNUMBER('4b9efdeaeb40'!D42)+ISNUMBER('66fab14edc4c'!D42)+ISNUMBER(d9a84a7879b5!D42)+ISNUMBER(caf2b28627a3!D42)+ISNUMBER('602e9d1875d1'!D42)+ISNUMBER(f168037f7f37!D42)+ISNUMBER(eb071de1ab08!D42)+ISNUMBER('7b3bd85715a4'!D42)+ISNUMBER(e2a9b537c609!D42)+ISNUMBER(f97457958ce9!D42)+ISNUMBER('281fcc7d7eae'!D42)+ISNUMBER('01454b1cfeba'!D42)+ISNUMBER('79287892b1d7'!D42)+ISNUMBER('1b3f96535b56'!D42),"") -> 2 | I29: =IF(ISNUMBER('1ae03038ed69'!E42)+ISNUMBER('1572eb063e5c'!E42)+ISNUMBER(b6ea66d78823!E42)+ISNUMBER('6d8dcb722ca4'!E42)+ISNUMBER('9306b30af184'!E42)+ISNUMBER('3b760aaeab13'!E42)+ISNUMBER(b2f4402deaee!E42)+ISNUMBER('1c4d314e87cd'!E42)+ISNUMBER(acd4708edfe6!E42)+ISNUMBER('9a32b1f50fb5'!E42)+ISNUMBER('2df562aa32e7'!E42)+ISNUMBER('3a5a3c04bd9d'!E42)+ISNUMBER('192241189337'!E42)+ISNUMBER('23a0423d7f40'!E42)+ISNUMBER('096252bb3796'!E42)+ISNUMBER(a53d1c7f9645!E42)+ISNUMBER('283d32631463'!E42)+ISNUMBER('1a542cfbf2c5'!E42)+ISNUMBER(cf262786a0e1!E42)+ISNUMBER('4b9efdeaeb40'!E42)+ISNUMBER('66fab14edc4c'!E42)+ISNUMBER(d9a84a7879b5!E42)+ISNUMBER(caf2b28627a3!E42)+ISNUMBER('602e9d1875d1'!E42)+ISNUMBER(f168037f7f37!E42)+ISNUMBER(eb071de1ab08!E42)+ISNUMBER('7b3bd85715a4'!E42)+ISNUMBER(e2a9b537c609!E42)+ISNUMBER(f97457958ce9!E42)+ISNUMBER('281fcc7d7eae'!E42)+ISNUMBER('01454b1cfeba'!E42)+ISNUMBER('79287892b1d7'!E42)+ISNUMBER('1b3f96535b56'!E42),ISNUMBER('1ae03038ed69'!E42)+ISNUMBER('1572eb063e5c'!E42)+ISNUMBER(b6ea66d78823!E42)+ISNUMBER('6d8dcb722ca4'!E42)+ISNUMBER('9306b30af184'!E42)+ISNUMBER('3b760aaeab13'!E42)+ISNUMBER(b2f4402deaee!E42)+ISNUMBER('1c4d314e87cd'!E42)+ISNUMBER(acd4708edfe6!E42)+ISNUMBER('9a32b1f50fb5'!E42)+ISNUMBER('2df562aa32e7'!E42)+ISNUMBER('3a5a3c04bd9d'!E42)+ISNUMBER('192241189337'!E42)+ISNUMBER('23a0423d7f40'!E42)+ISNUMBER('096252bb3796'!E42)+ISNUMBER(a53d1c7f9645!E42)+ISNUMBER('283d32631463'!E42)+ISNUMBER('1a542cfbf2c5'!E42)+ISNUMBER(cf262786a0e1!E42)+ISNUMBER('4b9efdeaeb40'!E42)+ISNUMBER('66fab14edc4c'!E42)+ISNUMBER(d9a84a7879b5!E42)+ISNUMBER(caf2b28627a3!E42)+ISNUMBER('602e9d1875d1'!E42)+ISNUMBER(f168037f7f37!E42)+ISNUMBER(eb071de1ab08!E42)+ISNUMBER('7b3bd85715a4'!E42)+ISNUMBER(e2a9b537c609!E42)+ISNUMBER(f97457958ce9!E42)+ISNUMBER('281fcc7d7eae'!E42)+ISNUMBER('01454b1cfeba'!E42)+ISNUMBER('79287892b1d7'!E42)+ISNUMBER('1b3f96535b56'!E42),"") | J29: =IF(ISNUMBER('1ae03038ed69'!F42)+ISNUMBER('1572eb063e5c'!F42)+ISNUMBER(b6ea66d78823!F42)+ISNUMBER('6d8dcb722ca4'!F42)+ISNUMBER('9306b30af184'!F42)+ISNUMBER('3b760aaeab13'!F42)+ISNUMBER(b2f4402deaee!F42)+ISNUMBER('1c4d314e87cd'!F42)+ISNUMBER(acd4708edfe6!F42)+ISNUMBER('9a32b1f50fb5'!F42)+ISNUMBER('2df562aa32e7'!F42)+ISNUMBER('3a5a3c04bd9d'!F42)+ISNUMBER('192241189337'!F42)+ISNUMBER('23a0423d7f40'!F42)+ISNUMBER('096252bb3796'!F42)+ISNUMBER(a53d1c7f9645!F42)+ISNUMBER('283d32631463'!F42)+ISNUMBER('1a542cfbf2c5'!F42)+ISNUMBER(cf262786a0e1!F42)+ISNUMBER('4b9efdeaeb40'!F42)+ISNUMBER('66fab14edc4c'!F42)+ISNUMBER(d9a84a7879b5!F42)+ISNUMBER(caf2b28627a3!F42)+ISNUMBER('602e9d1875d1'!F42)+ISNUMBER(f168037f7f37!F42)+ISNUMBER(eb071de1ab08!F42)+ISNUMBER('7b3bd85715a4'!F42)+ISNUMBER(e2a9b537c609!F42)+ISNUMBER(f97457958ce9!F42)+ISNUMBER('281fcc7d7eae'!F42)+ISNUMBER('01454b1cfeba'!F42)+ISNUMBER('79287892b1d7'!F42)+ISNUMBER('1b3f96535b56'!F42),ISNUMBER('1ae03038ed69'!F42)+ISNUMBER('1572eb063e5c'!F42)+ISNUMBER(b6ea66d78823!F42)+ISNUMBER('6d8dcb722ca4'!F42)+ISNUMBER('9306b30af184'!F42)+ISNUMBER('3b760aaeab13'!F42)+ISNUMBER(b2f4402deaee!F42)+ISNUMBER('1c4d314e87cd'!F42)+ISNUMBER(acd4708edfe6!F42)+ISNUMBER('9a32b1f50fb5'!F42)+ISNUMBER('2df562aa32e7'!F42)+ISNUMBER('3a5a3c04bd9d'!F42)+ISNUMBER('192241189337'!F42)+ISNUMBER('23a0423d7f40'!F42)+ISNUMBER('096252bb3796'!F42)+ISNUMBER(a53d1c7f9645!F42)+ISNUMBER('283d32631463'!F42)+ISNUMBER('1a542cfbf2c5'!F42)+ISNUMBER(cf262786a0e1!F42)+ISNUMBER('4b9efdeaeb40'!F42)+ISNUMBER('66fab14edc4c'!F42)+ISNUMBER(d9a84a7879b5!F42)+ISNUMBER(caf2b28627a3!F42)+ISNUMBER('602e9d1875d1'!F42)+ISNUMBER(f168037f7f37!F42)+ISNUMBER(eb071de1ab08!F42)+ISNUMBER('7b3bd85715a4'!F42)+ISNUMBER(e2a9b537c609!F42)+ISNUMBER(f97457958ce9!F42)+ISNUMBER('281fcc7d7eae'!F42)+ISNUMBER('01454b1cfeba'!F42)+ISNUMBER('79287892b1d7'!F42)+ISNUMBER('1b3f96535b56'!F42),"") | K29: =IF(ISNUMBER('1ae03038ed69'!G42)+ISNUMBER('1572eb063e5c'!G42)+ISNUMBER(b6ea66d78823!G42)+ISNUMBER('6d8dcb722ca4'!G42)+ISNUMBER('9306b30af184'!G42)+ISNUMBER('3b760aaeab13'!G42)+ISNUMBER(b2f4402deaee!G42)+ISNUMBER('1c4d314e87cd'!G42)+ISNUMBER(acd4708edfe6!G42)+ISNUMBER('9a32b1f50fb5'!G42)+ISNUMBER('2df562aa32e7'!G42)+ISNUMBER('3a5a3c04bd9d'!G42)+ISNUMBER('192241189337'!G42)+ISNUMBER('23a0423d7f40'!G42)+ISNUMBER('096252bb3796'!G42)+ISNUMBER(a53d1c7f9645!G42)+ISNUMBER('283d32631463'!G42)+ISNUMBER('1a542cfbf2c5'!G42)+ISNUMBER(cf262786a0e1!G42)+ISNUMBER('4b9efdeaeb40'!G42)+ISNUMBER('66fab14edc4c'!G42)+ISNUMBER(d9a84a7879b5!G42)+ISNUMBER(caf2b28627a3!G42)+ISNUMBER('602e9d1875d1'!G42)+ISNUMBER(f168037f7f37!G42)+ISNUMBER(eb071de1ab08!G42)+ISNUMBER('7b3bd85715a4'!G42)+ISNUMBER(e2a9b537c609!G42)+ISNUMBER(f97457958ce9!G42)+ISNUMBER('281fcc7d7eae'!G42)+ISNUMBER('01454b1cfeba'!G42)+ISNUMBER('79287892b1d7'!G42)+ISNUMBER('1b3f96535b56'!G42),ISNUMBER('1ae03038ed69'!G42)+ISNUMBER('1572eb063e5c'!G42)+ISNUMBER(b6ea66d78823!G42)+ISNUMBER('6d8dcb722ca4'!G42)+ISNUMBER('9306b30af184'!G42)+ISNUMBER('3b760aaeab13'!G42)+ISNUMBER(b2f4402deaee!G42)+ISNUMBER('1c4d314e87cd'!G42)+ISNUMBER(acd4708edfe6!G42)+ISNUMBER('9a32b1f50fb5'!G42)+ISNUMBER('2df562aa32e7'!G42)+ISNUMBER('3a5a3c04bd9d'!G42)+ISNUMBER('192241189337'!G42)+ISNUMBER('23a0423d7f40'!G42)+ISNUMBER('096252bb3796'!G42)+ISNUMBER(a53d1c7f9645!G42)+ISNUMBER('283d32631463'!G42)+ISNUMBER('1a542cfbf2c5'!G42)+ISNUMBER(cf262786a0e1!G42)+ISNUMBER('4b9efdeaeb40'!G42)+ISNUMBER('66fab14edc4c'!G42)+ISNUMBER(d9a84a7879b5!G42)+ISNUMBER(caf2b28627a3!G42)+ISNUMBER('602e9d1875d1'!G42)+ISNUMBER(f168037f7f37!G42)+ISNUMBER(eb071de1ab08!G42)+ISNUMBER('7b3bd85715a4'!G42)+ISNUMBER(e2a9b537c609!G42)+ISNUMBER(f97457958ce9!G42)+ISNUMBER('281fcc7d7eae'!G42)+ISNUMBER('01454b1cfeba'!G42)+ISNUMBER('79287892b1d7'!G42)+ISNUMBER('1b3f96535b56'!G42),"") | L29: =IF(ISNUMBER('1ae03038ed69'!H42)+ISNUMBER('1572eb063e5c'!H42)+ISNUMBER(b6ea66d78823!H42)+ISNUMBER('6d8dcb722ca4'!H42)+ISNUMBER('9306b30af184'!H42)+ISNUMBER('3b760aaeab13'!H42)+ISNUMBER(b2f4402deaee!H42)+ISNUMBER('1c4d314e87cd'!H42)+ISNUMBER(acd4708edfe6!H42)+ISNUMBER('9a32b1f50fb5'!H42)+ISNUMBER('2df562aa32e7'!H42)+ISNUMBER('3a5a3c04bd9d'!H42)+ISNUMBER('192241189337'!H42)+ISNUMBER('23a0423d7f40'!H42)+ISNUMBER('096252bb3796'!H42)+ISNUMBER(a53d1c7f9645!H42)+ISNUMBER('283d32631463'!H42)+ISNUMBER('1a542cfbf2c5'!H42)+ISNUMBER(cf262786a0e1!H42)+ISNUMBER('4b9efdeaeb40'!H42)+ISNUMBER('66fab14edc4c'!H42)+ISNUMBER(d9a84a7879b5!H42)+ISNUMBER(caf2b28627a3!H42)+ISNUMBER('602e9d1875d1'!H42)+ISNUMBER(f168037f7f37!H42)+ISNUMBER(eb071de1ab08!H42)+ISNUMBER('7b3bd85715a4'!H42)+ISNUMBER(e2a9b537c609!H42)+ISNUMBER(f97457958ce9!H42)+ISNUMBER('281fcc7d7eae'!H42)+ISNUMBER('01454b1cfeba'!H42)+ISNUMBER('79287892b1d7'!H42)+ISNUMBER('1b3f96535b56'!H42),ISNUMBER('1ae03038ed69'!H42)+ISNUMBER('1572eb063e5c'!H42)+ISNUMBER(b6ea66d78823!H42)+ISNUMBER('6d8dcb722ca4'!H42)+ISNUMBER('9306b30af184'!H42)+ISNUMBER('3b760aaeab13'!H42)+ISNUMBER(b2f4402deaee!H42)+ISNUMBER('1c4d314e87cd'!H42)+ISNUMBER(acd4708edfe6!H42)+ISNUMBER('9a32b1f50fb5'!H42)+ISNUMBER('2df562aa32e7'!H42)+ISNUMBER('3a5a3c04bd9d'!H42)+ISNUMBER('192241189337'!H42)+ISNUMBER('23a0423d7f40'!H42)+ISNUMBER('096252bb3796'!H42)+ISNUMBER(a53d1c7f9645!H42)+ISNUMBER('283d32631463'!H42)+ISNUMBER('1a542cfbf2c5'!H42)+ISNUMBER(cf262786a0e1!H42)+ISNUMBER('4b9efdeaeb40'!H42)+ISNUMBER('66fab14edc4c'!H42)+ISNUMBER(d9a84a7879b5!H42)+ISNUMBER(caf2b28627a3!H42)+ISNUMBER('602e9d1875d1'!H42)+ISNUMBER(f168037f7f37!H42)+ISNUMBER(eb071de1ab08!H42)+ISNUMBER('7b3bd85715a4'!H42)+ISNUMBER(e2a9b537c609!H42)+ISNUMBER(f97457958ce9!H42)+ISNUMBER('281fcc7d7eae'!H42)+ISNUMBER('01454b1cfeba'!H42)+ISNUMBER('79287892b1d7'!H42)+ISNUMBER('1b3f96535b56'!H42),"") | M29: =IF(ISNUMBER('1ae03038ed69'!I42)+ISNUMBER('1572eb063e5c'!I42)+ISNUMBER(b6ea66d78823!I42)+ISNUMBER('6d8dcb722ca4'!I42)+ISNUMBER('9306b30af184'!I42)+ISNUMBER('3b760aaeab13'!I42)+ISNUMBER(b2f4402deaee!I42)+ISNUMBER('1c4d314e87cd'!I42)+ISNUMBER(acd4708edfe6!I42)+ISNUMBER('9a32b1f50fb5'!I42)+ISNUMBER('2df562aa32e7'!I42)+ISNUMBER('3a5a3c04bd9d'!I42)+ISNUMBER('192241189337'!I42)+ISNUMBER('23a0423d7f40'!I42)+ISNUMBER('096252bb3796'!I42)+ISNUMBER(a53d1c7f9645!I42)+ISNUMBER('283d32631463'!I42)+ISNUMBER('1a542cfbf2c5'!I42)+ISNUMBER(cf262786a0e1!I42)+ISNUMBER('4b9efdeaeb40'!I42)+ISNUMBER('66fab14edc4c'!I42)+ISNUMBER(d9a84a7879b5!I42)+ISNUMBER(caf2b28627a3!I42)+ISNUMBER('602e9d1875d1'!I42)+ISNUMBER(f168037f7f37!I42)+ISNUMBER(eb071de1ab08!I42)+ISNUMBER('7b3bd85715a4'!I42)+ISNUMBER(e2a9b537c609!I42)+ISNUMBER(f97457958ce9!I42)+ISNUMBER('281fcc7d7eae'!I42)+ISNUMBER('01454b1cfeba'!I42)+ISNUMBER('79287892b1d7'!I42)+ISNUMBER('1b3f96535b56'!I42),ISNUMBER('1ae03038ed69'!I42)+ISNUMBER('1572eb063e5c'!I42)+ISNUMBER(b6ea66d78823!I42)+ISNUMBER('6d8dcb722ca4'!I42)+ISNUMBER('9306b30af184'!I42)+ISNUMBER('3b760aaeab13'!I42)+ISNUMBER(b2f4402deaee!I42)+ISNUMBER('1c4d314e87cd'!I42)+ISNUMBER(acd4708edfe6!I42)+ISNUMBER('9a32b1f50fb5'!I42)+ISNUMBER('2df562aa32e7'!I42)+ISNUMBER('3a5a3c04bd9d'!I42)+ISNUMBER('192241189337'!I42)+ISNUMBER('23a0423d7f40'!I42)+ISNUMBER('096252bb3796'!I42)+ISNUMBER(a53d1c7f9645!I42)+ISNUMBER('283d32631463'!I42)+ISNUMBER('1a542cfbf2c5'!I42)+ISNUMBER(cf262786a0e1!I42)+ISNUMBER('4b9efdeaeb40'!I42)+ISNUMBER('66fab14edc4c'!I42)+ISNUMBER(d9a84a7879b5!I42)+ISNUMBER(caf2b28627a3!I42)+ISNUMBER('602e9d1875d1'!I42)+ISNUMBER(f168037f7f37!I42)+ISNUMBER(eb071de1ab08!I42)+ISNUMBER('7b3bd85715a4'!I42)+ISNUMBER(e2a9b537c609!I42)+ISNUMBER(f97457958ce9!I42)+ISNUMBER('281fcc7d7eae'!I42)+ISNUMBER('01454b1cfeba'!I42)+ISNUMBER('79287892b1d7'!I42)+ISNUMBER('1b3f96535b56'!I42),"") | N29: =IF(ISNUMBER('1ae03038ed69'!J42)+ISNUMBER('1572eb063e5c'!J42)+ISNUMBER(b6ea66d78823!J42)+ISNUMBER('6d8dcb722ca4'!J42)+ISNUMBER('9306b30af184'!J42)+ISNUMBER('3b760aaeab13'!J42)+ISNUMBER(b2f4402deaee!J42)+ISNUMBER('1c4d314e87cd'!J42)+ISNUMBER(acd4708edfe6!J42)+ISNUMBER('9a32b1f50fb5'!J42)+ISNUMBER('2df562aa32e7'!J42)+ISNUMBER('3a5a3c04bd9d'!J42)+ISNUMBER('192241189337'!J42)+ISNUMBER('23a0423d7f40'!J42)+ISNUMBER('096252bb3796'!J42)+ISNUMBER(a53d1c7f9645!J42)+ISNUMBER('283d32631463'!J42)+ISNUMBER('1a542cfbf2c5'!J42)+ISNUMBER(cf262786a0e1!J42)+ISNUMBER('4b9efdeaeb40'!J42)+ISNUMBER('66fab14edc4c'!J42)+ISNUMBER(d9a84a7879b5!J42)+ISNUMBER(caf2b28627a3!J42)+ISNUMBER('602e9d1875d1'!J42)+ISNUMBER(f168037f7f37!J42)+ISNUMBER(eb071de1ab08!J42)+ISNUMBER('7b3bd85715a4'!J42)+ISNUMBER(e2a9b537c609!J42)+ISNUMBER(f97457958ce9!J42)+ISNUMBER('281fcc7d7eae'!J42)+ISNUMBER('01454b1cfeba'!J42)+ISNUMBER('79287892b1d7'!J42)+ISNUMBER('1b3f96535b56'!J42),ISNUMBER('1ae03038ed69'!J42)+ISNUMBER('1572eb063e5c'!J42)+ISNUMBER(b6ea66d78823!J42)+ISNUMBER('6d8dcb722ca4'!J42)+ISNUMBER('9306b30af184'!J42)+ISNUMBER('3b760aaeab13'!J42)+ISNUMBER(b2f4402deaee!J42)+ISNUMBER('1c4d314e87cd'!J42)+ISNUMBER(acd4708edfe6!J42)+ISNUMBER('9a32b1f50fb5'!J42)+ISNUMBER('2df562aa32e7'!J42)+ISNUMBER('3a5a3c04bd9d'!J42)+ISNUMBER('192241189337'!J42)+ISNUMBER('23a0423d7f40'!J42)+ISNUMBER('096252bb3796'!J42)+ISNUMBER(a53d1c7f9645!J42)+ISNUMBER('283d32631463'!J42)+ISNUMBER('1a542cfbf2c5'!J42)+ISNUMBER(cf262786a0e1!J42)+ISNUMBER('4b9efdeaeb40'!J42)+ISNUMBER('66fab14edc4c'!J42)+ISNUMBER(d9a84a7879b5!J42)+ISNUMBER(caf2b28627a3!J42)+ISNUMBER('602e9d1875d1'!J42)+ISNUMBER(f168037f7f37!J42)+ISNUMBER(eb071de1ab08!J42)+ISNUMBER('7b3bd85715a4'!J42)+ISNUMBER(e2a9b537c609!J42)+ISNUMBER(f97457958ce9!J42)+ISNUMBER('281fcc7d7eae'!J42)+ISNUMBER('01454b1cfeba'!J42)+ISNUMBER('79287892b1d7'!J42)+ISNUMBER('1b3f96535b56'!J42),"") | ... R29: =IF(ISNUMBER('1ae03038ed69'!N42)+ISNUMBER('1572eb063e5c'!N42)+ISNUMBER(b6ea66d78823!N42)+ISNUMBER('6d8dcb722ca4'!N42)+ISNUMBER('9306b30af184'!N42)+ISNUMBER('3b760aaeab13'!N42)+ISNUMBER(b2f4402deaee!N42)+ISNUMBER('1c4d314e87cd'!N42)+ISNUMBER(acd4708edfe6!N42)+ISNUMBER('9a32b1f50fb5'!N42)+ISNUMBER('2df562aa32e7'!N42)+ISNUMBER('3a5a3c04bd9d'!N42)+ISNUMBER('192241189337'!N42)+ISNUMBER('23a0423d7f40'!N42)+ISNUMBER('096252bb3796'!N42)+ISNUMBER(a53d1c7f9645!N42)+ISNUMBER('283d32631463'!N42)+ISNUMBER('1a542cfbf2c5'!N42)+ISNUMBER(cf262786a0e1!N42)+ISNUMBER('4b9efdeaeb40'!N42)+ISNUMBER('66fab14edc4c'!N42)+ISNUMBER(d9a84a7879b5!N42)+ISNUMBER(caf2b28627a3!N42)+ISNUMBER('602e9d1875d1'!N42)+ISNUMBER(f168037f7f37!N42)+ISNUMBER(eb071de1ab08!N42)+ISNUMBER('7b3bd85715a4'!N42)+ISNUMBER(e2a9b537c609!N42)+ISNUMBER(f97457958ce9!N42)+ISNUMBER('281fcc7d7eae'!N42)+ISNUMBER('01454b1cfeba'!N42)+ISNUMBER('79287892b1d7'!N42)+ISNUMBER('1b3f96535b56'!N42),ISNUMBER('1ae03038ed69'!N42)+ISNUMBER('1572eb063e5c'!N42)+ISNUMBER(b6ea66d78823!N42)+ISNUMBER('6d8dcb722ca4'!N42)+ISNUMBER('9306b30af184'!N42)+ISNUMBER('3b760aaeab13'!N42)+ISNUMBER(b2f4402deaee!N42)+ISNUMBER('1c4d314e87cd'!N42)+ISNUMBER(acd4708edfe6!N42)+ISNUMBER('9a32b1f50fb5'!N42)+ISNUMBER('2df562aa32e7'!N42)+ISNUMBER('3a5a3c04bd9d'!N42)+ISNUMBER('192241189337'!N42)+ISNUMBER('23a0423d7f40'!N42)+ISNUMBER('096252bb3796'!N42)+ISNUMBER(a53d1c7f9645!N42)+ISNUMBER('283d32631463'!N42)+ISNUMBER('1a542cfbf2c5'!N42)+ISNUMBER(cf262786a0e1!N42)+ISNUMBER('4b9efdeaeb40'!N42)+ISNUMBER('66fab14edc4c'!N42)+ISNUMBER(d9a84a7879b5!N42)+ISNUMBER(caf2b28627a3!N42)+ISNUMBER('602e9d1875d1'!N42)+ISNUMBER(f168037f7f37!N42)+ISNUMBER(eb071de1ab08!N42)+ISNUMBER('7b3bd85715a4'!N42)+ISNUMBER(e2a9b537c609!N42)+ISNUMBER(f97457958ce9!N42)+ISNUMBER('281fcc7d7eae'!N42)+ISNUMBER('01454b1cfeba'!N42)+ISNUMBER('79287892b1d7'!N42)+ISNUMBER('1b3f96535b56'!N42),"") -> 2 | U29: 66fab14edc4c | V29: High energy performance standards achieved
F30: =F14 -> Culture and community ide… | G30: =IF(ISNUMBER('1ae03038ed69'!C43)+ISNUMBER('1572eb063e5c'!C43)+ISNUMBER(b6ea66d78823!C43)+ISNUMBER('6d8dcb722ca4'!C43)+ISNUMBER('9306b30af184'!C43)+ISNUMBER('3b760aaeab13'!C43)+ISNUMBER(b2f4402deaee!C43)+ISNUMBER('1c4d314e87cd'!C43)+ISNUMBER(acd4708edfe6!C43)+ISNUMBER('9a32b1f50fb5'!C43)+ISNUMBER('2df562aa32e7'!C43)+ISNUMBER('3a5a3c04bd9d'!C43)+ISNUMBER('192241189337'!C43)+ISNUMBER('23a0423d7f40'!C43)+ISNUMBER('096252bb3796'!C43)+ISNUMBER(a53d1c7f9645!C43)+ISNUMBER('283d32631463'!C43)+ISNUMBER('1a542cfbf2c5'!C43)+ISNUMBER(cf262786a0e1!C43)+ISNUMBER('4b9efdeaeb40'!C43)+ISNUMBER('66fab14edc4c'!C43)+ISNUMBER(d9a84a7879b5!C43)+ISNUMBER(caf2b28627a3!C43)+ISNUMBER('602e9d1875d1'!C43)+ISNUMBER(f168037f7f37!C43)+ISNUMBER(eb071de1ab08!C43)+ISNUMBER('7b3bd85715a4'!C43)+ISNUMBER(e2a9b537c609!C43)+ISNUMBER(f97457958ce9!C43)+ISNUMBER('281fcc7d7eae'!C43)+ISNUMBER('01454b1cfeba'!C43)+ISNUMBER('79287892b1d7'!C43)+ISNUMBER('1b3f96535b56'!C43),ISNUMBER('1ae03038ed69'!C43)+ISNUMBER('1572eb063e5c'!C43)+ISNUMBER(b6ea66d78823!C43)+ISNUMBER('6d8dcb722ca4'!C43)+ISNUMBER('9306b30af184'!C43)+ISNUMBER('3b760aaeab13'!C43)+ISNUMBER(b2f4402deaee!C43)+ISNUMBER('1c4d314e87cd'!C43)+ISNUMBER(acd4708edfe6!C43)+ISNUMBER('9a32b1f50fb5'!C43)+ISNUMBER('2df562aa32e7'!C43)+ISNUMBER('3a5a3c04bd9d'!C43)+ISNUMBER('192241189337'!C43)+ISNUMBER('23a0423d7f40'!C43)+ISNUMBER('096252bb3796'!C43)+ISNUMBER(a53d1c7f9645!C43)+ISNUMBER('283d32631463'!C43)+ISNUMBER('1a542cfbf2c5'!C43)+ISNUMBER(cf262786a0e1!C43)+ISNUMBER('4b9efdeaeb40'!C43)+ISNUMBER('66fab14edc4c'!C43)+ISNUMBER(d9a84a7879b5!C43)+ISNUMBER(caf2b28627a3!C43)+ISNUMBER('602e9d1875d1'!C43)+ISNUMBER(f168037f7f37!C43)+ISNUMBER(eb071de1ab08!C43)+ISNUMBER('7b3bd85715a4'!C43)+ISNUMBER(e2a9b537c609!C43)+ISNUMBER(f97457958ce9!C43)+ISNUMBER('281fcc7d7eae'!C43)+ISNUMBER('01454b1cfeba'!C43)+ISNUMBER('79287892b1d7'!C43)+ISNUMBER('1b3f96535b56'!C43),"") -> 1 | H30: =IF(ISNUMBER('1ae03038ed69'!D43)+ISNUMBER('1572eb063e5c'!D43)+ISNUMBER(b6ea66d78823!D43)+ISNUMBER('6d8dcb722ca4'!D43)+ISNUMBER('9306b30af184'!D43)+ISNUMBER('3b760aaeab13'!D43)+ISNUMBER(b2f4402deaee!D43)+ISNUMBER('1c4d314e87cd'!D43)+ISNUMBER(acd4708edfe6!D43)+ISNUMBER('9a32b1f50fb5'!D43)+ISNUMBER('2df562aa32e7'!D43)+ISNUMBER('3a5a3c04bd9d'!D43)+ISNUMBER('192241189337'!D43)+ISNUMBER('23a0423d7f40'!D43)+ISNUMBER('096252bb3796'!D43)+ISNUMBER(a53d1c7f9645!D43)+ISNUMBER('283d32631463'!D43)+ISNUMBER('1a542cfbf2c5'!D43)+ISNUMBER(cf262786a0e1!D43)+ISNUMBER('4b9efdeaeb40'!D43)+ISNUMBER('66fab14edc4c'!D43)+ISNUMBER(d9a84a7879b5!D43)+ISNUMBER(caf2b28627a3!D43)+ISNUMBER('602e9d1875d1'!D43)+ISNUMBER(f168037f7f37!D43)+ISNUMBER(eb071de1ab08!D43)+ISNUMBER('7b3bd85715a4'!D43)+ISNUMBER(e2a9b537c609!D43)+ISNUMBER(f97457958ce9!D43)+ISNUMBER('281fcc7d7eae'!D43)+ISNUMBER('01454b1cfeba'!D43)+ISNUMBER('79287892b1d7'!D43)+ISNUMBER('1b3f96535b56'!D43),ISNUMBER('1ae03038ed69'!D43)+ISNUMBER('1572eb063e5c'!D43)+ISNUMBER(b6ea66d78823!D43)+ISNUMBER('6d8dcb722ca4'!D43)+ISNUMBER('9306b30af184'!D43)+ISNUMBER('3b760aaeab13'!D43)+ISNUMBER(b2f4402deaee!D43)+ISNUMBER('1c4d314e87cd'!D43)+ISNUMBER(acd4708edfe6!D43)+ISNUMBER('9a32b1f50fb5'!D43)+ISNUMBER('2df562aa32e7'!D43)+ISNUMBER('3a5a3c04bd9d'!D43)+ISNUMBER('192241189337'!D43)+ISNUMBER('23a0423d7f40'!D43)+ISNUMBER('096252bb3796'!D43)+ISNUMBER(a53d1c7f9645!D43)+ISNUMBER('283d32631463'!D43)+ISNUMBER('1a542cfbf2c5'!D43)+ISNUMBER(cf262786a0e1!D43)+ISNUMBER('4b9efdeaeb40'!D43)+ISNUMBER('66fab14edc4c'!D43)+ISNUMBER(d9a84a7879b5!D43)+ISNUMBER(caf2b28627a3!D43)+ISNUMBER('602e9d1875d1'!D43)+ISNUMBER(f168037f7f37!D43)+ISNUMBER(eb071de1ab08!D43)+ISNUMBER('7b3bd85715a4'!D43)+ISNUMBER(e2a9b537c609!D43)+ISNUMBER(f97457958ce9!D43)+ISNUMBER('281fcc7d7eae'!D43)+ISNUMBER('01454b1cfeba'!D43)+ISNUMBER('79287892b1d7'!D43)+ISNUMBER('1b3f96535b56'!D43),"") -> 1 | I30: =IF(ISNUMBER('1ae03038ed69'!E43)+ISNUMBER('1572eb063e5c'!E43)+ISNUMBER(b6ea66d78823!E43)+ISNUMBER('6d8dcb722ca4'!E43)+ISNUMBER('9306b30af184'!E43)+ISNUMBER('3b760aaeab13'!E43)+ISNUMBER(b2f4402deaee!E43)+ISNUMBER('1c4d314e87cd'!E43)+ISNUMBER(acd4708edfe6!E43)+ISNUMBER('9a32b1f50fb5'!E43)+ISNUMBER('2df562aa32e7'!E43)+ISNUMBER('3a5a3c04bd9d'!E43)+ISNUMBER('192241189337'!E43)+ISNUMBER('23a0423d7f40'!E43)+ISNUMBER('096252bb3796'!E43)+ISNUMBER(a53d1c7f9645!E43)+ISNUMBER('283d32631463'!E43)+ISNUMBER('1a542cfbf2c5'!E43)+ISNUMBER(cf262786a0e1!E43)+ISNUMBER('4b9efdeaeb40'!E43)+ISNUMBER('66fab14edc4c'!E43)+ISNUMBER(d9a84a7879b5!E43)+ISNUMBER(caf2b28627a3!E43)+ISNUMBER('602e9d1875d1'!E43)+ISNUMBER(f168037f7f37!E43)+ISNUMBER(eb071de1ab08!E43)+ISNUMBER('7b3bd85715a4'!E43)+ISNUMBER(e2a9b537c609!E43)+ISNUMBER(f97457958ce9!E43)+ISNUMBER('281fcc7d7eae'!E43)+ISNUMBER('01454b1cfeba'!E43)+ISNUMBER('79287892b1d7'!E43)+ISNUMBER('1b3f96535b56'!E43),ISNUMBER('1ae03038ed69'!E43)+ISNUMBER('1572eb063e5c'!E43)+ISNUMBER(b6ea66d78823!E43)+ISNUMBER('6d8dcb722ca4'!E43)+ISNUMBER('9306b30af184'!E43)+ISNUMBER('3b760aaeab13'!E43)+ISNUMBER(b2f4402deaee!E43)+ISNUMBER('1c4d314e87cd'!E43)+ISNUMBER(acd4708edfe6!E43)+ISNUMBER('9a32b1f50fb5'!E43)+ISNUMBER('2df562aa32e7'!E43)+ISNUMBER('3a5a3c04bd9d'!E43)+ISNUMBER('192241189337'!E43)+ISNUMBER('23a0423d7f40'!E43)+ISNUMBER('096252bb3796'!E43)+ISNUMBER(a53d1c7f9645!E43)+ISNUMBER('283d32631463'!E43)+ISNUMBER('1a542cfbf2c5'!E43)+ISNUMBER(cf262786a0e1!E43)+ISNUMBER('4b9efdeaeb40'!E43)+ISNUMBER('66fab14edc4c'!E43)+ISNUMBER(d9a84a7879b5!E43)+ISNUMBER(caf2b28627a3!E43)+ISNUMBER('602e9d1875d1'!E43)+ISNUMBER(f168037f7f37!E43)+ISNUMBER(eb071de1ab08!E43)+ISNUMBER('7b3bd85715a4'!E43)+ISNUMBER(e2a9b537c609!E43)+ISNUMBER(f97457958ce9!E43)+ISNUMBER('281fcc7d7eae'!E43)+ISNUMBER('01454b1cfeba'!E43)+ISNUMBER('79287892b1d7'!E43)+ISNUMBER('1b3f96535b56'!E43),"") -> 1 | J30: =IF(ISNUMBER('1ae03038ed69'!F43)+ISNUMBER('1572eb063e5c'!F43)+ISNUMBER(b6ea66d78823!F43)+ISNUMBER('6d8dcb722ca4'!F43)+ISNUMBER('9306b30af184'!F43)+ISNUMBER('3b760aaeab13'!F43)+ISNUMBER(b2f4402deaee!F43)+ISNUMBER('1c4d314e87cd'!F43)+ISNUMBER(acd4708edfe6!F43)+ISNUMBER('9a32b1f50fb5'!F43)+ISNUMBER('2df562aa32e7'!F43)+ISNUMBER('3a5a3c04bd9d'!F43)+ISNUMBER('192241189337'!F43)+ISNUMBER('23a0423d7f40'!F43)+ISNUMBER('096252bb3796'!F43)+ISNUMBER(a53d1c7f9645!F43)+ISNUMBER('283d32631463'!F43)+ISNUMBER('1a542cfbf2c5'!F43)+ISNUMBER(cf262786a0e1!F43)+ISNUMBER('4b9efdeaeb40'!F43)+ISNUMBER('66fab14edc4c'!F43)+ISNUMBER(d9a84a7879b5!F43)+ISNUMBER(caf2b28627a3!F43)+ISNUMBER('602e9d1875d1'!F43)+ISNUMBER(f168037f7f37!F43)+ISNUMBER(eb071de1ab08!F43)+ISNUMBER('7b3bd85715a4'!F43)+ISNUMBER(e2a9b537c609!F43)+ISNUMBER(f97457958ce9!F43)+ISNUMBER('281fcc7d7eae'!F43)+ISNUMBER('01454b1cfeba'!F43)+ISNUMBER('79287892b1d7'!F43)+ISNUMBER('1b3f96535b56'!F43),ISNUMBER('1ae03038ed69'!F43)+ISNUMBER('1572eb063e5c'!F43)+ISNUMBER(b6ea66d78823!F43)+ISNUMBER('6d8dcb722ca4'!F43)+ISNUMBER('9306b30af184'!F43)+ISNUMBER('3b760aaeab13'!F43)+ISNUMBER(b2f4402deaee!F43)+ISNUMBER('1c4d314e87cd'!F43)+ISNUMBER(acd4708edfe6!F43)+ISNUMBER('9a32b1f50fb5'!F43)+ISNUMBER('2df562aa32e7'!F43)+ISNUMBER('3a5a3c04bd9d'!F43)+ISNUMBER('192241189337'!F43)+ISNUMBER('23a0423d7f40'!F43)+ISNUMBER('096252bb3796'!F43)+ISNUMBER(a53d1c7f9645!F43)+ISNUMBER('283d32631463'!F43)+ISNUMBER('1a542cfbf2c5'!F43)+ISNUMBER(cf262786a0e1!F43)+ISNUMBER('4b9efdeaeb40'!F43)+ISNUMBER('66fab14edc4c'!F43)+ISNUMBER(d9a84a7879b5!F43)+ISNUMBER(caf2b28627a3!F43)+ISNUMBER('602e9d1875d1'!F43)+ISNUMBER(f168037f7f37!F43)+ISNUMBER(eb071de1ab08!F43)+ISNUMBER('7b3bd85715a4'!F43)+ISNUMBER(e2a9b537c609!F43)+ISNUMBER(f97457958ce9!F43)+ISNUMBER('281fcc7d7eae'!F43)+ISNUMBER('01454b1cfeba'!F43)+ISNUMBER('79287892b1d7'!F43)+ISNUMBER('1b3f96535b56'!F43),"") -> 1 | K30: =IF(ISNUMBER('1ae03038ed69'!G43)+ISNUMBER('1572eb063e5c'!G43)+ISNUMBER(b6ea66d78823!G43)+ISNUMBER('6d8dcb722ca4'!G43)+ISNUMBER('9306b30af184'!G43)+ISNUMBER('3b760aaeab13'!G43)+ISNUMBER(b2f4402deaee!G43)+ISNUMBER('1c4d314e87cd'!G43)+ISNUMBER(acd4708edfe6!G43)+ISNUMBER('9a32b1f50fb5'!G43)+ISNUMBER('2df562aa32e7'!G43)+ISNUMBER('3a5a3c04bd9d'!G43)+ISNUMBER('192241189337'!G43)+ISNUMBER('23a0423d7f40'!G43)+ISNUMBER('096252bb3796'!G43)+ISNUMBER(a53d1c7f9645!G43)+ISNUMBER('283d32631463'!G43)+ISNUMBER('1a542cfbf2c5'!G43)+ISNUMBER(cf262786a0e1!G43)+ISNUMBER('4b9efdeaeb40'!G43)+ISNUMBER('66fab14edc4c'!G43)+ISNUMBER(d9a84a7879b5!G43)+ISNUMBER(caf2b28627a3!G43)+ISNUMBER('602e9d1875d1'!G43)+ISNUMBER(f168037f7f37!G43)+ISNUMBER(eb071de1ab08!G43)+ISNUMBER('7b3bd85715a4'!G43)+ISNUMBER(e2a9b537c609!G43)+ISNUMBER(f97457958ce9!G43)+ISNUMBER('281fcc7d7eae'!G43)+ISNUMBER('01454b1cfeba'!G43)+ISNUMBER('79287892b1d7'!G43)+ISNUMBER('1b3f96535b56'!G43),ISNUMBER('1ae03038ed69'!G43)+ISNUMBER('1572eb063e5c'!G43)+ISNUMBER(b6ea66d78823!G43)+ISNUMBER('6d8dcb722ca4'!G43)+ISNUMBER('9306b30af184'!G43)+ISNUMBER('3b760aaeab13'!G43)+ISNUMBER(b2f4402deaee!G43)+ISNUMBER('1c4d314e87cd'!G43)+ISNUMBER(acd4708edfe6!G43)+ISNUMBER('9a32b1f50fb5'!G43)+ISNUMBER('2df562aa32e7'!G43)+ISNUMBER('3a5a3c04bd9d'!G43)+ISNUMBER('192241189337'!G43)+ISNUMBER('23a0423d7f40'!G43)+ISNUMBER('096252bb3796'!G43)+ISNUMBER(a53d1c7f9645!G43)+ISNUMBER('283d32631463'!G43)+ISNUMBER('1a542cfbf2c5'!G43)+ISNUMBER(cf262786a0e1!G43)+ISNUMBER('4b9efdeaeb40'!G43)+ISNUMBER('66fab14edc4c'!G43)+ISNUMBER(d9a84a7879b5!G43)+ISNUMBER(caf2b28627a3!G43)+ISNUMBER('602e9d1875d1'!G43)+ISNUMBER(f168037f7f37!G43)+ISNUMBER(eb071de1ab08!G43)+ISNUMBER('7b3bd85715a4'!G43)+ISNUMBER(e2a9b537c609!G43)+ISNUMBER(f97457958ce9!G43)+ISNUMBER('281fcc7d7eae'!G43)+ISNUMBER('01454b1cfeba'!G43)+ISNUMBER('79287892b1d7'!G43)+ISNUMBER('1b3f96535b56'!G43),"") | L30: =IF(ISNUMBER('1ae03038ed69'!H43)+ISNUMBER('1572eb063e5c'!H43)+ISNUMBER(b6ea66d78823!H43)+ISNUMBER('6d8dcb722ca4'!H43)+ISNUMBER('9306b30af184'!H43)+ISNUMBER('3b760aaeab13'!H43)+ISNUMBER(b2f4402deaee!H43)+ISNUMBER('1c4d314e87cd'!H43)+ISNUMBER(acd4708edfe6!H43)+ISNUMBER('9a32b1f50fb5'!H43)+ISNUMBER('2df562aa32e7'!H43)+ISNUMBER('3a5a3c04bd9d'!H43)+ISNUMBER('192241189337'!H43)+ISNUMBER('23a0423d7f40'!H43)+ISNUMBER('096252bb3796'!H43)+ISNUMBER(a53d1c7f9645!H43)+ISNUMBER('283d32631463'!H43)+ISNUMBER('1a542cfbf2c5'!H43)+ISNUMBER(cf262786a0e1!H43)+ISNUMBER('4b9efdeaeb40'!H43)+ISNUMBER('66fab14edc4c'!H43)+ISNUMBER(d9a84a7879b5!H43)+ISNUMBER(caf2b28627a3!H43)+ISNUMBER('602e9d1875d1'!H43)+ISNUMBER(f168037f7f37!H43)+ISNUMBER(eb071de1ab08!H43)+ISNUMBER('7b3bd85715a4'!H43)+ISNUMBER(e2a9b537c609!H43)+ISNUMBER(f97457958ce9!H43)+ISNUMBER('281fcc7d7eae'!H43)+ISNUMBER('01454b1cfeba'!H43)+ISNUMBER('79287892b1d7'!H43)+ISNUMBER('1b3f96535b56'!H43),ISNUMBER('1ae03038ed69'!H43)+ISNUMBER('1572eb063e5c'!H43)+ISNUMBER(b6ea66d78823!H43)+ISNUMBER('6d8dcb722ca4'!H43)+ISNUMBER('9306b30af184'!H43)+ISNUMBER('3b760aaeab13'!H43)+ISNUMBER(b2f4402deaee!H43)+ISNUMBER('1c4d314e87cd'!H43)+ISNUMBER(acd4708edfe6!H43)+ISNUMBER('9a32b1f50fb5'!H43)+ISNUMBER('2df562aa32e7'!H43)+ISNUMBER('3a5a3c04bd9d'!H43)+ISNUMBER('192241189337'!H43)+ISNUMBER('23a0423d7f40'!H43)+ISNUMBER('096252bb3796'!H43)+ISNUMBER(a53d1c7f9645!H43)+ISNUMBER('283d32631463'!H43)+ISNUMBER('1a542cfbf2c5'!H43)+ISNUMBER(cf262786a0e1!H43)+ISNUMBER('4b9efdeaeb40'!H43)+ISNUMBER('66fab14edc4c'!H43)+ISNUMBER(d9a84a7879b5!H43)+ISNUMBER(caf2b28627a3!H43)+ISNUMBER('602e9d1875d1'!H43)+ISNUMBER(f168037f7f37!H43)+ISNUMBER(eb071de1ab08!H43)+ISNUMBER('7b3bd85715a4'!H43)+ISNUMBER(e2a9b537c609!H43)+ISNUMBER(f97457958ce9!H43)+ISNUMBER('281fcc7d7eae'!H43)+ISNUMBER('01454b1cfeba'!H43)+ISNUMBER('79287892b1d7'!H43)+ISNUMBER('1b3f96535b56'!H43),"") | M30: =IF(ISNUMBER('1ae03038ed69'!I43)+ISNUMBER('1572eb063e5c'!I43)+ISNUMBER(b6ea66d78823!I43)+ISNUMBER('6d8dcb722ca4'!I43)+ISNUMBER('9306b30af184'!I43)+ISNUMBER('3b760aaeab13'!I43)+ISNUMBER(b2f4402deaee!I43)+ISNUMBER('1c4d314e87cd'!I43)+ISNUMBER(acd4708edfe6!I43)+ISNUMBER('9a32b1f50fb5'!I43)+ISNUMBER('2df562aa32e7'!I43)+ISNUMBER('3a5a3c04bd9d'!I43)+ISNUMBER('192241189337'!I43)+ISNUMBER('23a0423d7f40'!I43)+ISNUMBER('096252bb3796'!I43)+ISNUMBER(a53d1c7f9645!I43)+ISNUMBER('283d32631463'!I43)+ISNUMBER('1a542cfbf2c5'!I43)+ISNUMBER(cf262786a0e1!I43)+ISNUMBER('4b9efdeaeb40'!I43)+ISNUMBER('66fab14edc4c'!I43)+ISNUMBER(d9a84a7879b5!I43)+ISNUMBER(caf2b28627a3!I43)+ISNUMBER('602e9d1875d1'!I43)+ISNUMBER(f168037f7f37!I43)+ISNUMBER(eb071de1ab08!I43)+ISNUMBER('7b3bd85715a4'!I43)+ISNUMBER(e2a9b537c609!I43)+ISNUMBER(f97457958ce9!I43)+ISNUMBER('281fcc7d7eae'!I43)+ISNUMBER('01454b1cfeba'!I43)+ISNUMBER('79287892b1d7'!I43)+ISNUMBER('1b3f96535b56'!I43),ISNUMBER('1ae03038ed69'!I43)+ISNUMBER('1572eb063e5c'!I43)+ISNUMBER(b6ea66d78823!I43)+ISNUMBER('6d8dcb722ca4'!I43)+ISNUMBER('9306b30af184'!I43)+ISNUMBER('3b760aaeab13'!I43)+ISNUMBER(b2f4402deaee!I43)+ISNUMBER('1c4d314e87cd'!I43)+ISNUMBER(acd4708edfe6!I43)+ISNUMBER('9a32b1f50fb5'!I43)+ISNUMBER('2df562aa32e7'!I43)+ISNUMBER('3a5a3c04bd9d'!I43)+ISNUMBER('192241189337'!I43)+ISNUMBER('23a0423d7f40'!I43)+ISNUMBER('096252bb3796'!I43)+ISNUMBER(a53d1c7f9645!I43)+ISNUMBER('283d32631463'!I43)+ISNUMBER('1a542cfbf2c5'!I43)+ISNUMBER(cf262786a0e1!I43)+ISNUMBER('4b9efdeaeb40'!I43)+ISNUMBER('66fab14edc4c'!I43)+ISNUMBER(d9a84a7879b5!I43)+ISNUMBER(caf2b28627a3!I43)+ISNUMBER('602e9d1875d1'!I43)+ISNUMBER(f168037f7f37!I43)+ISNUMBER(eb071de1ab08!I43)+ISNUMBER('7b3bd85715a4'!I43)+ISNUMBER(e2a9b537c609!I43)+ISNUMBER(f97457958ce9!I43)+ISNUMBER('281fcc7d7eae'!I43)+ISNUMBER('01454b1cfeba'!I43)+ISNUMBER('79287892b1d7'!I43)+ISNUMBER('1b3f96535b56'!I43),"") | N30: =IF(ISNUMBER('1ae03038ed69'!J43)+ISNUMBER('1572eb063e5c'!J43)+ISNUMBER(b6ea66d78823!J43)+ISNUMBER('6d8dcb722ca4'!J43)+ISNUMBER('9306b30af184'!J43)+ISNUMBER('3b760aaeab13'!J43)+ISNUMBER(b2f4402deaee!J43)+ISNUMBER('1c4d314e87cd'!J43)+ISNUMBER(acd4708edfe6!J43)+ISNUMBER('9a32b1f50fb5'!J43)+ISNUMBER('2df562aa32e7'!J43)+ISNUMBER('3a5a3c04bd9d'!J43)+ISNUMBER('192241189337'!J43)+ISNUMBER('23a0423d7f40'!J43)+ISNUMBER('096252bb3796'!J43)+ISNUMBER(a53d1c7f9645!J43)+ISNUMBER('283d32631463'!J43)+ISNUMBER('1a542cfbf2c5'!J43)+ISNUMBER(cf262786a0e1!J43)+ISNUMBER('4b9efdeaeb40'!J43)+ISNUMBER('66fab14edc4c'!J43)+ISNUMBER(d9a84a7879b5!J43)+ISNUMBER(caf2b28627a3!J43)+ISNUMBER('602e9d1875d1'!J43)+ISNUMBER(f168037f7f37!J43)+ISNUMBER(eb071de1ab08!J43)+ISNUMBER('7b3bd85715a4'!J43)+ISNUMBER(e2a9b537c609!J43)+ISNUMBER(f97457958ce9!J43)+ISNUMBER('281fcc7d7eae'!J43)+ISNUMBER('01454b1cfeba'!J43)+ISNUMBER('79287892b1d7'!J43)+ISNUMBER('1b3f96535b56'!J43),ISNUMBER('1ae03038ed69'!J43)+ISNUMBER('1572eb063e5c'!J43)+ISNUMBER(b6ea66d78823!J43)+ISNUMBER('6d8dcb722ca4'!J43)+ISNUMBER('9306b30af184'!J43)+ISNUMBER('3b760aaeab13'!J43)+ISNUMBER(b2f4402deaee!J43)+ISNUMBER('1c4d314e87cd'!J43)+ISNUMBER(acd4708edfe6!J43)+ISNUMBER('9a32b1f50fb5'!J43)+ISNUMBER('2df562aa32e7'!J43)+ISNUMBER('3a5a3c04bd9d'!J43)+ISNUMBER('192241189337'!J43)+ISNUMBER('23a0423d7f40'!J43)+ISNUMBER('096252bb3796'!J43)+ISNUMBER(a53d1c7f9645!J43)+ISNUMBER('283d32631463'!J43)+ISNUMBER('1a542cfbf2c5'!J43)+ISNUMBER(cf262786a0e1!J43)+ISNUMBER('4b9efdeaeb40'!J43)+ISNUMBER('66fab14edc4c'!J43)+ISNUMBER(d9a84a7879b5!J43)+ISNUMBER(caf2b28627a3!J43)+ISNUMBER('602e9d1875d1'!J43)+ISNUMBER(f168037f7f37!J43)+ISNUMBER(eb071de1ab08!J43)+ISNUMBER('7b3bd85715a4'!J43)+ISNUMBER(e2a9b537c609!J43)+ISNUMBER(f97457958ce9!J43)+ISNUMBER('281fcc7d7eae'!J43)+ISNUMBER('01454b1cfeba'!J43)+ISNUMBER('79287892b1d7'!J43)+ISNUMBER('1b3f96535b56'!J43),"") | ... R30: =IF(ISNUMBER('1ae03038ed69'!N43)+ISNUMBER('1572eb063e5c'!N43)+ISNUMBER(b6ea66d78823!N43)+ISNUMBER('6d8dcb722ca4'!N43)+ISNUMBER('9306b30af184'!N43)+ISNUMBER('3b760aaeab13'!N43)+ISNUMBER(b2f4402deaee!N43)+ISNUMBER('1c4d314e87cd'!N43)+ISNUMBER(acd4708edfe6!N43)+ISNUMBER('9a32b1f50fb5'!N43)+ISNUMBER('2df562aa32e7'!N43)+ISNUMBER('3a5a3c04bd9d'!N43)+ISNUMBER('192241189337'!N43)+ISNUMBER('23a0423d7f40'!N43)+ISNUMBER('096252bb3796'!N43)+ISNUMBER(a53d1c7f9645!N43)+ISNUMBER('283d32631463'!N43)+ISNUMBER('1a542cfbf2c5'!N43)+ISNUMBER(cf262786a0e1!N43)+ISNUMBER('4b9efdeaeb40'!N43)+ISNUMBER('66fab14edc4c'!N43)+ISNUMBER(d9a84a7879b5!N43)+ISNUMBER(caf2b28627a3!N43)+ISNUMBER('602e9d1875d1'!N43)+ISNUMBER(f168037f7f37!N43)+ISNUMBER(eb071de1ab08!N43)+ISNUMBER('7b3bd85715a4'!N43)+ISNUMBER(e2a9b537c609!N43)+ISNUMBER(f97457958ce9!N43)+ISNUMBER('281fcc7d7eae'!N43)+ISNUMBER('01454b1cfeba'!N43)+ISNUMBER('79287892b1d7'!N43)+ISNUMBER('1b3f96535b56'!N43),ISNUMBER('1ae03038ed69'!N43)+ISNUMBER('1572eb063e5c'!N43)+ISNUMBER(b6ea66d78823!N43)+ISNUMBER('6d8dcb722ca4'!N43)+ISNUMBER('9306b30af184'!N43)+ISNUMBER('3b760aaeab13'!N43)+ISNUMBER(b2f4402deaee!N43)+ISNUMBER('1c4d314e87cd'!N43)+ISNUMBER(acd4708edfe6!N43)+ISNUMBER('9a32b1f50fb5'!N43)+ISNUMBER('2df562aa32e7'!N43)+ISNUMBER('3a5a3c04bd9d'!N43)+ISNUMBER('192241189337'!N43)+ISNUMBER('23a0423d7f40'!N43)+ISNUMBER('096252bb3796'!N43)+ISNUMBER(a53d1c7f9645!N43)+ISNUMBER('283d32631463'!N43)+ISNUMBER('1a542cfbf2c5'!N43)+ISNUMBER(cf262786a0e1!N43)+ISNUMBER('4b9efdeaeb40'!N43)+ISNUMBER('66fab14edc4c'!N43)+ISNUMBER(d9a84a7879b5!N43)+ISNUMBER(caf2b28627a3!N43)+ISNUMBER('602e9d1875d1'!N43)+ISNUMBER(f168037f7f37!N43)+ISNUMBER(eb071de1ab08!N43)+ISNUMBER('7b3bd85715a4'!N43)+ISNUMBER(e2a9b537c609!N43)+ISNUMBER(f97457958ce9!N43)+ISNUMBER('281fcc7d7eae'!N43)+ISNUMBER('01454b1cfeba'!N43)+ISNUMBER('79287892b1d7'!N43)+ISNUMBER('1b3f96535b56'!N43),"") | U30: d9a84a7879b5 | V30: Geodesign workshop for campus transformation.
F31: =F15 -> Living together, interdep… | G31: =IF(ISNUMBER('1ae03038ed69'!C44)+ISNUMBER('1572eb063e5c'!C44)+ISNUMBER(b6ea66d78823!C44)+ISNUMBER('6d8dcb722ca4'!C44)+ISNUMBER('9306b30af184'!C44)+ISNUMBER('3b760aaeab13'!C44)+ISNUMBER(b2f4402deaee!C44)+ISNUMBER('1c4d314e87cd'!C44)+ISNUMBER(acd4708edfe6!C44)+ISNUMBER('9a32b1f50fb5'!C44)+ISNUMBER('2df562aa32e7'!C44)+ISNUMBER('3a5a3c04bd9d'!C44)+ISNUMBER('192241189337'!C44)+ISNUMBER('23a0423d7f40'!C44)+ISNUMBER('096252bb3796'!C44)+ISNUMBER(a53d1c7f9645!C44)+ISNUMBER('283d32631463'!C44)+ISNUMBER('1a542cfbf2c5'!C44)+ISNUMBER(cf262786a0e1!C44)+ISNUMBER('4b9efdeaeb40'!C44)+ISNUMBER('66fab14edc4c'!C44)+ISNUMBER(d9a84a7879b5!C44)+ISNUMBER(caf2b28627a3!C44)+ISNUMBER('602e9d1875d1'!C44)+ISNUMBER(f168037f7f37!C44)+ISNUMBER(eb071de1ab08!C44)+ISNUMBER('7b3bd85715a4'!C44)+ISNUMBER(e2a9b537c609!C44)+ISNUMBER(f97457958ce9!C44)+ISNUMBER('281fcc7d7eae'!C44)+ISNUMBER('01454b1cfeba'!C44)+ISNUMBER('79287892b1d7'!C44)+ISNUMBER('1b3f96535b56'!C44),ISNUMBER('1ae03038ed69'!C44)+ISNUMBER('1572eb063e5c'!C44)+ISNUMBER(b6ea66d78823!C44)+ISNUMBER('6d8dcb722ca4'!C44)+ISNUMBER('9306b30af184'!C44)+ISNUMBER('3b760aaeab13'!C44)+ISNUMBER(b2f4402deaee!C44)+ISNUMBER('1c4d314e87cd'!C44)+ISNUMBER(acd4708edfe6!C44)+ISNUMBER('9a32b1f50fb5'!C44)+ISNUMBER('2df562aa32e7'!C44)+ISNUMBER('3a5a3c04bd9d'!C44)+ISNUMBER('192241189337'!C44)+ISNUMBER('23a0423d7f40'!C44)+ISNUMBER('096252bb3796'!C44)+ISNUMBER(a53d1c7f9645!C44)+ISNUMBER('283d32631463'!C44)+ISNUMBER('1a542cfbf2c5'!C44)+ISNUMBER(cf262786a0e1!C44)+ISNUMBER('4b9efdeaeb40'!C44)+ISNUMBER('66fab14edc4c'!C44)+ISNUMBER(d9a84a7879b5!C44)+ISNUMBER(caf2b28627a3!C44)+ISNUMBER('602e9d1875d1'!C44)+ISNUMBER(f168037f7f37!C44)+ISNUMBER(eb071de1ab08!C44)+ISNUMBER('7b3bd85715a4'!C44)+ISNUMBER(e2a9b537c609!C44)+ISNUMBER(f97457958ce9!C44)+ISNUMBER('281fcc7d7eae'!C44)+ISNUMBER('01454b1cfeba'!C44)+ISNUMBER('79287892b1d7'!C44)+ISNUMBER('1b3f96535b56'!C44),"") | H31: =IF(ISNUMBER('1ae03038ed69'!D44)+ISNUMBER('1572eb063e5c'!D44)+ISNUMBER(b6ea66d78823!D44)+ISNUMBER('6d8dcb722ca4'!D44)+ISNUMBER('9306b30af184'!D44)+ISNUMBER('3b760aaeab13'!D44)+ISNUMBER(b2f4402deaee!D44)+ISNUMBER('1c4d314e87cd'!D44)+ISNUMBER(acd4708edfe6!D44)+ISNUMBER('9a32b1f50fb5'!D44)+ISNUMBER('2df562aa32e7'!D44)+ISNUMBER('3a5a3c04bd9d'!D44)+ISNUMBER('192241189337'!D44)+ISNUMBER('23a0423d7f40'!D44)+ISNUMBER('096252bb3796'!D44)+ISNUMBER(a53d1c7f9645!D44)+ISNUMBER('283d32631463'!D44)+ISNUMBER('1a542cfbf2c5'!D44)+ISNUMBER(cf262786a0e1!D44)+ISNUMBER('4b9efdeaeb40'!D44)+ISNUMBER('66fab14edc4c'!D44)+ISNUMBER(d9a84a7879b5!D44)+ISNUMBER(caf2b28627a3!D44)+ISNUMBER('602e9d1875d1'!D44)+ISNUMBER(f168037f7f37!D44)+ISNUMBER(eb071de1ab08!D44)+ISNUMBER('7b3bd85715a4'!D44)+ISNUMBER(e2a9b537c609!D44)+ISNUMBER(f97457958ce9!D44)+ISNUMBER('281fcc7d7eae'!D44)+ISNUMBER('01454b1cfeba'!D44)+ISNUMBER('79287892b1d7'!D44)+ISNUMBER('1b3f96535b56'!D44),ISNUMBER('1ae03038ed69'!D44)+ISNUMBER('1572eb063e5c'!D44)+ISNUMBER(b6ea66d78823!D44)+ISNUMBER('6d8dcb722ca4'!D44)+ISNUMBER('9306b30af184'!D44)+ISNUMBER('3b760aaeab13'!D44)+ISNUMBER(b2f4402deaee!D44)+ISNUMBER('1c4d314e87cd'!D44)+ISNUMBER(acd4708edfe6!D44)+ISNUMBER('9a32b1f50fb5'!D44)+ISNUMBER('2df562aa32e7'!D44)+ISNUMBER('3a5a3c04bd9d'!D44)+ISNUMBER('192241189337'!D44)+ISNUMBER('23a0423d7f40'!D44)+ISNUMBER('096252bb3796'!D44)+ISNUMBER(a53d1c7f9645!D44)+ISNUMBER('283d32631463'!D44)+ISNUMBER('1a542cfbf2c5'!D44)+ISNUMBER(cf262786a0e1!D44)+ISNUMBER('4b9efdeaeb40'!D44)+ISNUMBER('66fab14edc4c'!D44)+ISNUMBER(d9a84a7879b5!D44)+ISNUMBER(caf2b28627a3!D44)+ISNUMBER('602e9d1875d1'!D44)+ISNUMBER(f168037f7f37!D44)+ISNUMBER(eb071de1ab08!D44)+ISNUMBER('7b3bd85715a4'!D44)+ISNUMBER(e2a9b537c609!D44)+ISNUMBER(f97457958ce9!D44)+ISNUMBER('281fcc7d7eae'!D44)+ISNUMBER('01454b1cfeba'!D44)+ISNUMBER('79287892b1d7'!D44)+ISNUMBER('1b3f96535b56'!D44),"") | I31: =IF(ISNUMBER('1ae03038ed69'!E44)+ISNUMBER('1572eb063e5c'!E44)+ISNUMBER(b6ea66d78823!E44)+ISNUMBER('6d8dcb722ca4'!E44)+ISNUMBER('9306b30af184'!E44)+ISNUMBER('3b760aaeab13'!E44)+ISNUMBER(b2f4402deaee!E44)+ISNUMBER('1c4d314e87cd'!E44)+ISNUMBER(acd4708edfe6!E44)+ISNUMBER('9a32b1f50fb5'!E44)+ISNUMBER('2df562aa32e7'!E44)+ISNUMBER('3a5a3c04bd9d'!E44)+ISNUMBER('192241189337'!E44)+ISNUMBER('23a0423d7f40'!E44)+ISNUMBER('096252bb3796'!E44)+ISNUMBER(a53d1c7f9645!E44)+ISNUMBER('283d32631463'!E44)+ISNUMBER('1a542cfbf2c5'!E44)+ISNUMBER(cf262786a0e1!E44)+ISNUMBER('4b9efdeaeb40'!E44)+ISNUMBER('66fab14edc4c'!E44)+ISNUMBER(d9a84a7879b5!E44)+ISNUMBER(caf2b28627a3!E44)+ISNUMBER('602e9d1875d1'!E44)+ISNUMBER(f168037f7f37!E44)+ISNUMBER(eb071de1ab08!E44)+ISNUMBER('7b3bd85715a4'!E44)+ISNUMBER(e2a9b537c609!E44)+ISNUMBER(f97457958ce9!E44)+ISNUMBER('281fcc7d7eae'!E44)+ISNUMBER('01454b1cfeba'!E44)+ISNUMBER('79287892b1d7'!E44)+ISNUMBER('1b3f96535b56'!E44),ISNUMBER('1ae03038ed69'!E44)+ISNUMBER('1572eb063e5c'!E44)+ISNUMBER(b6ea66d78823!E44)+ISNUMBER('6d8dcb722ca4'!E44)+ISNUMBER('9306b30af184'!E44)+ISNUMBER('3b760aaeab13'!E44)+ISNUMBER(b2f4402deaee!E44)+ISNUMBER('1c4d314e87cd'!E44)+ISNUMBER(acd4708edfe6!E44)+ISNUMBER('9a32b1f50fb5'!E44)+ISNUMBER('2df562aa32e7'!E44)+ISNUMBER('3a5a3c04bd9d'!E44)+ISNUMBER('192241189337'!E44)+ISNUMBER('23a0423d7f40'!E44)+ISNUMBER('096252bb3796'!E44)+ISNUMBER(a53d1c7f9645!E44)+ISNUMBER('283d32631463'!E44)+ISNUMBER('1a542cfbf2c5'!E44)+ISNUMBER(cf262786a0e1!E44)+ISNUMBER('4b9efdeaeb40'!E44)+ISNUMBER('66fab14edc4c'!E44)+ISNUMBER(d9a84a7879b5!E44)+ISNUMBER(caf2b28627a3!E44)+ISNUMBER('602e9d1875d1'!E44)+ISNUMBER(f168037f7f37!E44)+ISNUMBER(eb071de1ab08!E44)+ISNUMBER('7b3bd85715a4'!E44)+ISNUMBER(e2a9b537c609!E44)+ISNUMBER(f97457958ce9!E44)+ISNUMBER('281fcc7d7eae'!E44)+ISNUMBER('01454b1cfeba'!E44)+ISNUMBER('79287892b1d7'!E44)+ISNUMBER('1b3f96535b56'!E44),"") | J31: =IF(ISNUMBER('1ae03038ed69'!F44)+ISNUMBER('1572eb063e5c'!F44)+ISNUMBER(b6ea66d78823!F44)+ISNUMBER('6d8dcb722ca4'!F44)+ISNUMBER('9306b30af184'!F44)+ISNUMBER('3b760aaeab13'!F44)+ISNUMBER(b2f4402deaee!F44)+ISNUMBER('1c4d314e87cd'!F44)+ISNUMBER(acd4708edfe6!F44)+ISNUMBER('9a32b1f50fb5'!F44)+ISNUMBER('2df562aa32e7'!F44)+ISNUMBER('3a5a3c04bd9d'!F44)+ISNUMBER('192241189337'!F44)+ISNUMBER('23a0423d7f40'!F44)+ISNUMBER('096252bb3796'!F44)+ISNUMBER(a53d1c7f9645!F44)+ISNUMBER('283d32631463'!F44)+ISNUMBER('1a542cfbf2c5'!F44)+ISNUMBER(cf262786a0e1!F44)+ISNUMBER('4b9efdeaeb40'!F44)+ISNUMBER('66fab14edc4c'!F44)+ISNUMBER(d9a84a7879b5!F44)+ISNUMBER(caf2b28627a3!F44)+ISNUMBER('602e9d1875d1'!F44)+ISNUMBER(f168037f7f37!F44)+ISNUMBER(eb071de1ab08!F44)+ISNUMBER('7b3bd85715a4'!F44)+ISNUMBER(e2a9b537c609!F44)+ISNUMBER(f97457958ce9!F44)+ISNUMBER('281fcc7d7eae'!F44)+ISNUMBER('01454b1cfeba'!F44)+ISNUMBER('79287892b1d7'!F44)+ISNUMBER('1b3f96535b56'!F44),ISNUMBER('1ae03038ed69'!F44)+ISNUMBER('1572eb063e5c'!F44)+ISNUMBER(b6ea66d78823!F44)+ISNUMBER('6d8dcb722ca4'!F44)+ISNUMBER('9306b30af184'!F44)+ISNUMBER('3b760aaeab13'!F44)+ISNUMBER(b2f4402deaee!F44)+ISNUMBER('1c4d314e87cd'!F44)+ISNUMBER(acd4708edfe6!F44)+ISNUMBER('9a32b1f50fb5'!F44)+ISNUMBER('2df562aa32e7'!F44)+ISNUMBER('3a5a3c04bd9d'!F44)+ISNUMBER('192241189337'!F44)+ISNUMBER('23a0423d7f40'!F44)+ISNUMBER('096252bb3796'!F44)+ISNUMBER(a53d1c7f9645!F44)+ISNUMBER('283d32631463'!F44)+ISNUMBER('1a542cfbf2c5'!F44)+ISNUMBER(cf262786a0e1!F44)+ISNUMBER('4b9efdeaeb40'!F44)+ISNUMBER('66fab14edc4c'!F44)+ISNUMBER(d9a84a7879b5!F44)+ISNUMBER(caf2b28627a3!F44)+ISNUMBER('602e9d1875d1'!F44)+ISNUMBER(f168037f7f37!F44)+ISNUMBER(eb071de1ab08!F44)+ISNUMBER('7b3bd85715a4'!F44)+ISNUMBER(e2a9b537c609!F44)+ISNUMBER(f97457958ce9!F44)+ISNUMBER('281fcc7d7eae'!F44)+ISNUMBER('01454b1cfeba'!F44)+ISNUMBER('79287892b1d7'!F44)+ISNUMBER('1b3f96535b56'!F44),"") | K31: =IF(ISNUMBER('1ae03038ed69'!G44)+ISNUMBER('1572eb063e5c'!G44)+ISNUMBER(b6ea66d78823!G44)+ISNUMBER('6d8dcb722ca4'!G44)+ISNUMBER('9306b30af184'!G44)+ISNUMBER('3b760aaeab13'!G44)+ISNUMBER(b2f4402deaee!G44)+ISNUMBER('1c4d314e87cd'!G44)+ISNUMBER(acd4708edfe6!G44)+ISNUMBER('9a32b1f50fb5'!G44)+ISNUMBER('2df562aa32e7'!G44)+ISNUMBER('3a5a3c04bd9d'!G44)+ISNUMBER('192241189337'!G44)+ISNUMBER('23a0423d7f40'!G44)+ISNUMBER('096252bb3796'!G44)+ISNUMBER(a53d1c7f9645!G44)+ISNUMBER('283d32631463'!G44)+ISNUMBER('1a542cfbf2c5'!G44)+ISNUMBER(cf262786a0e1!G44)+ISNUMBER('4b9efdeaeb40'!G44)+ISNUMBER('66fab14edc4c'!G44)+ISNUMBER(d9a84a7879b5!G44)+ISNUMBER(caf2b28627a3!G44)+ISNUMBER('602e9d1875d1'!G44)+ISNUMBER(f168037f7f37!G44)+ISNUMBER(eb071de1ab08!G44)+ISNUMBER('7b3bd85715a4'!G44)+ISNUMBER(e2a9b537c609!G44)+ISNUMBER(f97457958ce9!G44)+ISNUMBER('281fcc7d7eae'!G44)+ISNUMBER('01454b1cfeba'!G44)+ISNUMBER('79287892b1d7'!G44)+ISNUMBER('1b3f96535b56'!G44),ISNUMBER('1ae03038ed69'!G44)+ISNUMBER('1572eb063e5c'!G44)+ISNUMBER(b6ea66d78823!G44)+ISNUMBER('6d8dcb722ca4'!G44)+ISNUMBER('9306b30af184'!G44)+ISNUMBER('3b760aaeab13'!G44)+ISNUMBER(b2f4402deaee!G44)+ISNUMBER('1c4d314e87cd'!G44)+ISNUMBER(acd4708edfe6!G44)+ISNUMBER('9a32b1f50fb5'!G44)+ISNUMBER('2df562aa32e7'!G44)+ISNUMBER('3a5a3c04bd9d'!G44)+ISNUMBER('192241189337'!G44)+ISNUMBER('23a0423d7f40'!G44)+ISNUMBER('096252bb3796'!G44)+ISNUMBER(a53d1c7f9645!G44)+ISNUMBER('283d32631463'!G44)+ISNUMBER('1a542cfbf2c5'!G44)+ISNUMBER(cf262786a0e1!G44)+ISNUMBER('4b9efdeaeb40'!G44)+ISNUMBER('66fab14edc4c'!G44)+ISNUMBER(d9a84a7879b5!G44)+ISNUMBER(caf2b28627a3!G44)+ISNUMBER('602e9d1875d1'!G44)+ISNUMBER(f168037f7f37!G44)+ISNUMBER(eb071de1ab08!G44)+ISNUMBER('7b3bd85715a4'!G44)+ISNUMBER(e2a9b537c609!G44)+ISNUMBER(f97457958ce9!G44)+ISNUMBER('281fcc7d7eae'!G44)+ISNUMBER('01454b1cfeba'!G44)+ISNUMBER('79287892b1d7'!G44)+ISNUMBER('1b3f96535b56'!G44),"") | L31: =IF(ISNUMBER('1ae03038ed69'!H44)+ISNUMBER('1572eb063e5c'!H44)+ISNUMBER(b6ea66d78823!H44)+ISNUMBER('6d8dcb722ca4'!H44)+ISNUMBER('9306b30af184'!H44)+ISNUMBER('3b760aaeab13'!H44)+ISNUMBER(b2f4402deaee!H44)+ISNUMBER('1c4d314e87cd'!H44)+ISNUMBER(acd4708edfe6!H44)+ISNUMBER('9a32b1f50fb5'!H44)+ISNUMBER('2df562aa32e7'!H44)+ISNUMBER('3a5a3c04bd9d'!H44)+ISNUMBER('192241189337'!H44)+ISNUMBER('23a0423d7f40'!H44)+ISNUMBER('096252bb3796'!H44)+ISNUMBER(a53d1c7f9645!H44)+ISNUMBER('283d32631463'!H44)+ISNUMBER('1a542cfbf2c5'!H44)+ISNUMBER(cf262786a0e1!H44)+ISNUMBER('4b9efdeaeb40'!H44)+ISNUMBER('66fab14edc4c'!H44)+ISNUMBER(d9a84a7879b5!H44)+ISNUMBER(caf2b28627a3!H44)+ISNUMBER('602e9d1875d1'!H44)+ISNUMBER(f168037f7f37!H44)+ISNUMBER(eb071de1ab08!H44)+ISNUMBER('7b3bd85715a4'!H44)+ISNUMBER(e2a9b537c609!H44)+ISNUMBER(f97457958ce9!H44)+ISNUMBER('281fcc7d7eae'!H44)+ISNUMBER('01454b1cfeba'!H44)+ISNUMBER('79287892b1d7'!H44)+ISNUMBER('1b3f96535b56'!H44),ISNUMBER('1ae03038ed69'!H44)+ISNUMBER('1572eb063e5c'!H44)+ISNUMBER(b6ea66d78823!H44)+ISNUMBER('6d8dcb722ca4'!H44)+ISNUMBER('9306b30af184'!H44)+ISNUMBER('3b760aaeab13'!H44)+ISNUMBER(b2f4402deaee!H44)+ISNUMBER('1c4d314e87cd'!H44)+ISNUMBER(acd4708edfe6!H44)+ISNUMBER('9a32b1f50fb5'!H44)+ISNUMBER('2df562aa32e7'!H44)+ISNUMBER('3a5a3c04bd9d'!H44)+ISNUMBER('192241189337'!H44)+ISNUMBER('23a0423d7f40'!H44)+ISNUMBER('096252bb3796'!H44)+ISNUMBER(a53d1c7f9645!H44)+ISNUMBER('283d32631463'!H44)+ISNUMBER('1a542cfbf2c5'!H44)+ISNUMBER(cf262786a0e1!H44)+ISNUMBER('4b9efdeaeb40'!H44)+ISNUMBER('66fab14edc4c'!H44)+ISNUMBER(d9a84a7879b5!H44)+ISNUMBER(caf2b28627a3!H44)+ISNUMBER('602e9d1875d1'!H44)+ISNUMBER(f168037f7f37!H44)+ISNUMBER(eb071de1ab08!H44)+ISNUMBER('7b3bd85715a4'!H44)+ISNUMBER(e2a9b537c609!H44)+ISNUMBER(f97457958ce9!H44)+ISNUMBER('281fcc7d7eae'!H44)+ISNUMBER('01454b1cfeba'!H44)+ISNUMBER('79287892b1d7'!H44)+ISNUMBER('1b3f96535b56'!H44),"") | M31: =IF(ISNUMBER('1ae03038ed69'!I44)+ISNUMBER('1572eb063e5c'!I44)+ISNUMBER(b6ea66d78823!I44)+ISNUMBER('6d8dcb722ca4'!I44)+ISNUMBER('9306b30af184'!I44)+ISNUMBER('3b760aaeab13'!I44)+ISNUMBER(b2f4402deaee!I44)+ISNUMBER('1c4d314e87cd'!I44)+ISNUMBER(acd4708edfe6!I44)+ISNUMBER('9a32b1f50fb5'!I44)+ISNUMBER('2df562aa32e7'!I44)+ISNUMBER('3a5a3c04bd9d'!I44)+ISNUMBER('192241189337'!I44)+ISNUMBER('23a0423d7f40'!I44)+ISNUMBER('096252bb3796'!I44)+ISNUMBER(a53d1c7f9645!I44)+ISNUMBER('283d32631463'!I44)+ISNUMBER('1a542cfbf2c5'!I44)+ISNUMBER(cf262786a0e1!I44)+ISNUMBER('4b9efdeaeb40'!I44)+ISNUMBER('66fab14edc4c'!I44)+ISNUMBER(d9a84a7879b5!I44)+ISNUMBER(caf2b28627a3!I44)+ISNUMBER('602e9d1875d1'!I44)+ISNUMBER(f168037f7f37!I44)+ISNUMBER(eb071de1ab08!I44)+ISNUMBER('7b3bd85715a4'!I44)+ISNUMBER(e2a9b537c609!I44)+ISNUMBER(f97457958ce9!I44)+ISNUMBER('281fcc7d7eae'!I44)+ISNUMBER('01454b1cfeba'!I44)+ISNUMBER('79287892b1d7'!I44)+ISNUMBER('1b3f96535b56'!I44),ISNUMBER('1ae03038ed69'!I44)+ISNUMBER('1572eb063e5c'!I44)+ISNUMBER(b6ea66d78823!I44)+ISNUMBER('6d8dcb722ca4'!I44)+ISNUMBER('9306b30af184'!I44)+ISNUMBER('3b760aaeab13'!I44)+ISNUMBER(b2f4402deaee!I44)+ISNUMBER('1c4d314e87cd'!I44)+ISNUMBER(acd4708edfe6!I44)+ISNUMBER('9a32b1f50fb5'!I44)+ISNUMBER('2df562aa32e7'!I44)+ISNUMBER('3a5a3c04bd9d'!I44)+ISNUMBER('192241189337'!I44)+ISNUMBER('23a0423d7f40'!I44)+ISNUMBER('096252bb3796'!I44)+ISNUMBER(a53d1c7f9645!I44)+ISNUMBER('283d32631463'!I44)+ISNUMBER('1a542cfbf2c5'!I44)+ISNUMBER(cf262786a0e1!I44)+ISNUMBER('4b9efdeaeb40'!I44)+ISNUMBER('66fab14edc4c'!I44)+ISNUMBER(d9a84a7879b5!I44)+ISNUMBER(caf2b28627a3!I44)+ISNUMBER('602e9d1875d1'!I44)+ISNUMBER(f168037f7f37!I44)+ISNUMBER(eb071de1ab08!I44)+ISNUMBER('7b3bd85715a4'!I44)+ISNUMBER(e2a9b537c609!I44)+ISNUMBER(f97457958ce9!I44)+ISNUMBER('281fcc7d7eae'!I44)+ISNUMBER('01454b1cfeba'!I44)+ISNUMBER('79287892b1d7'!I44)+ISNUMBER('1b3f96535b56'!I44),"") | N31: =IF(ISNUMBER('1ae03038ed69'!J44)+ISNUMBER('1572eb063e5c'!J44)+ISNUMBER(b6ea66d78823!J44)+ISNUMBER('6d8dcb722ca4'!J44)+ISNUMBER('9306b30af184'!J44)+ISNUMBER('3b760aaeab13'!J44)+ISNUMBER(b2f4402deaee!J44)+ISNUMBER('1c4d314e87cd'!J44)+ISNUMBER(acd4708edfe6!J44)+ISNUMBER('9a32b1f50fb5'!J44)+ISNUMBER('2df562aa32e7'!J44)+ISNUMBER('3a5a3c04bd9d'!J44)+ISNUMBER('192241189337'!J44)+ISNUMBER('23a0423d7f40'!J44)+ISNUMBER('096252bb3796'!J44)+ISNUMBER(a53d1c7f9645!J44)+ISNUMBER('283d32631463'!J44)+ISNUMBER('1a542cfbf2c5'!J44)+ISNUMBER(cf262786a0e1!J44)+ISNUMBER('4b9efdeaeb40'!J44)+ISNUMBER('66fab14edc4c'!J44)+ISNUMBER(d9a84a7879b5!J44)+ISNUMBER(caf2b28627a3!J44)+ISNUMBER('602e9d1875d1'!J44)+ISNUMBER(f168037f7f37!J44)+ISNUMBER(eb071de1ab08!J44)+ISNUMBER('7b3bd85715a4'!J44)+ISNUMBER(e2a9b537c609!J44)+ISNUMBER(f97457958ce9!J44)+ISNUMBER('281fcc7d7eae'!J44)+ISNUMBER('01454b1cfeba'!J44)+ISNUMBER('79287892b1d7'!J44)+ISNUMBER('1b3f96535b56'!J44),ISNUMBER('1ae03038ed69'!J44)+ISNUMBER('1572eb063e5c'!J44)+ISNUMBER(b6ea66d78823!J44)+ISNUMBER('6d8dcb722ca4'!J44)+ISNUMBER('9306b30af184'!J44)+ISNUMBER('3b760aaeab13'!J44)+ISNUMBER(b2f4402deaee!J44)+ISNUMBER('1c4d314e87cd'!J44)+ISNUMBER(acd4708edfe6!J44)+ISNUMBER('9a32b1f50fb5'!J44)+ISNUMBER('2df562aa32e7'!J44)+ISNUMBER('3a5a3c04bd9d'!J44)+ISNUMBER('192241189337'!J44)+ISNUMBER('23a0423d7f40'!J44)+ISNUMBER('096252bb3796'!J44)+ISNUMBER(a53d1c7f9645!J44)+ISNUMBER('283d32631463'!J44)+ISNUMBER('1a542cfbf2c5'!J44)+ISNUMBER(cf262786a0e1!J44)+ISNUMBER('4b9efdeaeb40'!J44)+ISNUMBER('66fab14edc4c'!J44)+ISNUMBER(d9a84a7879b5!J44)+ISNUMBER(caf2b28627a3!J44)+ISNUMBER('602e9d1875d1'!J44)+ISNUMBER(f168037f7f37!J44)+ISNUMBER(eb071de1ab08!J44)+ISNUMBER('7b3bd85715a4'!J44)+ISNUMBER(e2a9b537c609!J44)+ISNUMBER(f97457958ce9!J44)+ISNUMBER('281fcc7d7eae'!J44)+ISNUMBER('01454b1cfeba'!J44)+ISNUMBER('79287892b1d7'!J44)+ISNUMBER('1b3f96535b56'!J44),"") | ... R31: =IF(ISNUMBER('1ae03038ed69'!N44)+ISNUMBER('1572eb063e5c'!N44)+ISNUMBER(b6ea66d78823!N44)+ISNUMBER('6d8dcb722ca4'!N44)+ISNUMBER('9306b30af184'!N44)+ISNUMBER('3b760aaeab13'!N44)+ISNUMBER(b2f4402deaee!N44)+ISNUMBER('1c4d314e87cd'!N44)+ISNUMBER(acd4708edfe6!N44)+ISNUMBER('9a32b1f50fb5'!N44)+ISNUMBER('2df562aa32e7'!N44)+ISNUMBER('3a5a3c04bd9d'!N44)+ISNUMBER('192241189337'!N44)+ISNUMBER('23a0423d7f40'!N44)+ISNUMBER('096252bb3796'!N44)+ISNUMBER(a53d1c7f9645!N44)+ISNUMBER('283d32631463'!N44)+ISNUMBER('1a542cfbf2c5'!N44)+ISNUMBER(cf262786a0e1!N44)+ISNUMBER('4b9efdeaeb40'!N44)+ISNUMBER('66fab14edc4c'!N44)+ISNUMBER(d9a84a7879b5!N44)+ISNUMBER(caf2b28627a3!N44)+ISNUMBER('602e9d1875d1'!N44)+ISNUMBER(f168037f7f37!N44)+ISNUMBER(eb071de1ab08!N44)+ISNUMBER('7b3bd85715a4'!N44)+ISNUMBER(e2a9b537c609!N44)+ISNUMBER(f97457958ce9!N44)+ISNUMBER('281fcc7d7eae'!N44)+ISNUMBER('01454b1cfeba'!N44)+ISNUMBER('79287892b1d7'!N44)+ISNUMBER('1b3f96535b56'!N44),ISNUMBER('1ae03038ed69'!N44)+ISNUMBER('1572eb063e5c'!N44)+ISNUMBER(b6ea66d78823!N44)+ISNUMBER('6d8dcb722ca4'!N44)+ISNUMBER('9306b30af184'!N44)+ISNUMBER('3b760aaeab13'!N44)+ISNUMBER(b2f4402deaee!N44)+ISNUMBER('1c4d314e87cd'!N44)+ISNUMBER(acd4708edfe6!N44)+ISNUMBER('9a32b1f50fb5'!N44)+ISNUMBER('2df562aa32e7'!N44)+ISNUMBER('3a5a3c04bd9d'!N44)+ISNUMBER('192241189337'!N44)+ISNUMBER('23a0423d7f40'!N44)+ISNUMBER('096252bb3796'!N44)+ISNUMBER(a53d1c7f9645!N44)+ISNUMBER('283d32631463'!N44)+ISNUMBER('1a542cfbf2c5'!N44)+ISNUMBER(cf262786a0e1!N44)+ISNUMBER('4b9efdeaeb40'!N44)+ISNUMBER('66fab14edc4c'!N44)+ISNUMBER(d9a84a7879b5!N44)+ISNUMBER(caf2b28627a3!N44)+ISNUMBER('602e9d1875d1'!N44)+ISNUMBER(f168037f7f37!N44)+ISNUMBER(eb071de1ab08!N44)+ISNUMBER('7b3bd85715a4'!N44)+ISNUMBER(e2a9b537c609!N44)+ISNUMBER(f97457958ce9!N44)+ISNUMBER('281fcc7d7eae'!N44)+ISNUMBER('01454b1cfeba'!N44)+ISNUMBER('79287892b1d7'!N44)+ISNUMBER('1b3f96535b56'!N44),"") -> 1 | U31: caf2b28627a3 | V31: Automated analysis for "soft" human-centered criteria.
F32: =F16 -> Economy and sustainable p… | G32: =IF(ISNUMBER('1ae03038ed69'!C45)+ISNUMBER('1572eb063e5c'!C45)+ISNUMBER(b6ea66d78823!C45)+ISNUMBER('6d8dcb722ca4'!C45)+ISNUMBER('9306b30af184'!C45)+ISNUMBER('3b760aaeab13'!C45)+ISNUMBER(b2f4402deaee!C45)+ISNUMBER('1c4d314e87cd'!C45)+ISNUMBER(acd4708edfe6!C45)+ISNUMBER('9a32b1f50fb5'!C45)+ISNUMBER('2df562aa32e7'!C45)+ISNUMBER('3a5a3c04bd9d'!C45)+ISNUMBER('192241189337'!C45)+ISNUMBER('23a0423d7f40'!C45)+ISNUMBER('096252bb3796'!C45)+ISNUMBER(a53d1c7f9645!C45)+ISNUMBER('283d32631463'!C45)+ISNUMBER('1a542cfbf2c5'!C45)+ISNUMBER(cf262786a0e1!C45)+ISNUMBER('4b9efdeaeb40'!C45)+ISNUMBER('66fab14edc4c'!C45)+ISNUMBER(d9a84a7879b5!C45)+ISNUMBER(caf2b28627a3!C45)+ISNUMBER('602e9d1875d1'!C45)+ISNUMBER(f168037f7f37!C45)+ISNUMBER(eb071de1ab08!C45)+ISNUMBER('7b3bd85715a4'!C45)+ISNUMBER(e2a9b537c609!C45)+ISNUMBER(f97457958ce9!C45)+ISNUMBER('281fcc7d7eae'!C45)+ISNUMBER('01454b1cfeba'!C45)+ISNUMBER('79287892b1d7'!C45)+ISNUMBER('1b3f96535b56'!C45),ISNUMBER('1ae03038ed69'!C45)+ISNUMBER('1572eb063e5c'!C45)+ISNUMBER(b6ea66d78823!C45)+ISNUMBER('6d8dcb722ca4'!C45)+ISNUMBER('9306b30af184'!C45)+ISNUMBER('3b760aaeab13'!C45)+ISNUMBER(b2f4402deaee!C45)+ISNUMBER('1c4d314e87cd'!C45)+ISNUMBER(acd4708edfe6!C45)+ISNUMBER('9a32b1f50fb5'!C45)+ISNUMBER('2df562aa32e7'!C45)+ISNUMBER('3a5a3c04bd9d'!C45)+ISNUMBER('192241189337'!C45)+ISNUMBER('23a0423d7f40'!C45)+ISNUMBER('096252bb3796'!C45)+ISNUMBER(a53d1c7f9645!C45)+ISNUMBER('283d32631463'!C45)+ISNUMBER('1a542cfbf2c5'!C45)+ISNUMBER(cf262786a0e1!C45)+ISNUMBER('4b9efdeaeb40'!C45)+ISNUMBER('66fab14edc4c'!C45)+ISNUMBER(d9a84a7879b5!C45)+ISNUMBER(caf2b28627a3!C45)+ISNUMBER('602e9d1875d1'!C45)+ISNUMBER(f168037f7f37!C45)+ISNUMBER(eb071de1ab08!C45)+ISNUMBER('7b3bd85715a4'!C45)+ISNUMBER(e2a9b537c609!C45)+ISNUMBER(f97457958ce9!C45)+ISNUMBER('281fcc7d7eae'!C45)+ISNUMBER('01454b1cfeba'!C45)+ISNUMBER('79287892b1d7'!C45)+ISNUMBER('1b3f96535b56'!C45),"") -> 3 | H32: =IF(ISNUMBER('1ae03038ed69'!D45)+ISNUMBER('1572eb063e5c'!D45)+ISNUMBER(b6ea66d78823!D45)+ISNUMBER('6d8dcb722ca4'!D45)+ISNUMBER('9306b30af184'!D45)+ISNUMBER('3b760aaeab13'!D45)+ISNUMBER(b2f4402deaee!D45)+ISNUMBER('1c4d314e87cd'!D45)+ISNUMBER(acd4708edfe6!D45)+ISNUMBER('9a32b1f50fb5'!D45)+ISNUMBER('2df562aa32e7'!D45)+ISNUMBER('3a5a3c04bd9d'!D45)+ISNUMBER('192241189337'!D45)+ISNUMBER('23a0423d7f40'!D45)+ISNUMBER('096252bb3796'!D45)+ISNUMBER(a53d1c7f9645!D45)+ISNUMBER('283d32631463'!D45)+ISNUMBER('1a542cfbf2c5'!D45)+ISNUMBER(cf262786a0e1!D45)+ISNUMBER('4b9efdeaeb40'!D45)+ISNUMBER('66fab14edc4c'!D45)+ISNUMBER(d9a84a7879b5!D45)+ISNUMBER(caf2b28627a3!D45)+ISNUMBER('602e9d1875d1'!D45)+ISNUMBER(f168037f7f37!D45)+ISNUMBER(eb071de1ab08!D45)+ISNUMBER('7b3bd85715a4'!D45)+ISNUMBER(e2a9b537c609!D45)+ISNUMBER(f97457958ce9!D45)+ISNUMBER('281fcc7d7eae'!D45)+ISNUMBER('01454b1cfeba'!D45)+ISNUMBER('79287892b1d7'!D45)+ISNUMBER('1b3f96535b56'!D45),ISNUMBER('1ae03038ed69'!D45)+ISNUMBER('1572eb063e5c'!D45)+ISNUMBER(b6ea66d78823!D45)+ISNUMBER('6d8dcb722ca4'!D45)+ISNUMBER('9306b30af184'!D45)+ISNUMBER('3b760aaeab13'!D45)+ISNUMBER(b2f4402deaee!D45)+ISNUMBER('1c4d314e87cd'!D45)+ISNUMBER(acd4708edfe6!D45)+ISNUMBER('9a32b1f50fb5'!D45)+ISNUMBER('2df562aa32e7'!D45)+ISNUMBER('3a5a3c04bd9d'!D45)+ISNUMBER('192241189337'!D45)+ISNUMBER('23a0423d7f40'!D45)+ISNUMBER('096252bb3796'!D45)+ISNUMBER(a53d1c7f9645!D45)+ISNUMBER('283d32631463'!D45)+ISNUMBER('1a542cfbf2c5'!D45)+ISNUMBER(cf262786a0e1!D45)+ISNUMBER('4b9efdeaeb40'!D45)+ISNUMBER('66fab14edc4c'!D45)+ISNUMBER(d9a84a7879b5!D45)+ISNUMBER(caf2b28627a3!D45)+ISNUMBER('602e9d1875d1'!D45)+ISNUMBER(f168037f7f37!D45)+ISNUMBER(eb071de1ab08!D45)+ISNUMBER('7b3bd85715a4'!D45)+ISNUMBER(e2a9b537c609!D45)+ISNUMBER(f97457958ce9!D45)+ISNUMBER('281fcc7d7eae'!D45)+ISNUMBER('01454b1cfeba'!D45)+ISNUMBER('79287892b1d7'!D45)+ISNUMBER('1b3f96535b56'!D45),"") | I32: =IF(ISNUMBER('1ae03038ed69'!E45)+ISNUMBER('1572eb063e5c'!E45)+ISNUMBER(b6ea66d78823!E45)+ISNUMBER('6d8dcb722ca4'!E45)+ISNUMBER('9306b30af184'!E45)+ISNUMBER('3b760aaeab13'!E45)+ISNUMBER(b2f4402deaee!E45)+ISNUMBER('1c4d314e87cd'!E45)+ISNUMBER(acd4708edfe6!E45)+ISNUMBER('9a32b1f50fb5'!E45)+ISNUMBER('2df562aa32e7'!E45)+ISNUMBER('3a5a3c04bd9d'!E45)+ISNUMBER('192241189337'!E45)+ISNUMBER('23a0423d7f40'!E45)+ISNUMBER('096252bb3796'!E45)+ISNUMBER(a53d1c7f9645!E45)+ISNUMBER('283d32631463'!E45)+ISNUMBER('1a542cfbf2c5'!E45)+ISNUMBER(cf262786a0e1!E45)+ISNUMBER('4b9efdeaeb40'!E45)+ISNUMBER('66fab14edc4c'!E45)+ISNUMBER(d9a84a7879b5!E45)+ISNUMBER(caf2b28627a3!E45)+ISNUMBER('602e9d1875d1'!E45)+ISNUMBER(f168037f7f37!E45)+ISNUMBER(eb071de1ab08!E45)+ISNUMBER('7b3bd85715a4'!E45)+ISNUMBER(e2a9b537c609!E45)+ISNUMBER(f97457958ce9!E45)+ISNUMBER('281fcc7d7eae'!E45)+ISNUMBER('01454b1cfeba'!E45)+ISNUMBER('79287892b1d7'!E45)+ISNUMBER('1b3f96535b56'!E45),ISNUMBER('1ae03038ed69'!E45)+ISNUMBER('1572eb063e5c'!E45)+ISNUMBER(b6ea66d78823!E45)+ISNUMBER('6d8dcb722ca4'!E45)+ISNUMBER('9306b30af184'!E45)+ISNUMBER('3b760aaeab13'!E45)+ISNUMBER(b2f4402deaee!E45)+ISNUMBER('1c4d314e87cd'!E45)+ISNUMBER(acd4708edfe6!E45)+ISNUMBER('9a32b1f50fb5'!E45)+ISNUMBER('2df562aa32e7'!E45)+ISNUMBER('3a5a3c04bd9d'!E45)+ISNUMBER('192241189337'!E45)+ISNUMBER('23a0423d7f40'!E45)+ISNUMBER('096252bb3796'!E45)+ISNUMBER(a53d1c7f9645!E45)+ISNUMBER('283d32631463'!E45)+ISNUMBER('1a542cfbf2c5'!E45)+ISNUMBER(cf262786a0e1!E45)+ISNUMBER('4b9efdeaeb40'!E45)+ISNUMBER('66fab14edc4c'!E45)+ISNUMBER(d9a84a7879b5!E45)+ISNUMBER(caf2b28627a3!E45)+ISNUMBER('602e9d1875d1'!E45)+ISNUMBER(f168037f7f37!E45)+ISNUMBER(eb071de1ab08!E45)+ISNUMBER('7b3bd85715a4'!E45)+ISNUMBER(e2a9b537c609!E45)+ISNUMBER(f97457958ce9!E45)+ISNUMBER('281fcc7d7eae'!E45)+ISNUMBER('01454b1cfeba'!E45)+ISNUMBER('79287892b1d7'!E45)+ISNUMBER('1b3f96535b56'!E45),"") -> 1 | J32: =IF(ISNUMBER('1ae03038ed69'!F45)+ISNUMBER('1572eb063e5c'!F45)+ISNUMBER(b6ea66d78823!F45)+ISNUMBER('6d8dcb722ca4'!F45)+ISNUMBER('9306b30af184'!F45)+ISNUMBER('3b760aaeab13'!F45)+ISNUMBER(b2f4402deaee!F45)+ISNUMBER('1c4d314e87cd'!F45)+ISNUMBER(acd4708edfe6!F45)+ISNUMBER('9a32b1f50fb5'!F45)+ISNUMBER('2df562aa32e7'!F45)+ISNUMBER('3a5a3c04bd9d'!F45)+ISNUMBER('192241189337'!F45)+ISNUMBER('23a0423d7f40'!F45)+ISNUMBER('096252bb3796'!F45)+ISNUMBER(a53d1c7f9645!F45)+ISNUMBER('283d32631463'!F45)+ISNUMBER('1a542cfbf2c5'!F45)+ISNUMBER(cf262786a0e1!F45)+ISNUMBER('4b9efdeaeb40'!F45)+ISNUMBER('66fab14edc4c'!F45)+ISNUMBER(d9a84a7879b5!F45)+ISNUMBER(caf2b28627a3!F45)+ISNUMBER('602e9d1875d1'!F45)+ISNUMBER(f168037f7f37!F45)+ISNUMBER(eb071de1ab08!F45)+ISNUMBER('7b3bd85715a4'!F45)+ISNUMBER(e2a9b537c609!F45)+ISNUMBER(f97457958ce9!F45)+ISNUMBER('281fcc7d7eae'!F45)+ISNUMBER('01454b1cfeba'!F45)+ISNUMBER('79287892b1d7'!F45)+ISNUMBER('1b3f96535b56'!F45),ISNUMBER('1ae03038ed69'!F45)+ISNUMBER('1572eb063e5c'!F45)+ISNUMBER(b6ea66d78823!F45)+ISNUMBER('6d8dcb722ca4'!F45)+ISNUMBER('9306b30af184'!F45)+ISNUMBER('3b760aaeab13'!F45)+ISNUMBER(b2f4402deaee!F45)+ISNUMBER('1c4d314e87cd'!F45)+ISNUMBER(acd4708edfe6!F45)+ISNUMBER('9a32b1f50fb5'!F45)+ISNUMBER('2df562aa32e7'!F45)+ISNUMBER('3a5a3c04bd9d'!F45)+ISNUMBER('192241189337'!F45)+ISNUMBER('23a0423d7f40'!F45)+ISNUMBER('096252bb3796'!F45)+ISNUMBER(a53d1c7f9645!F45)+ISNUMBER('283d32631463'!F45)+ISNUMBER('1a542cfbf2c5'!F45)+ISNUMBER(cf262786a0e1!F45)+ISNUMBER('4b9efdeaeb40'!F45)+ISNUMBER('66fab14edc4c'!F45)+ISNUMBER(d9a84a7879b5!F45)+ISNUMBER(caf2b28627a3!F45)+ISNUMBER('602e9d1875d1'!F45)+ISNUMBER(f168037f7f37!F45)+ISNUMBER(eb071de1ab08!F45)+ISNUMBER('7b3bd85715a4'!F45)+ISNUMBER(e2a9b537c609!F45)+ISNUMBER(f97457958ce9!F45)+ISNUMBER('281fcc7d7eae'!F45)+ISNUMBER('01454b1cfeba'!F45)+ISNUMBER('79287892b1d7'!F45)+ISNUMBER('1b3f96535b56'!F45),"") -> 1 | K32: =IF(ISNUMBER('1ae03038ed69'!G45)+ISNUMBER('1572eb063e5c'!G45)+ISNUMBER(b6ea66d78823!G45)+ISNUMBER('6d8dcb722ca4'!G45)+ISNUMBER('9306b30af184'!G45)+ISNUMBER('3b760aaeab13'!G45)+ISNUMBER(b2f4402deaee!G45)+ISNUMBER('1c4d314e87cd'!G45)+ISNUMBER(acd4708edfe6!G45)+ISNUMBER('9a32b1f50fb5'!G45)+ISNUMBER('2df562aa32e7'!G45)+ISNUMBER('3a5a3c04bd9d'!G45)+ISNUMBER('192241189337'!G45)+ISNUMBER('23a0423d7f40'!G45)+ISNUMBER('096252bb3796'!G45)+ISNUMBER(a53d1c7f9645!G45)+ISNUMBER('283d32631463'!G45)+ISNUMBER('1a542cfbf2c5'!G45)+ISNUMBER(cf262786a0e1!G45)+ISNUMBER('4b9efdeaeb40'!G45)+ISNUMBER('66fab14edc4c'!G45)+ISNUMBER(d9a84a7879b5!G45)+ISNUMBER(caf2b28627a3!G45)+ISNUMBER('602e9d1875d1'!G45)+ISNUMBER(f168037f7f37!G45)+ISNUMBER(eb071de1ab08!G45)+ISNUMBER('7b3bd85715a4'!G45)+ISNUMBER(e2a9b537c609!G45)+ISNUMBER(f97457958ce9!G45)+ISNUMBER('281fcc7d7eae'!G45)+ISNUMBER('01454b1cfeba'!G45)+ISNUMBER('79287892b1d7'!G45)+ISNUMBER('1b3f96535b56'!G45),ISNUMBER('1ae03038ed69'!G45)+ISNUMBER('1572eb063e5c'!G45)+ISNUMBER(b6ea66d78823!G45)+ISNUMBER('6d8dcb722ca4'!G45)+ISNUMBER('9306b30af184'!G45)+ISNUMBER('3b760aaeab13'!G45)+ISNUMBER(b2f4402deaee!G45)+ISNUMBER('1c4d314e87cd'!G45)+ISNUMBER(acd4708edfe6!G45)+ISNUMBER('9a32b1f50fb5'!G45)+ISNUMBER('2df562aa32e7'!G45)+ISNUMBER('3a5a3c04bd9d'!G45)+ISNUMBER('192241189337'!G45)+ISNUMBER('23a0423d7f40'!G45)+ISNUMBER('096252bb3796'!G45)+ISNUMBER(a53d1c7f9645!G45)+ISNUMBER('283d32631463'!G45)+ISNUMBER('1a542cfbf2c5'!G45)+ISNUMBER(cf262786a0e1!G45)+ISNUMBER('4b9efdeaeb40'!G45)+ISNUMBER('66fab14edc4c'!G45)+ISNUMBER(d9a84a7879b5!G45)+ISNUMBER(caf2b28627a3!G45)+ISNUMBER('602e9d1875d1'!G45)+ISNUMBER(f168037f7f37!G45)+ISNUMBER(eb071de1ab08!G45)+ISNUMBER('7b3bd85715a4'!G45)+ISNUMBER(e2a9b537c609!G45)+ISNUMBER(f97457958ce9!G45)+ISNUMBER('281fcc7d7eae'!G45)+ISNUMBER('01454b1cfeba'!G45)+ISNUMBER('79287892b1d7'!G45)+ISNUMBER('1b3f96535b56'!G45),"") -> 3 | L32: =IF(ISNUMBER('1ae03038ed69'!H45)+ISNUMBER('1572eb063e5c'!H45)+ISNUMBER(b6ea66d78823!H45)+ISNUMBER('6d8dcb722ca4'!H45)+ISNUMBER('9306b30af184'!H45)+ISNUMBER('3b760aaeab13'!H45)+ISNUMBER(b2f4402deaee!H45)+ISNUMBER('1c4d314e87cd'!H45)+ISNUMBER(acd4708edfe6!H45)+ISNUMBER('9a32b1f50fb5'!H45)+ISNUMBER('2df562aa32e7'!H45)+ISNUMBER('3a5a3c04bd9d'!H45)+ISNUMBER('192241189337'!H45)+ISNUMBER('23a0423d7f40'!H45)+ISNUMBER('096252bb3796'!H45)+ISNUMBER(a53d1c7f9645!H45)+ISNUMBER('283d32631463'!H45)+ISNUMBER('1a542cfbf2c5'!H45)+ISNUMBER(cf262786a0e1!H45)+ISNUMBER('4b9efdeaeb40'!H45)+ISNUMBER('66fab14edc4c'!H45)+ISNUMBER(d9a84a7879b5!H45)+ISNUMBER(caf2b28627a3!H45)+ISNUMBER('602e9d1875d1'!H45)+ISNUMBER(f168037f7f37!H45)+ISNUMBER(eb071de1ab08!H45)+ISNUMBER('7b3bd85715a4'!H45)+ISNUMBER(e2a9b537c609!H45)+ISNUMBER(f97457958ce9!H45)+ISNUMBER('281fcc7d7eae'!H45)+ISNUMBER('01454b1cfeba'!H45)+ISNUMBER('79287892b1d7'!H45)+ISNUMBER('1b3f96535b56'!H45),ISNUMBER('1ae03038ed69'!H45)+ISNUMBER('1572eb063e5c'!H45)+ISNUMBER(b6ea66d78823!H45)+ISNUMBER('6d8dcb722ca4'!H45)+ISNUMBER('9306b30af184'!H45)+ISNUMBER('3b760aaeab13'!H45)+ISNUMBER(b2f4402deaee!H45)+ISNUMBER('1c4d314e87cd'!H45)+ISNUMBER(acd4708edfe6!H45)+ISNUMBER('9a32b1f50fb5'!H45)+ISNUMBER('2df562aa32e7'!H45)+ISNUMBER('3a5a3c04bd9d'!H45)+ISNUMBER('192241189337'!H45)+ISNUMBER('23a0423d7f40'!H45)+ISNUMBER('096252bb3796'!H45)+ISNUMBER(a53d1c7f9645!H45)+ISNUMBER('283d32631463'!H45)+ISNUMBER('1a542cfbf2c5'!H45)+ISNUMBER(cf262786a0e1!H45)+ISNUMBER('4b9efdeaeb40'!H45)+ISNUMBER('66fab14edc4c'!H45)+ISNUMBER(d9a84a7879b5!H45)+ISNUMBER(caf2b28627a3!H45)+ISNUMBER('602e9d1875d1'!H45)+ISNUMBER(f168037f7f37!H45)+ISNUMBER(eb071de1ab08!H45)+ISNUMBER('7b3bd85715a4'!H45)+ISNUMBER(e2a9b537c609!H45)+ISNUMBER(f97457958ce9!H45)+ISNUMBER('281fcc7d7eae'!H45)+ISNUMBER('01454b1cfeba'!H45)+ISNUMBER('79287892b1d7'!H45)+ISNUMBER('1b3f96535b56'!H45),"") -> 2 | M32: =IF(ISNUMBER('1ae03038ed69'!I45)+ISNUMBER('1572eb063e5c'!I45)+ISNUMBER(b6ea66d78823!I45)+ISNUMBER('6d8dcb722ca4'!I45)+ISNUMBER('9306b30af184'!I45)+ISNUMBER('3b760aaeab13'!I45)+ISNUMBER(b2f4402deaee!I45)+ISNUMBER('1c4d314e87cd'!I45)+ISNUMBER(acd4708edfe6!I45)+ISNUMBER('9a32b1f50fb5'!I45)+ISNUMBER('2df562aa32e7'!I45)+ISNUMBER('3a5a3c04bd9d'!I45)+ISNUMBER('192241189337'!I45)+ISNUMBER('23a0423d7f40'!I45)+ISNUMBER('096252bb3796'!I45)+ISNUMBER(a53d1c7f9645!I45)+ISNUMBER('283d32631463'!I45)+ISNUMBER('1a542cfbf2c5'!I45)+ISNUMBER(cf262786a0e1!I45)+ISNUMBER('4b9efdeaeb40'!I45)+ISNUMBER('66fab14edc4c'!I45)+ISNUMBER(d9a84a7879b5!I45)+ISNUMBER(caf2b28627a3!I45)+ISNUMBER('602e9d1875d1'!I45)+ISNUMBER(f168037f7f37!I45)+ISNUMBER(eb071de1ab08!I45)+ISNUMBER('7b3bd85715a4'!I45)+ISNUMBER(e2a9b537c609!I45)+ISNUMBER(f97457958ce9!I45)+ISNUMBER('281fcc7d7eae'!I45)+ISNUMBER('01454b1cfeba'!I45)+ISNUMBER('79287892b1d7'!I45)+ISNUMBER('1b3f96535b56'!I45),ISNUMBER('1ae03038ed69'!I45)+ISNUMBER('1572eb063e5c'!I45)+ISNUMBER(b6ea66d78823!I45)+ISNUMBER('6d8dcb722ca4'!I45)+ISNUMBER('9306b30af184'!I45)+ISNUMBER('3b760aaeab13'!I45)+ISNUMBER(b2f4402deaee!I45)+ISNUMBER('1c4d314e87cd'!I45)+ISNUMBER(acd4708edfe6!I45)+ISNUMBER('9a32b1f50fb5'!I45)+ISNUMBER('2df562aa32e7'!I45)+ISNUMBER('3a5a3c04bd9d'!I45)+ISNUMBER('192241189337'!I45)+ISNUMBER('23a0423d7f40'!I45)+ISNUMBER('096252bb3796'!I45)+ISNUMBER(a53d1c7f9645!I45)+ISNUMBER('283d32631463'!I45)+ISNUMBER('1a542cfbf2c5'!I45)+ISNUMBER(cf262786a0e1!I45)+ISNUMBER('4b9efdeaeb40'!I45)+ISNUMBER('66fab14edc4c'!I45)+ISNUMBER(d9a84a7879b5!I45)+ISNUMBER(caf2b28627a3!I45)+ISNUMBER('602e9d1875d1'!I45)+ISNUMBER(f168037f7f37!I45)+ISNUMBER(eb071de1ab08!I45)+ISNUMBER('7b3bd85715a4'!I45)+ISNUMBER(e2a9b537c609!I45)+ISNUMBER(f97457958ce9!I45)+ISNUMBER('281fcc7d7eae'!I45)+ISNUMBER('01454b1cfeba'!I45)+ISNUMBER('79287892b1d7'!I45)+ISNUMBER('1b3f96535b56'!I45),"") -> 8 | N32: =IF(ISNUMBER('1ae03038ed69'!J45)+ISNUMBER('1572eb063e5c'!J45)+ISNUMBER(b6ea66d78823!J45)+ISNUMBER('6d8dcb722ca4'!J45)+ISNUMBER('9306b30af184'!J45)+ISNUMBER('3b760aaeab13'!J45)+ISNUMBER(b2f4402deaee!J45)+ISNUMBER('1c4d314e87cd'!J45)+ISNUMBER(acd4708edfe6!J45)+ISNUMBER('9a32b1f50fb5'!J45)+ISNUMBER('2df562aa32e7'!J45)+ISNUMBER('3a5a3c04bd9d'!J45)+ISNUMBER('192241189337'!J45)+ISNUMBER('23a0423d7f40'!J45)+ISNUMBER('096252bb3796'!J45)+ISNUMBER(a53d1c7f9645!J45)+ISNUMBER('283d32631463'!J45)+ISNUMBER('1a542cfbf2c5'!J45)+ISNUMBER(cf262786a0e1!J45)+ISNUMBER('4b9efdeaeb40'!J45)+ISNUMBER('66fab14edc4c'!J45)+ISNUMBER(d9a84a7879b5!J45)+ISNUMBER(caf2b28627a3!J45)+ISNUMBER('602e9d1875d1'!J45)+ISNUMBER(f168037f7f37!J45)+ISNUMBER(eb071de1ab08!J45)+ISNUMBER('7b3bd85715a4'!J45)+ISNUMBER(e2a9b537c609!J45)+ISNUMBER(f97457958ce9!J45)+ISNUMBER('281fcc7d7eae'!J45)+ISNUMBER('01454b1cfeba'!J45)+ISNUMBER('79287892b1d7'!J45)+ISNUMBER('1b3f96535b56'!J45),ISNUMBER('1ae03038ed69'!J45)+ISNUMBER('1572eb063e5c'!J45)+ISNUMBER(b6ea66d78823!J45)+ISNUMBER('6d8dcb722ca4'!J45)+ISNUMBER('9306b30af184'!J45)+ISNUMBER('3b760aaeab13'!J45)+ISNUMBER(b2f4402deaee!J45)+ISNUMBER('1c4d314e87cd'!J45)+ISNUMBER(acd4708edfe6!J45)+ISNUMBER('9a32b1f50fb5'!J45)+ISNUMBER('2df562aa32e7'!J45)+ISNUMBER('3a5a3c04bd9d'!J45)+ISNUMBER('192241189337'!J45)+ISNUMBER('23a0423d7f40'!J45)+ISNUMBER('096252bb3796'!J45)+ISNUMBER(a53d1c7f9645!J45)+ISNUMBER('283d32631463'!J45)+ISNUMBER('1a542cfbf2c5'!J45)+ISNUMBER(cf262786a0e1!J45)+ISNUMBER('4b9efdeaeb40'!J45)+ISNUMBER('66fab14edc4c'!J45)+ISNUMBER(d9a84a7879b5!J45)+ISNUMBER(caf2b28627a3!J45)+ISNUMBER('602e9d1875d1'!J45)+ISNUMBER(f168037f7f37!J45)+ISNUMBER(eb071de1ab08!J45)+ISNUMBER('7b3bd85715a4'!J45)+ISNUMBER(e2a9b537c609!J45)+ISNUMBER(f97457958ce9!J45)+ISNUMBER('281fcc7d7eae'!J45)+ISNUMBER('01454b1cfeba'!J45)+ISNUMBER('79287892b1d7'!J45)+ISNUMBER('1b3f96535b56'!J45),"") -> 3 | ... R32: =IF(ISNUMBER('1ae03038ed69'!N45)+ISNUMBER('1572eb063e5c'!N45)+ISNUMBER(b6ea66d78823!N45)+ISNUMBER('6d8dcb722ca4'!N45)+ISNUMBER('9306b30af184'!N45)+ISNUMBER('3b760aaeab13'!N45)+ISNUMBER(b2f4402deaee!N45)+ISNUMBER('1c4d314e87cd'!N45)+ISNUMBER(acd4708edfe6!N45)+ISNUMBER('9a32b1f50fb5'!N45)+ISNUMBER('2df562aa32e7'!N45)+ISNUMBER('3a5a3c04bd9d'!N45)+ISNUMBER('192241189337'!N45)+ISNUMBER('23a0423d7f40'!N45)+ISNUMBER('096252bb3796'!N45)+ISNUMBER(a53d1c7f9645!N45)+ISNUMBER('283d32631463'!N45)+ISNUMBER('1a542cfbf2c5'!N45)+ISNUMBER(cf262786a0e1!N45)+ISNUMBER('4b9efdeaeb40'!N45)+ISNUMBER('66fab14edc4c'!N45)+ISNUMBER(d9a84a7879b5!N45)+ISNUMBER(caf2b28627a3!N45)+ISNUMBER('602e9d1875d1'!N45)+ISNUMBER(f168037f7f37!N45)+ISNUMBER(eb071de1ab08!N45)+ISNUMBER('7b3bd85715a4'!N45)+ISNUMBER(e2a9b537c609!N45)+ISNUMBER(f97457958ce9!N45)+ISNUMBER('281fcc7d7eae'!N45)+ISNUMBER('01454b1cfeba'!N45)+ISNUMBER('79287892b1d7'!N45)+ISNUMBER('1b3f96535b56'!N45),ISNUMBER('1ae03038ed69'!N45)+ISNUMBER('1572eb063e5c'!N45)+ISNUMBER(b6ea66d78823!N45)+ISNUMBER('6d8dcb722ca4'!N45)+ISNUMBER('9306b30af184'!N45)+ISNUMBER('3b760aaeab13'!N45)+ISNUMBER(b2f4402deaee!N45)+ISNUMBER('1c4d314e87cd'!N45)+ISNUMBER(acd4708edfe6!N45)+ISNUMBER('9a32b1f50fb5'!N45)+ISNUMBER('2df562aa32e7'!N45)+ISNUMBER('3a5a3c04bd9d'!N45)+ISNUMBER('192241189337'!N45)+ISNUMBER('23a0423d7f40'!N45)+ISNUMBER('096252bb3796'!N45)+ISNUMBER(a53d1c7f9645!N45)+ISNUMBER('283d32631463'!N45)+ISNUMBER('1a542cfbf2c5'!N45)+ISNUMBER(cf262786a0e1!N45)+ISNUMBER('4b9efdeaeb40'!N45)+ISNUMBER('66fab14edc4c'!N45)+ISNUMBER(d9a84a7879b5!N45)+ISNUMBER(caf2b28627a3!N45)+ISNUMBER('602e9d1875d1'!N45)+ISNUMBER(f168037f7f37!N45)+ISNUMBER(eb071de1ab08!N45)+ISNUMBER('7b3bd85715a4'!N45)+ISNUMBER(e2a9b537c609!N45)+ISNUMBER(f97457958ce9!N45)+ISNUMBER('281fcc7d7eae'!N45)+ISNUMBER('01454b1cfeba'!N45)+ISNUMBER('79287892b1d7'!N45)+ISNUMBER('1b3f96535b56'!N45),"") -> 1 | U32: 602e9d1875d1 | V32: Instant LCA metrics feedback in early building design stage
